Workbook

Sheet Start Here
A1: Annual Planning Workbook
A3: How to fill it in (in this order)
A4: 1. Settings | B4: Plan year, focus factor, holidays, and the dropdown lists (roles, statuses, categories).
A5: 2. Objectives | B5: 3–5 objectives for the year with a measurable key result each.
A6: 3. Projects | B6: One row per initiative: objective, priority, size, dates, owners. Effort & labor cost auto-fill.
A7: 4. Team | B7: Everyone supplying capacity, incl. contractors and Open Req placeholders with start dates.
A8: 5. Allocation | B8: Person × project × month as a fraction of their time. This is the heart of resource planning.
A9: 6. Milestones / RAID | B9: Committed dates, decision gates, risks and dependencies.
A10: 7. Review | B10: Dashboard → gaps & over-allocation; Capacity → who's red; Roadmap → sequencing.
A12: Colour legend
A13: Yellow cell, blue text | B13: Input — type here.
A14: Grey cell | B14: Formula — don't overwrite.
A15: Green text | B15: Pulled from another tab.
A17: Planning tips
A18: Plan to ~85% not 100% | B18: The focus factor reserves time for support, meetings and unplanned work.
A19: Use Open Req rows | B19: Plan the work first; the role gap on the Dashboard becomes your hiring ask.
A20: Rank, don't just tag | B20: If demand > capacity, cut from the bottom of P3/P4 — make the trade-off visible in the meeting.
A21: Quarterly re-plan | B21: Re-forecast Allocation each quarter; keep the yearly view as the baseline copy.
A23: Power BI
A24: Data source | B24: Get Data → Excel → pick tables tblProjects, tblTeam, tblAllocation, tblMilestones, tblRAID, tblObjectives.
A25: Allocation months | B25: In Power Query select Jan–Dec on tblAllocation → Unpivot Columns → gives Month/Allocation rows.
A26: Blank rows | B26: Filter each table on its ID/Name column ≠ blank (template rows are pre-built).
A27: Relationships | B27: tblProjects[ID] → tblAllocation[Project ID], tblMilestones, tblRAID; tblTeam[Name] → tblAllocation[Resource].
A29: Sample data | B29: All rows are illustrative examples — overwrite or delete them (keep the formula columns).

Sheet Dashboard
A1: Plan Summary
A2: ="Plan year "&Settings!B3&" • all effort in FTE-months (1 = one person for one month)" -> Plan year 2027 • all effort in FTE-months (1 = one person for one month)
A4: Active projects | B4: P1 projects | C4: Demand (FTE-mo) | D4: Staffed capacity | E4: Open-req capacity | F4: Gap (staffed − demand) | G4: People >100% in any month | H4: Open high risks | I4: Total budget
A5: =COUNTIFS(Projects!A5:A54,"<>",Projects!K5:K54,"<>Cancelled") -> 3 | B5: =COUNTIFS(Projects!E5:E54,"P1",Projects!K5:K54,"<>Cancelled") -> 1 | C5: =SUM(Allocation!Q5:Q204) -> 52.2 | D5: =SUMIFS(Capacity!P70:P129,Capacity!C70:C129,"<>Open Req") -> 49.312212 | E5: =SUMIFS(Capacity!P70:P129,Capacity!C70:C129,"Open Req") -> 7.1964827 | F5: =D5-C5 -> -2.8877877 | G5: =COUNTIF(Capacity!P6:P65,">1.0001") -> 6 | H5: =COUNTIFS(RAID!H5:H104,"High",RAID!L5:L104,"<>Closed") -> 0 | I5: =SUM(Projects!P5:P54) -> 706800
A7: Capacity vs demand by month
A8: Month | B8: Staffed capacity | C8: Open-req capacity | D8: Demand | E8: Gap (staffed − demand) | F8: Team utilization
A9: =Settings!A8 -> 46388 | B9: =SUMIFS(Capacity!D$70:D$129,Capacity!$C$70:$C$129,"<>Open Req") -> 4.0868421 | C9: =SUMIFS(Capacity!D$70:D$129,Capacity!$C$70:$C$129,"Open Req") -> 0 | D9: =SUM(Allocation!E$5:E$204) -> 3.7 | E9: =B9-D9 -> 0.38684211 | F9: =IF(B9+C9=0,"",D9/(B9+C9)) -> 0.90534449
A10: =Settings!A9 -> 46419 | B10: =SUMIFS(Capacity!E$70:E$129,Capacity!$C$70:$C$129,"<>Open Req") -> 4.0868421 | C10: =SUMIFS(Capacity!E$70:E$129,Capacity!$C$70:$C$129,"Open Req") -> 0 | D10: =SUM(Allocation!F$5:F$204) -> 3.7 | E10: =B10-D10 -> 0.38684211 | F10: =IF(B10+C10=0,"",D10/(B10+C10)) -> 0.90534449
A11: =Settings!A10 -> 46447 | B11: =SUMIFS(Capacity!F$70:F$129,Capacity!$C$70:$C$129,"<>Open Req") -> 4.1227273 | C11: =SUMIFS(Capacity!F$70:F$129,Capacity!$C$70:$C$129,"Open Req") -> 0 | D11: =SUM(Allocation!G$5:G$204) -> 4.6 | E11: =B11-D11 -> -0.47727273 | F11: =IF(B11+C11=0,"",D11/(B11+C11)) -> 1.1157663
A12: =Settings!A11 -> 46478 | B12: =SUMIFS(Capacity!G$70:G$129,Capacity!$C$70:$C$129,"<>Open Req") -> 4.1227273 | C12: =SUMIFS(Capacity!G$70:G$129,Capacity!$C$70:$C$129,"Open Req") -> 0.80170455 | D12: =SUM(Allocation!H$5:H$204) -> 5.4 | E12: =B12-D12 -> -1.2772727 | F12: =IF(B12+C12=0,"",D12/(B12+C12)) -> 1.0965732
A13: =Settings!A12 -> 46508 | B13: =SUMIFS(Capacity!H$70:H$129,Capacity!$C$70:$C$129,"<>Open Req") -> 4.1 | C13: =SUMIFS(Capacity!H$70:H$129,Capacity!$C$70:$C$129,"Open Req") -> 0.796875 | D13: =SUM(Allocation!I$5:I$204) -> 4.8 | E13: =B13-D13 -> -0.7 | F13: =IF(B13+C13=0,"",D13/(B13+C13)) -> 0.98021698
A14: =Settings!A13 -> 46539 | B14: =SUMIFS(Capacity!I$70:I$129,Capacity!$C$70:$C$129,"<>Open Req") -> 4.1119048 | C14: =SUMIFS(Capacity!I$70:I$129,Capacity!$C$70:$C$129,"Open Req") -> 0.79940476 | D14: =SUM(Allocation!J$5:J$204) -> 4.8 | E14: =B14-D14 -> -0.68809524 | F14: =IF(B14+C14=0,"",D14/(B14+C14)) -> 0.97733608
A15: =Settings!A14 -> 46569 | B15: =SUMIFS(Capacity!J$70:J$129,Capacity!$C$70:$C$129,"<>Open Req") -> 4.1119048 | C15: =SUMIFS(Capacity!J$70:J$129,Capacity!$C$70:$C$129,"Open Req") -> 0.79940476 | D15: =SUM(Allocation!K$5:K$204) -> 4.8 | E15: =B15-D15 -> -0.68809524 | F15: =IF(B15+C15=0,"",D15/(B15+C15)) -> 0.97733608
A16: =Settings!A15 -> 46600 | B16: =SUMIFS(Capacity!K$70:K$129,Capacity!$C$70:$C$129,"<>Open Req") -> 4.1227273 | C16: =SUMIFS(Capacity!K$70:K$129,Capacity!$C$70:$C$129,"Open Req") -> 0.80170455 | D16: =SUM(Allocation!L$5:L$204) -> 4.8 | E16: =B16-D16 -> -0.67727273 | F16: =IF(B16+C16=0,"",D16/(B16+C16)) -> 0.97473174
A17: =Settings!A16 -> 46631 | B17: =SUMIFS(Capacity!L$70:L$129,Capacity!$C$70:$C$129,"<>Open Req") -> 4.1119048 | C17: =SUMIFS(Capacity!L$70:L$129,Capacity!$C$70:$C$129,"Open Req") -> 0.79940476 | D17: =SUM(Allocation!M$5:M$204) -> 3.9 | E17: =B17-D17 -> 0.21190476 | F17: =IF(B17+C17=0,"",D17/(B17+C17)) -> 0.79408557
A18: =Settings!A17 -> 46661 | B18: =SUMIFS(Capacity!M$70:M$129,Capacity!$C$70:$C$129,"<>Open Req") -> 4.1119048 | C18: =SUMIFS(Capacity!M$70:M$129,Capacity!$C$70:$C$129,"Open Req") -> 0.79940476 | D18: =SUM(Allocation!N$5:N$204) -> 3.9 | E18: =B18-D18 -> 0.21190476 | F18: =IF(B18+C18=0,"",D18/(B18+C18)) -> 0.79408557
A19: =Settings!A18 -> 46692 | B19: =SUMIFS(Capacity!N$70:N$129,Capacity!$C$70:$C$129,"<>Open Req") -> 4.1 | C19: =SUMIFS(Capacity!N$70:N$129,Capacity!$C$70:$C$129,"Open Req") -> 0.796875 | D19: =SUM(Allocation!O$5:O$204) -> 3.9 | E19: =B19-D19 -> 0.2 | F19: =IF(B19+C19=0,"",D19/(B19+C19)) -> 0.79642629
A20: =Settings!A19 -> 46722 | B20: =SUMIFS(Capacity!O$70:O$129,Capacity!$C$70:$C$129,"<>Open Req") -> 4.1227273 | C20: =SUMIFS(Capacity!O$70:O$129,Capacity!$C$70:$C$129,"Open Req") -> 0.80170455 | D20: =SUM(Allocation!P$5:P$204) -> 3.9 | E20: =B20-D20 -> 0.22272727 | F20: =IF(B20+C20=0,"",D20/(B20+C20)) -> 0.79196954
A21: Total | B21: =SUM(B9:B20) -> 49.312212 | C21: =SUM(C9:C20) -> 7.1964827 | D21: =SUM(D9:D20) -> 52.2 | E21: =SUM(E9:E20) -> -2.8877877 | F21: =IF(B21+C21=0,"",D21/(B21+C21)) -> 0.92375165
A24: Supply vs demand by role (annual FTE-months)
A25: Role | B25: Staffed supply | C25: Open-req supply | D25: Demand | E25: Gap (staffed − demand)
A26: =IF(Settings!N8="","",Settings!N8) -> Engineering Manager | B26: =IF(A26="","",SUMIFS(Capacity!$P$70:$P$129,Capacity!$B$70:$B$129,A26,Capacity!$C$70:$C$129,"<>Open Req")) -> 0 | C26: =IF(A26="","",SUMIFS(Capacity!$P$70:$P$129,Capacity!$B$70:$B$129,A26,Capacity!$C$70:$C$129,"Open Req")) -> 0 | D26: =IF(A26="","",SUMIFS(Allocation!$Q$5:$Q$204,Allocation!$B$5:$B$204,A26)) -> 0 | E26: =IF(A26="","",B26-D26) -> 0
A27: =IF(Settings!N9="","",Settings!N9) -> Tech Lead | B27: =IF(A27="","",SUMIFS(Capacity!$P$70:$P$129,Capacity!$B$70:$B$129,A27,Capacity!$C$70:$C$129,"<>Open Req")) -> 8.8299233 | C27: =IF(A27="","",SUMIFS(Capacity!$P$70:$P$129,Capacity!$B$70:$B$129,A27,Capacity!$C$70:$C$129,"Open Req")) -> 0 | D27: =IF(A27="","",SUMIFS(Allocation!$Q$5:$Q$204,Allocation!$B$5:$B$204,A27)) -> 9.2 | E27: =IF(A27="","",B27-D27) -> -0.37007671
A28: =IF(Settings!N10="","",Settings!N10) -> Architect | B28: =IF(A28="","",SUMIFS(Capacity!$P$70:$P$129,Capacity!$B$70:$B$129,A28,Capacity!$C$70:$C$129,"<>Open Req")) -> 0 | C28: =IF(A28="","",SUMIFS(Capacity!$P$70:$P$129,Capacity!$B$70:$B$129,A28,Capacity!$C$70:$C$129,"Open Req")) -> 0 | D28: =IF(A28="","",SUMIFS(Allocation!$Q$5:$Q$204,Allocation!$B$5:$B$204,A28)) -> 0 | E28: =IF(A28="","",B28-D28) -> 0
A29: =IF(Settings!N11="","",Settings!N11) -> Backend Developer | B29: =IF(A29="","",SUMIFS(Capacity!$P$70:$P$129,Capacity!$B$70:$B$129,A29,Capacity!$C$70:$C$129,"<>Open Req")) -> 9.3817935 | C29: =IF(A29="","",SUMIFS(Capacity!$P$70:$P$129,Capacity!$B$70:$B$129,A29,Capacity!$C$70:$C$129,"Open Req")) -> 0 | D29: =IF(A29="","",SUMIFS(Allocation!$Q$5:$Q$204,Allocation!$B$5:$B$204,A29)) -> 8.4 | E29: =IF(A29="","",B29-D29) -> 0.9817935
A30: =IF(Settings!N12="","",Settings!N12) -> Frontend Developer | B30: =IF(A30="","",SUMIFS(Capacity!$P$70:$P$129,Capacity!$B$70:$B$129,A30,Capacity!$C$70:$C$129,"<>Open Req")) -> 10.366832 | C30: =IF(A30="","",SUMIFS(Capacity!$P$70:$P$129,Capacity!$B$70:$B$129,A30,Capacity!$C$70:$C$129,"Open Req")) -> 7.1964827 | D30: =IF(A30="","",SUMIFS(Allocation!$Q$5:$Q$204,Allocation!$B$5:$B$204,A30)) -> 18 | E30: =IF(A30="","",B30-D30) -> -7.6331681
A31: =IF(Settings!N13="","",Settings!N13) -> Full-stack Developer | B31: =IF(A31="","",SUMIFS(Capacity!$P$70:$P$129,Capacity!$B$70:$B$129,A31,Capacity!$C$70:$C$129,"<>Open Req")) -> 10.366832 | C31: =IF(A31="","",SUMIFS(Capacity!$P$70:$P$129,Capacity!$B$70:$B$129,A31,Capacity!$C$70:$C$129,"Open Req")) -> 0 | D31: =IF(A31="","",SUMIFS(Allocation!$Q$5:$Q$204,Allocation!$B$5:$B$204,A31)) -> 7.6 | E31: =IF(A31="","",B31-D31) -> 2.7668319
A32: =IF(Settings!N14="","",Settings!N14) -> QA / SDET | B32: =IF(A32="","",SUMIFS(Capacity!$P$70:$P$129,Capacity!$B$70:$B$129,A32,Capacity!$C$70:$C$129,"<>Open Req")) -> 10.366832 | C32: =IF(A32="","",SUMIFS(Capacity!$P$70:$P$129,Capacity!$B$70:$B$129,A32,Capacity!$C$70:$C$129,"Open Req")) -> 0 | D32: =IF(A32="","",SUMIFS(Allocation!$Q$5:$Q$204,Allocation!$B$5:$B$204,A32)) -> 9 | E32: =IF(A32="","",B32-D32) -> 1.3668319
A33: =IF(Settings!N15="","",Settings!N15) -> DevOps / SRE | B33: =IF(A33="","",SUMIFS(Capacity!$P$70:$P$129,Capacity!$B$70:$B$129,A33,Capacity!$C$70:$C$129,"<>Open Req")) -> 0 | C33: =IF(A33="","",SUMIFS(Capacity!$P$70:$P$129,Capacity!$B$70:$B$129,A33,Capacity!$C$70:$C$129,"Open Req")) -> 0 | D33: =IF(A33="","",SUMIFS(Allocation!$Q$5:$Q$204,Allocation!$B$5:$B$204,A33)) -> 0 | E33: =IF(A33="","",B33-D33) -> 0
A34: =IF(Settings!N16="","",Settings!N16) -> Business Analyst | B34: =IF(A34="","",SUMIFS(Capacity!$P$70:$P$129,Capacity!$B$70:$B$129,A34,Capacity!$C$70:$C$129,"<>Open Req")) -> 0 | C34: =IF(A34="","",SUMIFS(Capacity!$P$70:$P$129,Capacity!$B$70:$B$129,A34,Capacity!$C$70:$C$129,"Open Req")) -> 0 | D34: =IF(A34="","",SUMIFS(Allocation!$Q$5:$Q$204,Allocation!$B$5:$B$204,A34)) -> 0 | E34: =IF(A34="","",B34-D34) -> 0
A35: =IF(Settings!N17="","",Settings!N17) -> Product Owner | B35: =IF(A35="","",SUMIFS(Capacity!$P$70:$P$129,Capacity!$B$70:$B$129,A35,Capacity!$C$70:$C$129,"<>Open Req")) -> 0 | C35: =IF(A35="","",SUMIFS(Capacity!$P$70:$P$129,Capacity!$B$70:$B$129,A35,Capacity!$C$70:$C$129,"Open Req")) -> 0 | D35: =IF(A35="","",SUMIFS(Allocation!$Q$5:$Q$204,Allocation!$B$5:$B$204,A35)) -> 0 | E35: =IF(A35="","",B35-D35) -> 0
A36: =IF(Settings!N18="","",Settings!N18) -> Scrum Master | B36: =IF(A36="","",SUMIFS(Capacity!$P$70:$P$129,Capacity!$B$70:$B$129,A36,Capacity!$C$70:$C$129,"<>Open Req")) -> 0 | C36: =IF(A36="","",SUMIFS(Capacity!$P$70:$P$129,Capacity!$B$70:$B$129,A36,Capacity!$C$70:$C$129,"Open Req")) -> 0 | D36: =IF(A36="","",SUMIFS(Allocation!$Q$5:$Q$204,Allocation!$B$5:$B$204,A36)) -> 0 | E36: =IF(A36="","",B36-D36) -> 0
A37: =IF(Settings!N19="","",Settings!N19) -> UX Designer | B37: =IF(A37="","",SUMIFS(Capacity!$P$70:$P$129,Capacity!$B$70:$B$129,A37,Capacity!$C$70:$C$129,"<>Open Req")) -> 0 | C37: =IF(A37="","",SUMIFS(Capacity!$P$70:$P$129,Capacity!$B$70:$B$129,A37,Capacity!$C$70:$C$129,"Open Req")) -> 0 | D37: =IF(A37="","",SUMIFS(Allocation!$Q$5:$Q$204,Allocation!$B$5:$B$204,A37)) -> 0 | E37: =IF(A37="","",B37-D37) -> 0
A40: Portfolio mix by category
A41: Category | B41: # Projects | C41: FTE-months | D41: % of demand | F41: Status | G41: # Projects
A42: =Settings!J8 -> Run / KTLO | B42: =COUNTIFS(Projects!$D$5:$D$54,A42,Projects!$K$5:$K$54,"<>Cancelled") -> 1 | C42: =SUMIFS(Projects!$M$5:$M$54,Projects!$D$5:$D$54,A42) -> 2.4 | D42: =IF($C$5=0,"",C42/$C$5) -> 0.045977011 | F42: =Settings!H8 -> Proposed | G42: =COUNTIFS(Projects!$K$5:$K$54,F42,Projects!$A$5:$A$54,"<>") -> 1
A43: =Settings!J9 -> Grow | B43: =COUNTIFS(Projects!$D$5:$D$54,A43,Projects!$K$5:$K$54,"<>Cancelled") -> 1 | C43: =SUMIFS(Projects!$M$5:$M$54,Projects!$D$5:$D$54,A43) -> 5.4 | D43: =IF($C$5=0,"",C43/$C$5) -> 0.10344828 | F43: =Settings!H9 -> Approved | G43: =COUNTIFS(Projects!$K$5:$K$54,F43,Projects!$A$5:$A$54,"<>") -> 1
A44: =Settings!J10 -> Transform | B44: =COUNTIFS(Projects!$D$5:$D$54,A44,Projects!$K$5:$K$54,"<>Cancelled") -> 1 | C44: =SUMIFS(Projects!$M$5:$M$54,Projects!$D$5:$D$54,A44) -> 44.4 | D44: =IF($C$5=0,"",C44/$C$5) -> 0.85057471 | F44: =Settings!H10 -> In Progress | G44: =COUNTIFS(Projects!$K$5:$K$54,F44,Projects!$A$5:$A$54,"<>") -> 1
A45: =Settings!J11 -> Compliance / Risk | B45: =COUNTIFS(Projects!$D$5:$D$54,A45,Projects!$K$5:$K$54,"<>Cancelled") -> 0 | C45: =SUMIFS(Projects!$M$5:$M$54,Projects!$D$5:$D$54,A45) -> 0 | D45: =IF($C$5=0,"",C45/$C$5) -> 0 | F45: =Settings!H11 -> On Hold | G45: =COUNTIFS(Projects!$K$5:$K$54,F45,Projects!$A$5:$A$54,"<>") -> 0
A46: =Settings!J12 -> Tech Debt | B46: =COUNTIFS(Projects!$D$5:$D$54,A46,Projects!$K$5:$K$54,"<>Cancelled") -> 0 | C46: =SUMIFS(Projects!$M$5:$M$54,Projects!$D$5:$D$54,A46) -> 0 | D46: =IF($C$5=0,"",C46/$C$5) -> 0 | F46: =Settings!H12 -> Done | G46: =COUNTIFS(Projects!$K$5:$K$54,F46,Projects!$A$5:$A$54,"<>") -> 0
F47: =Settings!H13 -> Cancelled | G47: =COUNTIFS(Projects!$K$5:$K$54,F47,Projects!$A$5:$A$54,"<>") -> 0

Sheet Objectives
A1: Objectives & Key Results
A2: What the year is for. Every project should ladder up to one objective.
A4: Obj ID | B4: Objective | C4: Key Result | D4: Target | E4: Owner | F4: # Projects | G4: Planned FTE-months
A5: O1 | B5: Modernize legacy platforms | C5: Legacy JSP/Struts screens retired | D5: 60% | E5: Siva | F5: =IF(A5="","",COUNTIF(Projects!$C$5:$C$54,A5)) -> 1 | G5: =IF(A5="","",SUMIFS(Projects!$M$5:$M$54,Projects!$C$5:$C$54,A5)) -> 44.4
A6: O2 | B6: Improve reliability & operational visibility | C6: Reduction in P1/P2 incidents YoY | D6: 30% | E6: Siva | F6: =IF(A6="","",COUNTIF(Projects!$C$5:$C$54,A6)) -> 2 | G6: =IF(A6="","",SUMIFS(Projects!$M$5:$M$54,Projects!$C$5:$C$54,A6)) -> 7.8
A7: O3 | B7: Deliver priority business features | C7: Roadmap commitments shipped on time | D7: 90% | F7: =IF(A7="","",COUNTIF(Projects!$C$5:$C$54,A7)) -> 0 | G7: =IF(A7="","",SUMIFS(Projects!$M$5:$M$54,Projects!$C$5:$C$54,A7)) -> 0
F8: =IF(A8="","",COUNTIF(Projects!$C$5:$C$54,A8)) | G8: =IF(A8="","",SUMIFS(Projects!$M$5:$M$54,Projects!$C$5:$C$54,A8))
F9: =IF(A9="","",COUNTIF(Projects!$C$5:$C$54,A9)) | G9: =IF(A9="","",SUMIFS(Projects!$M$5:$M$54,Projects!$C$5:$C$54,A9))
F10: =IF(A10="","",COUNTIF(Projects!$C$5:$C$54,A10)) | G10: =IF(A10="","",SUMIFS(Projects!$M$5:$M$54,Projects!$C$5:$C$54,A10))
F11: =IF(A11="","",COUNTIF(Projects!$C$5:$C$54,A11)) | G11: =IF(A11="","",SUMIFS(Projects!$M$5:$M$54,Projects!$C$5:$C$54,A11))
F12: =IF(A12="","",COUNTIF(Projects!$C$5:$C$54,A12)) | G12: =IF(A12="","",SUMIFS(Projects!$M$5:$M$54,Projects!$C$5:$C$54,A12))
F13: =IF(A13="","",COUNTIF(Projects!$C$5:$C$54,A13)) | G13: =IF(A13="","",SUMIFS(Projects!$M$5:$M$54,Projects!$C$5:$C$54,A13))
F14: =IF(A14="","",COUNTIF(Projects!$C$5:$C$54,A14)) | G14: =IF(A14="","",SUMIFS(Projects!$M$5:$M$54,Projects!$C$5:$C$54,A14))
F15: =IF(A15="","",COUNTIF(Projects!$C$5:$C$54,A15)) | G15: =IF(A15="","",SUMIFS(Projects!$M$5:$M$54,Projects!$C$5:$C$54,A15))
F16: =IF(A16="","",COUNTIF(Projects!$C$5:$C$54,A16)) | G16: =IF(A16="","",SUMIFS(Projects!$M$5:$M$54,Projects!$C$5:$C$54,A16))
F17: =IF(A17="","",COUNTIF(Projects!$C$5:$C$54,A17)) | G17: =IF(A17="","",SUMIFS(Projects!$M$5:$M$54,Projects!$C$5:$C$54,A17))
F18: =IF(A18="","",COUNTIF(Projects!$C$5:$C$54,A18)) | G18: =IF(A18="","",SUMIFS(Projects!$M$5:$M$54,Projects!$C$5:$C$54,A18))
F19: =IF(A19="","",COUNTIF(Projects!$C$5:$C$54,A19)) | G19: =IF(A19="","",SUMIFS(Projects!$M$5:$M$54,Projects!$C$5:$C$54,A19))
... F24: =IF(A24="","",COUNTIF(Projects!$C$5:$C$54,A24)) | G24: =IF(A24="","",SUMIFS(Projects!$M$5:$M$54,Projects!$C$5:$C$54,A24))

Sheet Projects
A1: Project Portfolio
A2: One row per project. Effort and labor cost fill in automatically from the Allocation tab. Sample rows — overwrite.
A4: ID | B4: Project | C4: Objective ID | D4: Category | E4: Priority | F4: Size | G4: Business Owner | H4: Tech Lead | I4: Start | J4: End | K4: Status | L4: RAG | M4: Planned FTE-months | N4: Labor cost | O4: Non-labor budget | P4: Total budget | Q4: Key dependencies | R4: Success measure / notes
A5: P001 | B5: RepApp Angular migration (strangler fig) | C5: O1 | D5: Transform | E5: P1 | F5: XL | H5: Tech Lead 1 | I5: 46391 | J5: 46738 | K5: In Progress | L5: Green | M5: =IF(A5="","",SUMIFS(Allocation!$Q$5:$Q$204,Allocation!$C$5:$C$204,A5)) -> 44.4 | N5: =IF(A5="","",SUMIFS(Allocation!$S$5:$S$204,Allocation!$C$5:$C$204,A5)) -> 580800 | O5: 0 | P5: =IF(A5="","",N5+O5) -> 580800 | Q5: Contractor continuity; TBH Angular dev by Apr | R5: Phase 1–2 screens live; JSP decommission decision by Nov
A6: P002 | B6: Application portfolio dashboard | C6: O2 | D6: Run / KTLO | E6: P2 | F6: M | G6: Manager peer group | H6: Tech Lead 1 | I6: 46398 | J6: 46507 | K6: Approved | L6: Amber | M6: =IF(A6="","",SUMIFS(Allocation!$Q$5:$Q$204,Allocation!$C$5:$C$204,A6)) -> 2.4 | N6: =IF(A6="","",SUMIFS(Allocation!$S$5:$S$204,Allocation!$C$5:$C$204,A6)) -> 34400 | O6: 5000 | P6: =IF(A6="","",N6+O6) -> 39400 | Q6: SNOW + Jira API access | R6: Dashboard adopted by peer managers
A7: P003 | B7: Observability & alerting uplift | C7: O2 | D7: Grow | E7: P2 | F7: M | H7: Java Dev 1 | I7: 46447 | J7: 46630 | K7: Proposed | L7: Green | M7: =IF(A7="","",SUMIFS(Allocation!$Q$5:$Q$204,Allocation!$C$5:$C$204,A7)) -> 5.4 | N7: =IF(A7="","",SUMIFS(Allocation!$S$5:$S$204,Allocation!$C$5:$C$204,A7)) -> 66600 | O7: 20000 | P7: =IF(A7="","",N7+O7) -> 86600 | Q7: Platform team logging standards | R7: Alert baseline in prod; MTTR down
M8: =IF(A8="","",SUMIFS(Allocation!$Q$5:$Q$204,Allocation!$C$5:$C$204,A8)) | N8: =IF(A8="","",SUMIFS(Allocation!$S$5:$S$204,Allocation!$C$5:$C$204,A8)) | P8: =IF(A8="","",N8+O8)
M9: =IF(A9="","",SUMIFS(Allocation!$Q$5:$Q$204,Allocation!$C$5:$C$204,A9)) | N9: =IF(A9="","",SUMIFS(Allocation!$S$5:$S$204,Allocation!$C$5:$C$204,A9)) | P9: =IF(A9="","",N9+O9)
M10: =IF(A10="","",SUMIFS(Allocation!$Q$5:$Q$204,Allocation!$C$5:$C$204,A10)) | N10: =IF(A10="","",SUMIFS(Allocation!$S$5:$S$204,Allocation!$C$5:$C$204,A10)) | P10: =IF(A10="","",N10+O10)
M11: =IF(A11="","",SUMIFS(Allocation!$Q$5:$Q$204,Allocation!$C$5:$C$204,A11)) | N11: =IF(A11="","",SUMIFS(Allocation!$S$5:$S$204,Allocation!$C$5:$C$204,A11)) | P11: =IF(A11="","",N11+O11)
M12: =IF(A12="","",SUMIFS(Allocation!$Q$5:$Q$204,Allocation!$C$5:$C$204,A12)) | N12: =IF(A12="","",SUMIFS(Allocation!$S$5:$S$204,Allocation!$C$5:$C$204,A12)) | P12: =IF(A12="","",N12+O12)
M13: =IF(A13="","",SUMIFS(Allocation!$Q$5:$Q$204,Allocation!$C$5:$C$204,A13)) | N13: =IF(A13="","",SUMIFS(Allocation!$S$5:$S$204,Allocation!$C$5:$C$204,A13)) | P13: =IF(A13="","",N13+O13)
M14: =IF(A14="","",SUMIFS(Allocation!$Q$5:$Q$204,Allocation!$C$5:$C$204,A14)) | N14: =IF(A14="","",SUMIFS(Allocation!$S$5:$S$204,Allocation!$C$5:$C$204,A14)) | P14: =IF(A14="","",N14+O14)
M15: =IF(A15="","",SUMIFS(Allocation!$Q$5:$Q$204,Allocation!$C$5:$C$204,A15)) | N15: =IF(A15="","",SUMIFS(Allocation!$S$5:$S$204,Allocation!$C$5:$C$204,A15)) | P15: =IF(A15="","",N15+O15)
M16: =IF(A16="","",SUMIFS(Allocation!$Q$5:$Q$204,Allocation!$C$5:$C$204,A16)) | N16: =IF(A16="","",SUMIFS(Allocation!$S$5:$S$204,Allocation!$C$5:$C$204,A16)) | P16: =IF(A16="","",N16+O16)
M17: =IF(A17="","",SUMIFS(Allocation!$Q$5:$Q$204,Allocation!$C$5:$C$204,A17)) | N17: =IF(A17="","",SUMIFS(Allocation!$S$5:$S$204,Allocation!$C$5:$C$204,A17)) | P17: =IF(A17="","",N17+O17)
M18: =IF(A18="","",SUMIFS(Allocation!$Q$5:$Q$204,Allocation!$C$5:$C$204,A18)) | N18: =IF(A18="","",SUMIFS(Allocation!$S$5:$S$204,Allocation!$C$5:$C$204,A18)) | P18: =IF(A18="","",N18+O18)
M19: =IF(A19="","",SUMIFS(Allocation!$Q$5:$Q$204,Allocation!$C$5:$C$204,A19)) | N19: =IF(A19="","",SUMIFS(Allocation!$S$5:$S$204,Allocation!$C$5:$C$204,A19)) | P19: =IF(A19="","",N19+O19)
... M54: =IF(A54="","",SUMIFS(Allocation!$Q$5:$Q$204,Allocation!$C$5:$C$204,A54)) | N54: =IF(A54="","",SUMIFS(Allocation!$S$5:$S$204,Allocation!$C$5:$C$204,A54)) | P54: =IF(A54="","",N54+O54)

Sheet Roadmap
A1: Annual Roadmap
A2: Bars come from project Start/End dates; ◆ = milestone in that month. Sorted as entered on Projects.
G4: =Settings!$C$8 -> Q1 | H4: =Settings!$C$9 -> Q1 | I4: =Settings!$C$10 -> Q1 | J4: =Settings!$C$11 -> Q2 | K4: =Settings!$C$12 -> Q2 | L4: =Settings!$C$13 -> Q2 | M4: =Settings!$C$14 -> Q3 | N4: =Settings!$C$15 -> Q3 | O4: =Settings!$C$16 -> Q3 | P4: =Settings!$C$17 -> Q4 | Q4: =Settings!$C$18 -> Q4 | R4: =Settings!$C$19 -> Q4
A5: ID | B5: Project | C5: Priority | D5: Status | E5: Start | F5: End | G5: =Settings!$A$8 -> 46388 | H5: =Settings!$A$9 -> 46419 | I5: =Settings!$A$10 -> 46447 | J5: =Settings!$A$11 -> 46478 | K5: =Settings!$A$12 -> 46508 | L5: =Settings!$A$13 -> 46539 | M5: =Settings!$A$14 -> 46569 | N5: =Settings!$A$15 -> 46600 | O5: =Settings!$A$16 -> 46631 | P5: =Settings!$A$17 -> 46661 | Q5: =Settings!$A$18 -> 46692 | R5: =Settings!$A$19 -> 46722
A6: =IF(Projects!$A5="","",Projects!$A5) -> P001 | B6: =IF(Projects!$A5="","",Projects!$B5) -> RepApp Angular migration (strangler fig) | C6: =IF(Projects!$A5="","",Projects!$E5) -> P1 | D6: =IF(Projects!$A5="","",Projects!$K5) -> In Progress | E6: =IF(Projects!$A5="","",Projects!$I5) -> 46391 | F6: =IF(Projects!$A5="","",Projects!$J5) -> 46738 | G6: =IF($A6="","",IF(COUNTIFS(Milestones!$A$5:$A$104,$A6,Milestones!$D$5:$D$104,">="&G$5,Milestones!$D$5:$D$104,"<="&EOMONTH(G$5,0))>0,"◆","")) | H6: =IF($A6="","",IF(COUNTIFS(Milestones!$A$5:$A$104,$A6,Milestones!$D$5:$D$104,">="&H$5,Milestones!$D$5:$D$104,"<="&EOMONTH(H$5,0))>0,"◆","")) | I6: =IF($A6="","",IF(COUNTIFS(Milestones!$A$5:$A$104,$A6,Milestones!$D$5:$D$104,">="&I$5,Milestones!$D$5:$D$104,"<="&EOMONTH(I$5,0))>0,"◆","")) -> ◆ | J6: =IF($A6="","",IF(COUNTIFS(Milestones!$A$5:$A$104,$A6,Milestones!$D$5:$D$104,">="&J$5,Milestones!$D$5:$D$104,"<="&EOMONTH(J$5,0))>0,"◆","")) | K6: =IF($A6="","",IF(COUNTIFS(Milestones!$A$5:$A$104,$A6,Milestones!$D$5:$D$104,">="&K$5,Milestones!$D$5:$D$104,"<="&EOMONTH(K$5,0))>0,"◆","")) | L6: =IF($A6="","",IF(COUNTIFS(Milestones!$A$5:$A$104,$A6,Milestones!$D$5:$D$104,">="&L$5,Milestones!$D$5:$D$104,"<="&EOMONTH(L$5,0))>0,"◆","")) | M6: =IF($A6="","",IF(COUNTIFS(Milestones!$A$5:$A$104,$A6,Milestones!$D$5:$D$104,">="&M$5,Milestones!$D$5:$D$104,"<="&EOMONTH(M$5,0))>0,"◆","")) -> ◆ | N6: =IF($A6="","",IF(COUNTIFS(Milestones!$A$5:$A$104,$A6,Milestones!$D$5:$D$104,">="&N$5,Milestones!$D$5:$D$104,"<="&EOMONTH(N$5,0))>0,"◆","")) | ... R6: =IF($A6="","",IF(COUNTIFS(Milestones!$A$5:$A$104,$A6,Milestones!$D$5:$D$104,">="&R$5,Milestones!$D$5:$D$104,"<="&EOMONTH(R$5,0))>0,"◆",""))
A7: =IF(Projects!$A6="","",Projects!$A6) -> P002 | B7: =IF(Projects!$A6="","",Projects!$B6) -> Application portfolio dashboard | C7: =IF(Projects!$A6="","",Projects!$E6) -> P2 | D7: =IF(Projects!$A6="","",Projects!$K6) -> Approved | E7: =IF(Projects!$A6="","",Projects!$I6) -> 46398 | F7: =IF(Projects!$A6="","",Projects!$J6) -> 46507 | G7: =IF($A7="","",IF(COUNTIFS(Milestones!$A$5:$A$104,$A7,Milestones!$D$5:$D$104,">="&G$5,Milestones!$D$5:$D$104,"<="&EOMONTH(G$5,0))>0,"◆","")) | H7: =IF($A7="","",IF(COUNTIFS(Milestones!$A$5:$A$104,$A7,Milestones!$D$5:$D$104,">="&H$5,Milestones!$D$5:$D$104,"<="&EOMONTH(H$5,0))>0,"◆","")) | I7: =IF($A7="","",IF(COUNTIFS(Milestones!$A$5:$A$104,$A7,Milestones!$D$5:$D$104,">="&I$5,Milestones!$D$5:$D$104,"<="&EOMONTH(I$5,0))>0,"◆","")) -> ◆ | J7: =IF($A7="","",IF(COUNTIFS(Milestones!$A$5:$A$104,$A7,Milestones!$D$5:$D$104,">="&J$5,Milestones!$D$5:$D$104,"<="&EOMONTH(J$5,0))>0,"◆","")) | K7: =IF($A7="","",IF(COUNTIFS(Milestones!$A$5:$A$104,$A7,Milestones!$D$5:$D$104,">="&K$5,Milestones!$D$5:$D$104,"<="&EOMONTH(K$5,0))>0,"◆","")) | L7: =IF($A7="","",IF(COUNTIFS(Milestones!$A$5:$A$104,$A7,Milestones!$D$5:$D$104,">="&L$5,Milestones!$D$5:$D$104,"<="&EOMONTH(L$5,0))>0,"◆","")) | M7: =IF($A7="","",IF(COUNTIFS(Milestones!$A$5:$A$104,$A7,Milestones!$D$5:$D$104,">="&M$5,Milestones!$D$5:$D$104,"<="&EOMONTH(M$5,0))>0,"◆","")) | N7: =IF($A7="","",IF(COUNTIFS(Milestones!$A$5:$A$104,$A7,Milestones!$D$5:$D$104,">="&N$5,Milestones!$D$5:$D$104,"<="&EOMONTH(N$5,0))>0,"◆","")) | ... R7: =IF($A7="","",IF(COUNTIFS(Milestones!$A$5:$A$104,$A7,Milestones!$D$5:$D$104,">="&R$5,Milestones!$D$5:$D$104,"<="&EOMONTH(R$5,0))>0,"◆",""))
A8: =IF(Projects!$A7="","",Projects!$A7) -> P003 | B8: =IF(Projects!$A7="","",Projects!$B7) -> Observability & alerting uplift | C8: =IF(Projects!$A7="","",Projects!$E7) -> P2 | D8: =IF(Projects!$A7="","",Projects!$K7) -> Proposed | E8: =IF(Projects!$A7="","",Projects!$I7) -> 46447 | F8: =IF(Projects!$A7="","",Projects!$J7) -> 46630 | G8: =IF($A8="","",IF(COUNTIFS(Milestones!$A$5:$A$104,$A8,Milestones!$D$5:$D$104,">="&G$5,Milestones!$D$5:$D$104,"<="&EOMONTH(G$5,0))>0,"◆","")) | H8: =IF($A8="","",IF(COUNTIFS(Milestones!$A$5:$A$104,$A8,Milestones!$D$5:$D$104,">="&H$5,Milestones!$D$5:$D$104,"<="&EOMONTH(H$5,0))>0,"◆","")) | I8: =IF($A8="","",IF(COUNTIFS(Milestones!$A$5:$A$104,$A8,Milestones!$D$5:$D$104,">="&I$5,Milestones!$D$5:$D$104,"<="&EOMONTH(I$5,0))>0,"◆","")) | J8: =IF($A8="","",IF(COUNTIFS(Milestones!$A$5:$A$104,$A8,Milestones!$D$5:$D$104,">="&J$5,Milestones!$D$5:$D$104,"<="&EOMONTH(J$5,0))>0,"◆","")) | K8: =IF($A8="","",IF(COUNTIFS(Milestones!$A$5:$A$104,$A8,Milestones!$D$5:$D$104,">="&K$5,Milestones!$D$5:$D$104,"<="&EOMONTH(K$5,0))>0,"◆","")) | L8: =IF($A8="","",IF(COUNTIFS(Milestones!$A$5:$A$104,$A8,Milestones!$D$5:$D$104,">="&L$5,Milestones!$D$5:$D$104,"<="&EOMONTH(L$5,0))>0,"◆","")) -> ◆ | M8: =IF($A8="","",IF(COUNTIFS(Milestones!$A$5:$A$104,$A8,Milestones!$D$5:$D$104,">="&M$5,Milestones!$D$5:$D$104,"<="&EOMONTH(M$5,0))>0,"◆","")) | N8: =IF($A8="","",IF(COUNTIFS(Milestones!$A$5:$A$104,$A8,Milestones!$D$5:$D$104,">="&N$5,Milestones!$D$5:$D$104,"<="&EOMONTH(N$5,0))>0,"◆","")) | ... R8: =IF($A8="","",IF(COUNTIFS(Milestones!$A$5:$A$104,$A8,Milestones!$D$5:$D$104,">="&R$5,Milestones!$D$5:$D$104,"<="&EOMONTH(R$5,0))>0,"◆",""))
A9: =IF(Projects!$A8="","",Projects!$A8) | B9: =IF(Projects!$A8="","",Projects!$B8) | C9: =IF(Projects!$A8="","",Projects!$E8) | D9: =IF(Projects!$A8="","",Projects!$K8) | E9: =IF(Projects!$A8="","",Projects!$I8) | F9: =IF(Projects!$A8="","",Projects!$J8) | G9: =IF($A9="","",IF(COUNTIFS(Milestones!$A$5:$A$104,$A9,Milestones!$D$5:$D$104,">="&G$5,Milestones!$D$5:$D$104,"<="&EOMONTH(G$5,0))>0,"◆","")) | H9: =IF($A9="","",IF(COUNTIFS(Milestones!$A$5:$A$104,$A9,Milestones!$D$5:$D$104,">="&H$5,Milestones!$D$5:$D$104,"<="&EOMONTH(H$5,0))>0,"◆","")) | I9: =IF($A9="","",IF(COUNTIFS(Milestones!$A$5:$A$104,$A9,Milestones!$D$5:$D$104,">="&I$5,Milestones!$D$5:$D$104,"<="&EOMONTH(I$5,0))>0,"◆","")) | J9: =IF($A9="","",IF(COUNTIFS(Milestones!$A$5:$A$104,$A9,Milestones!$D$5:$D$104,">="&J$5,Milestones!$D$5:$D$104,"<="&EOMONTH(J$5,0))>0,"◆","")) | K9: =IF($A9="","",IF(COUNTIFS(Milestones!$A$5:$A$104,$A9,Milestones!$D$5:$D$104,">="&K$5,Milestones!$D$5:$D$104,"<="&EOMONTH(K$5,0))>0,"◆","")) | L9: =IF($A9="","",IF(COUNTIFS(Milestones!$A$5:$A$104,$A9,Milestones!$D$5:$D$104,">="&L$5,Milestones!$D$5:$D$104,"<="&EOMONTH(L$5,0))>0,"◆","")) | M9: =IF($A9="","",IF(COUNTIFS(Milestones!$A$5:$A$104,$A9,Milestones!$D$5:$D$104,">="&M$5,Milestones!$D$5:$D$104,"<="&EOMONTH(M$5,0))>0,"◆","")) | N9: =IF($A9="","",IF(COUNTIFS(Milestones!$A$5:$A$104,$A9,Milestones!$D$5:$D$104,">="&N$5,Milestones!$D$5:$D$104,"<="&EOMONTH(N$5,0))>0,"◆","")) | ... R9: =IF($A9="","",IF(COUNTIFS(Milestones!$A$5:$A$104,$A9,Milestones!$D$5:$D$104,">="&R$5,Milestones!$D$5:$D$104,"<="&EOMONTH(R$5,0))>0,"◆",""))
A10: =IF(Projects!$A9="","",Projects!$A9) | B10: =IF(Projects!$A9="","",Projects!$B9) | C10: =IF(Projects!$A9="","",Projects!$E9) | D10: =IF(Projects!$A9="","",Projects!$K9) | E10: =IF(Projects!$A9="","",Projects!$I9) | F10: =IF(Projects!$A9="","",Projects!$J9) | G10: =IF($A10="","",IF(COUNTIFS(Milestones!$A$5:$A$104,$A10,Milestones!$D$5:$D$104,">="&G$5,Milestones!$D$5:$D$104,"<="&EOMONTH(G$5,0))>0,"◆","")) | H10: =IF($A10="","",IF(COUNTIFS(Milestones!$A$5:$A$104,$A10,Milestones!$D$5:$D$104,">="&H$5,Milestones!$D$5:$D$104,"<="&EOMONTH(H$5,0))>0,"◆","")) | I10: =IF($A10="","",IF(COUNTIFS(Milestones!$A$5:$A$104,$A10,Milestones!$D$5:$D$104,">="&I$5,Milestones!$D$5:$D$104,"<="&EOMONTH(I$5,0))>0,"◆","")) | J10: =IF($A10="","",IF(COUNTIFS(Milestones!$A$5:$A$104,$A10,Milestones!$D$5:$D$104,">="&J$5,Milestones!$D$5:$D$104,"<="&EOMONTH(J$5,0))>0,"◆","")) | K10: =IF($A10="","",IF(COUNTIFS(Milestones!$A$5:$A$104,$A10,Milestones!$D$5:$D$104,">="&K$5,Milestones!$D$5:$D$104,"<="&EOMONTH(K$5,0))>0,"◆","")) | L10: =IF($A10="","",IF(COUNTIFS(Milestones!$A$5:$A$104,$A10,Milestones!$D$5:$D$104,">="&L$5,Milestones!$D$5:$D$104,"<="&EOMONTH(L$5,0))>0,"◆","")) | M10: =IF($A10="","",IF(COUNTIFS(Milestones!$A$5:$A$104,$A10,Milestones!$D$5:$D$104,">="&M$5,Milestones!$D$5:$D$104,"<="&EOMONTH(M$5,0))>0,"◆","")) | N10: =IF($A10="","",IF(COUNTIFS(Milestones!$A$5:$A$104,$A10,Milestones!$D$5:$D$104,">="&N$5,Milestones!$D$5:$D$104,"<="&EOMONTH(N$5,0))>0,"◆","")) | ... R10: =IF($A10="","",IF(COUNTIFS(Milestones!$A$5:$A$104,$A10,Milestones!$D$5:$D$104,">="&R$5,Milestones!$D$5:$D$104,"<="&EOMONTH(R$5,0))>0,"◆",""))
A11: =IF(Projects!$A10="","",Projects!$A10) | B11: =IF(Projects!$A10="","",Projects!$B10) | C11: =IF(Projects!$A10="","",Projects!$E10) | D11: =IF(Projects!$A10="","",Projects!$K10) | E11: =IF(Projects!$A10="","",Projects!$I10) | F11: =IF(Projects!$A10="","",Projects!$J10) | G11: =IF($A11="","",IF(COUNTIFS(Milestones!$A$5:$A$104,$A11,Milestones!$D$5:$D$104,">="&G$5,Milestones!$D$5:$D$104,"<="&EOMONTH(G$5,0))>0,"◆","")) | H11: =IF($A11="","",IF(COUNTIFS(Milestones!$A$5:$A$104,$A11,Milestones!$D$5:$D$104,">="&H$5,Milestones!$D$5:$D$104,"<="&EOMONTH(H$5,0))>0,"◆","")) | I11: =IF($A11="","",IF(COUNTIFS(Milestones!$A$5:$A$104,$A11,Milestones!$D$5:$D$104,">="&I$5,Milestones!$D$5:$D$104,"<="&EOMONTH(I$5,0))>0,"◆","")) | J11: =IF($A11="","",IF(COUNTIFS(Milestones!$A$5:$A$104,$A11,Milestones!$D$5:$D$104,">="&J$5,Milestones!$D$5:$D$104,"<="&EOMONTH(J$5,0))>0,"◆","")) | K11: =IF($A11="","",IF(COUNTIFS(Milestones!$A$5:$A$104,$A11,Milestones!$D$5:$D$104,">="&K$5,Milestones!$D$5:$D$104,"<="&EOMONTH(K$5,0))>0,"◆","")) | L11: =IF($A11="","",IF(COUNTIFS(Milestones!$A$5:$A$104,$A11,Milestones!$D$5:$D$104,">="&L$5,Milestones!$D$5:$D$104,"<="&EOMONTH(L$5,0))>0,"◆","")) | M11: =IF($A11="","",IF(COUNTIFS(Milestones!$A$5:$A$104,$A11,Milestones!$D$5:$D$104,">="&M$5,Milestones!$D$5:$D$104,"<="&EOMONTH(M$5,0))>0,"◆","")) | N11: =IF($A11="","",IF(COUNTIFS(Milestones!$A$5:$A$104,$A11,Milestones!$D$5:$D$104,">="&N$5,Milestones!$D$5:$D$104,"<="&EOMONTH(N$5,0))>0,"◆","")) | ... R11: =IF($A11="","",IF(COUNTIFS(Milestones!$A$5:$A$104,$A11,Milestones!$D$5:$D$104,">="&R$5,Milestones!$D$5:$D$104,"<="&EOMONTH(R$5,0))>0,"◆",""))
A12: =IF(Projects!$A11="","",Projects!$A11) | B12: =IF(Projects!$A11="","",Projects!$B11) | C12: =IF(Projects!$A11="","",Projects!$E11) | D12: =IF(Projects!$A11="","",Projects!$K11) | E12: =IF(Projects!$A11="","",Projects!$I11) | F12: =IF(Projects!$A11="","",Projects!$J11) | G12: =IF($A12="","",IF(COUNTIFS(Milestones!$A$5:$A$104,$A12,Milestones!$D$5:$D$104,">="&G$5,Milestones!$D$5:$D$104,"<="&EOMONTH(G$5,0))>0,"◆","")) | H12: =IF($A12="","",IF(COUNTIFS(Milestones!$A$5:$A$104,$A12,Milestones!$D$5:$D$104,">="&H$5,Milestones!$D$5:$D$104,"<="&EOMONTH(H$5,0))>0,"◆","")) | I12: =IF($A12="","",IF(COUNTIFS(Milestones!$A$5:$A$104,$A12,Milestones!$D$5:$D$104,">="&I$5,Milestones!$D$5:$D$104,"<="&EOMONTH(I$5,0))>0,"◆","")) | J12: =IF($A12="","",IF(COUNTIFS(Milestones!$A$5:$A$104,$A12,Milestones!$D$5:$D$104,">="&J$5,Milestones!$D$5:$D$104,"<="&EOMONTH(J$5,0))>0,"◆","")) | K12: =IF($A12="","",IF(COUNTIFS(Milestones!$A$5:$A$104,$A12,Milestones!$D$5:$D$104,">="&K$5,Milestones!$D$5:$D$104,"<="&EOMONTH(K$5,0))>0,"◆","")) | L12: =IF($A12="","",IF(COUNTIFS(Milestones!$A$5:$A$104,$A12,Milestones!$D$5:$D$104,">="&L$5,Milestones!$D$5:$D$104,"<="&EOMONTH(L$5,0))>0,"◆","")) | M12: =IF($A12="","",IF(COUNTIFS(Milestones!$A$5:$A$104,$A12,Milestones!$D$5:$D$104,">="&M$5,Milestones!$D$5:$D$104,"<="&EOMONTH(M$5,0))>0,"◆","")) | N12: =IF($A12="","",IF(COUNTIFS(Milestones!$A$5:$A$104,$A12,Milestones!$D$5:$D$104,">="&N$5,Milestones!$D$5:$D$104,"<="&EOMONTH(N$5,0))>0,"◆","")) | ... R12: =IF($A12="","",IF(COUNTIFS(Milestones!$A$5:$A$104,$A12,Milestones!$D$5:$D$104,">="&R$5,Milestones!$D$5:$D$104,"<="&EOMONTH(R$5,0))>0,"◆",""))
A13: =IF(Projects!$A12="","",Projects!$A12) | B13: =IF(Projects!$A12="","",Projects!$B12) | C13: =IF(Projects!$A12="","",Projects!$E12) | D13: =IF(Projects!$A12="","",Projects!$K12) | E13: =IF(Projects!$A12="","",Projects!$I12) | F13: =IF(Projects!$A12="","",Projects!$J12) | G13: =IF($A13="","",IF(COUNTIFS(Milestones!$A$5:$A$104,$A13,Milestones!$D$5:$D$104,">="&G$5,Milestones!$D$5:$D$104,"<="&EOMONTH(G$5,0))>0,"◆","")) | H13: =IF($A13="","",IF(COUNTIFS(Milestones!$A$5:$A$104,$A13,Milestones!$D$5:$D$104,">="&H$5,Milestones!$D$5:$D$104,"<="&EOMONTH(H$5,0))>0,"◆","")) | I13: =IF($A13="","",IF(COUNTIFS(Milestones!$A$5:$A$104,$A13,Milestones!$D$5:$D$104,">="&I$5,Milestones!$D$5:$D$104,"<="&EOMONTH(I$5,0))>0,"◆","")) | J13: =IF($A13="","",IF(COUNTIFS(Milestones!$A$5:$A$104,$A13,Milestones!$D$5:$D$104,">="&J$5,Milestones!$D$5:$D$104,"<="&EOMONTH(J$5,0))>0,"◆","")) | K13: =IF($A13="","",IF(COUNTIFS(Milestones!$A$5:$A$104,$A13,Milestones!$D$5:$D$104,">="&K$5,Milestones!$D$5:$D$104,"<="&EOMONTH(K$5,0))>0,"◆","")) | L13: =IF($A13="","",IF(COUNTIFS(Milestones!$A$5:$A$104,$A13,Milestones!$D$5:$D$104,">="&L$5,Milestones!$D$5:$D$104,"<="&EOMONTH(L$5,0))>0,"◆","")) | M13: =IF($A13="","",IF(COUNTIFS(Milestones!$A$5:$A$104,$A13,Milestones!$D$5:$D$104,">="&M$5,Milestones!$D$5:$D$104,"<="&EOMONTH(M$5,0))>0,"◆","")) | N13: =IF($A13="","",IF(COUNTIFS(Milestones!$A$5:$A$104,$A13,Milestones!$D$5:$D$104,">="&N$5,Milestones!$D$5:$D$104,"<="&EOMONTH(N$5,0))>0,"◆","")) | ... R13: =IF($A13="","",IF(COUNTIFS(Milestones!$A$5:$A$104,$A13,Milestones!$D$5:$D$104,">="&R$5,Milestones!$D$5:$D$104,"<="&EOMONTH(R$5,0))>0,"◆",""))
A14: =IF(Projects!$A13="","",Projects!$A13) | B14: =IF(Projects!$A13="","",Projects!$B13) | C14: =IF(Projects!$A13="","",Projects!$E13) | D14: =IF(Projects!$A13="","",Projects!$K13) | E14: =IF(Projects!$A13="","",Projects!$I13) | F14: =IF(Projects!$A13="","",Projects!$J13) | G14: =IF($A14="","",IF(COUNTIFS(Milestones!$A$5:$A$104,$A14,Milestones!$D$5:$D$104,">="&G$5,Milestones!$D$5:$D$104,"<="&EOMONTH(G$5,0))>0,"◆","")) | H14: =IF($A14="","",IF(COUNTIFS(Milestones!$A$5:$A$104,$A14,Milestones!$D$5:$D$104,">="&H$5,Milestones!$D$5:$D$104,"<="&EOMONTH(H$5,0))>0,"◆","")) | I14: =IF($A14="","",IF(COUNTIFS(Milestones!$A$5:$A$104,$A14,Milestones!$D$5:$D$104,">="&I$5,Milestones!$D$5:$D$104,"<="&EOMONTH(I$5,0))>0,"◆","")) | J14: =IF($A14="","",IF(COUNTIFS(Milestones!$A$5:$A$104,$A14,Milestones!$D$5:$D$104,">="&J$5,Milestones!$D$5:$D$104,"<="&EOMONTH(J$5,0))>0,"◆","")) | K14: =IF($A14="","",IF(COUNTIFS(Milestones!$A$5:$A$104,$A14,Milestones!$D$5:$D$104,">="&K$5,Milestones!$D$5:$D$104,"<="&EOMONTH(K$5,0))>0,"◆","")) | L14: =IF($A14="","",IF(COUNTIFS(Milestones!$A$5:$A$104,$A14,Milestones!$D$5:$D$104,">="&L$5,Milestones!$D$5:$D$104,"<="&EOMONTH(L$5,0))>0,"◆","")) | M14: =IF($A14="","",IF(COUNTIFS(Milestones!$A$5:$A$104,$A14,Milestones!$D$5:$D$104,">="&M$5,Milestones!$D$5:$D$104,"<="&EOMONTH(M$5,0))>0,"◆","")) | N14: =IF($A14="","",IF(COUNTIFS(Milestones!$A$5:$A$104,$A14,Milestones!$D$5:$D$104,">="&N$5,Milestones!$D$5:$D$104,"<="&EOMONTH(N$5,0))>0,"◆","")) | ... R14: =IF($A14="","",IF(COUNTIFS(Milestones!$A$5:$A$104,$A14,Milestones!$D$5:$D$104,">="&R$5,Milestones!$D$5:$D$104,"<="&EOMONTH(R$5,0))>0,"◆",""))
A15: =IF(Projects!$A14="","",Projects!$A14) | B15: =IF(Projects!$A14="","",Projects!$B14) | C15: =IF(Projects!$A14="","",Projects!$E14) | D15: =IF(Projects!$A14="","",Projects!$K14) | E15: =IF(Projects!$A14="","",Projects!$I14) | F15: =IF(Projects!$A14="","",Projects!$J14) | G15: =IF($A15="","",IF(COUNTIFS(Milestones!$A$5:$A$104,$A15,Milestones!$D$5:$D$104,">="&G$5,Milestones!$D$5:$D$104,"<="&EOMONTH(G$5,0))>0,"◆","")) | H15: =IF($A15="","",IF(COUNTIFS(Milestones!$A$5:$A$104,$A15,Milestones!$D$5:$D$104,">="&H$5,Milestones!$D$5:$D$104,"<="&EOMONTH(H$5,0))>0,"◆","")) | I15: =IF($A15="","",IF(COUNTIFS(Milestones!$A$5:$A$104,$A15,Milestones!$D$5:$D$104,">="&I$5,Milestones!$D$5:$D$104,"<="&EOMONTH(I$5,0))>0,"◆","")) | J15: =IF($A15="","",IF(COUNTIFS(Milestones!$A$5:$A$104,$A15,Milestones!$D$5:$D$104,">="&J$5,Milestones!$D$5:$D$104,"<="&EOMONTH(J$5,0))>0,"◆","")) | K15: =IF($A15="","",IF(COUNTIFS(Milestones!$A$5:$A$104,$A15,Milestones!$D$5:$D$104,">="&K$5,Milestones!$D$5:$D$104,"<="&EOMONTH(K$5,0))>0,"◆","")) | L15: =IF($A15="","",IF(COUNTIFS(Milestones!$A$5:$A$104,$A15,Milestones!$D$5:$D$104,">="&L$5,Milestones!$D$5:$D$104,"<="&EOMONTH(L$5,0))>0,"◆","")) | M15: =IF($A15="","",IF(COUNTIFS(Milestones!$A$5:$A$104,$A15,Milestones!$D$5:$D$104,">="&M$5,Milestones!$D$5:$D$104,"<="&EOMONTH(M$5,0))>0,"◆","")) | N15: =IF($A15="","",IF(COUNTIFS(Milestones!$A$5:$A$104,$A15,Milestones!$D$5:$D$104,">="&N$5,Milestones!$D$5:$D$104,"<="&EOMONTH(N$5,0))>0,"◆","")) | ... R15: =IF($A15="","",IF(COUNTIFS(Milestones!$A$5:$A$104,$A15,Milestones!$D$5:$D$104,">="&R$5,Milestones!$D$5:$D$104,"<="&EOMONTH(R$5,0))>0,"◆",""))
A16: =IF(Projects!$A15="","",Projects!$A15) | B16: =IF(Projects!$A15="","",Projects!$B15) | C16: =IF(Projects!$A15="","",Projects!$E15) | D16: =IF(Projects!$A15="","",Projects!$K15) | E16: =IF(Projects!$A15="","",Projects!$I15) | F16: =IF(Projects!$A15="","",Projects!$J15) | G16: =IF($A16="","",IF(COUNTIFS(Milestones!$A$5:$A$104,$A16,Milestones!$D$5:$D$104,">="&G$5,Milestones!$D$5:$D$104,"<="&EOMONTH(G$5,0))>0,"◆","")) | H16: =IF($A16="","",IF(COUNTIFS(Milestones!$A$5:$A$104,$A16,Milestones!$D$5:$D$104,">="&H$5,Milestones!$D$5:$D$104,"<="&EOMONTH(H$5,0))>0,"◆","")) | I16: =IF($A16="","",IF(COUNTIFS(Milestones!$A$5:$A$104,$A16,Milestones!$D$5:$D$104,">="&I$5,Milestones!$D$5:$D$104,"<="&EOMONTH(I$5,0))>0,"◆","")) | J16: =IF($A16="","",IF(COUNTIFS(Milestones!$A$5:$A$104,$A16,Milestones!$D$5:$D$104,">="&J$5,Milestones!$D$5:$D$104,"<="&EOMONTH(J$5,0))>0,"◆","")) | K16: =IF($A16="","",IF(COUNTIFS(Milestones!$A$5:$A$104,$A16,Milestones!$D$5:$D$104,">="&K$5,Milestones!$D$5:$D$104,"<="&EOMONTH(K$5,0))>0,"◆","")) | L16: =IF($A16="","",IF(COUNTIFS(Milestones!$A$5:$A$104,$A16,Milestones!$D$5:$D$104,">="&L$5,Milestones!$D$5:$D$104,"<="&EOMONTH(L$5,0))>0,"◆","")) | M16: =IF($A16="","",IF(COUNTIFS(Milestones!$A$5:$A$104,$A16,Milestones!$D$5:$D$104,">="&M$5,Milestones!$D$5:$D$104,"<="&EOMONTH(M$5,0))>0,"◆","")) | N16: =IF($A16="","",IF(COUNTIFS(Milestones!$A$5:$A$104,$A16,Milestones!$D$5:$D$104,">="&N$5,Milestones!$D$5:$D$104,"<="&EOMONTH(N$5,0))>0,"◆","")) | ... R16: =IF($A16="","",IF(COUNTIFS(Milestones!$A$5:$A$104,$A16,Milestones!$D$5:$D$104,">="&R$5,Milestones!$D$5:$D$104,"<="&EOMONTH(R$5,0))>0,"◆",""))
A17: =IF(Projects!$A16="","",Projects!$A16) | B17: =IF(Projects!$A16="","",Projects!$B16) | C17: =IF(Projects!$A16="","",Projects!$E16) | D17: =IF(Projects!$A16="","",Projects!$K16) | E17: =IF(Projects!$A16="","",Projects!$I16) | F17: =IF(Projects!$A16="","",Projects!$J16) | G17: =IF($A17="","",IF(COUNTIFS(Milestones!$A$5:$A$104,$A17,Milestones!$D$5:$D$104,">="&G$5,Milestones!$D$5:$D$104,"<="&EOMONTH(G$5,0))>0,"◆","")) | H17: =IF($A17="","",IF(COUNTIFS(Milestones!$A$5:$A$104,$A17,Milestones!$D$5:$D$104,">="&H$5,Milestones!$D$5:$D$104,"<="&EOMONTH(H$5,0))>0,"◆","")) | I17: =IF($A17="","",IF(COUNTIFS(Milestones!$A$5:$A$104,$A17,Milestones!$D$5:$D$104,">="&I$5,Milestones!$D$5:$D$104,"<="&EOMONTH(I$5,0))>0,"◆","")) | J17: =IF($A17="","",IF(COUNTIFS(Milestones!$A$5:$A$104,$A17,Milestones!$D$5:$D$104,">="&J$5,Milestones!$D$5:$D$104,"<="&EOMONTH(J$5,0))>0,"◆","")) | K17: =IF($A17="","",IF(COUNTIFS(Milestones!$A$5:$A$104,$A17,Milestones!$D$5:$D$104,">="&K$5,Milestones!$D$5:$D$104,"<="&EOMONTH(K$5,0))>0,"◆","")) | L17: =IF($A17="","",IF(COUNTIFS(Milestones!$A$5:$A$104,$A17,Milestones!$D$5:$D$104,">="&L$5,Milestones!$D$5:$D$104,"<="&EOMONTH(L$5,0))>0,"◆","")) | M17: =IF($A17="","",IF(COUNTIFS(Milestones!$A$5:$A$104,$A17,Milestones!$D$5:$D$104,">="&M$5,Milestones!$D$5:$D$104,"<="&EOMONTH(M$5,0))>0,"◆","")) | N17: =IF($A17="","",IF(COUNTIFS(Milestones!$A$5:$A$104,$A17,Milestones!$D$5:$D$104,">="&N$5,Milestones!$D$5:$D$104,"<="&EOMONTH(N$5,0))>0,"◆","")) | ... R17: =IF($A17="","",IF(COUNTIFS(Milestones!$A$5:$A$104,$A17,Milestones!$D$5:$D$104,">="&R$5,Milestones!$D$5:$D$104,"<="&EOMONTH(R$5,0))>0,"◆",""))
... A55: =IF(Projects!$A54="","",Projects!$A54) | B55: =IF(Projects!$A54="","",Projects!$B54) | C55: =IF(Projects!$A54="","",Projects!$E54) | D55: =IF(Projects!$A54="","",Projects!$K54) | E55: =IF(Projects!$A54="","",Projects!$I54) | F55: =IF(Projects!$A54="","",Projects!$J54) | G55: =IF($A55="","",IF(COUNTIFS(Milestones!$A$5:$A$104,$A55,Milestones!$D$5:$D$104,">="&G$5,Milestones!$D$5:$D$104,"<="&EOMONTH(G$5,0))>0,"◆","")) | H55: =IF($A55="","",IF(COUNTIFS(Milestones!$A$5:$A$104,$A55,Milestones!$D$5:$D$104,">="&H$5,Milestones!$D$5:$D$104,"<="&EOMONTH(H$5,0))>0,"◆","")) | I55: =IF($A55="","",IF(COUNTIFS(Milestones!$A$5:$A$104,$A55,Milestones!$D$5:$D$104,">="&I$5,Milestones!$D$5:$D$104,"<="&EOMONTH(I$5,0))>0,"◆","")) | J55: =IF($A55="","",IF(COUNTIFS(Milestones!$A$5:$A$104,$A55,Milestones!$D$5:$D$104,">="&J$5,Milestones!$D$5:$D$104,"<="&EOMONTH(J$5,0))>0,"◆","")) | K55: =IF($A55="","",IF(COUNTIFS(Milestones!$A$5:$A$104,$A55,Milestones!$D$5:$D$104,">="&K$5,Milestones!$D$5:$D$104,"<="&EOMONTH(K$5,0))>0,"◆","")) | L55: =IF($A55="","",IF(COUNTIFS(Milestones!$A$5:$A$104,$A55,Milestones!$D$5:$D$104,">="&L$5,Milestones!$D$5:$D$104,"<="&EOMONTH(L$5,0))>0,"◆","")) | M55: =IF($A55="","",IF(COUNTIFS(Milestones!$A$5:$A$104,$A55,Milestones!$D$5:$D$104,">="&M$5,Milestones!$D$5:$D$104,"<="&EOMONTH(M$5,0))>0,"◆","")) | N55: =IF($A55="","",IF(COUNTIFS(Milestones!$A$5:$A$104,$A55,Milestones!$D$5:$D$104,">="&N$5,Milestones!$D$5:$D$104,"<="&EOMONTH(N$5,0))>0,"◆","")) | ... R55: =IF($A55="","",IF(COUNTIFS(Milestones!$A$5:$A$104,$A55,Milestones!$D$5:$D$104,">="&R$5,Milestones!$D$5:$D$104,"<="&EOMONTH(R$5,0))>0,"◆",""))

Sheet Team
A1: Team & Resources
A2: Everyone who supplies capacity — FTEs, contractors, and open reqs (to show hiring need). Sample rows — overwrite.
A4: Name | B4: Role | C4: Type | D4: Vendor / Org | E4: Primary skills | F4: Location | G4: Availability % | H4: PTO days / yr | I4: Start date | J4: End date | K4: Monthly cost rate | L4: Annual capacity (FTE-mo) | M4: Annual allocated (FTE-mo) | N4: Utilization | P4: Notes
A5: Tech Lead 1 | B5: Tech Lead | C5: FTE | D5: Fidelity | E5: Java, Spring Boot, AWS | F5: Raleigh | G5: 0.8 | H5: 20 | K5: 15000 | L5: =IF(A5="","",Capacity!P70) -> 8.8299233 | M5: =IF(A5="","",Capacity!P134) -> 9.2 | N5: =IF(OR(A5="",L5=0),"",M5/L5) -> 1.0419117 | P5: • Availability % = time for project work (focus factor). Blank uses Settings default.
A6: Java Dev 1 | B6: Backend Developer | C6: FTE | D6: Fidelity | E6: Java, Kafka | F6: Raleigh | G6: 0.85 | H6: 20 | K6: 12000 | L6: =IF(A6="","",Capacity!P71) -> 9.3817935 | M6: =IF(A6="","",Capacity!P135) -> 8.4 | N6: =IF(OR(A6="",L6=0),"",M6/L6) -> 0.89535119 | P6: • Blank start/end = full plan year. Use them for new joiners and contractor roll-offs.
A7: Angular Dev 1 | B7: Frontend Developer | C7: Contractor | D7: InRhythm | E7: Angular, TypeScript | F7: Remote | G7: 0.9 | H7: 10 | K7: 14000 | L7: =IF(A7="","",Capacity!P72) -> 10.366832 | M7: =IF(A7="","",Capacity!P136) -> 10.8 | N7: =IF(OR(A7="",L7=0),"",M7/L7) -> 1.041784 | P7: • Monthly cost rate is a placeholder — use loaded/blended rates from Finance.
A8: Angular Dev 2 | B8: Full-stack Developer | C8: Contractor | D8: InRhythm | E8: Angular, Java | F8: Remote | G8: 0.9 | H8: 10 | K8: 14000 | L8: =IF(A8="","",Capacity!P73) -> 10.366832 | M8: =IF(A8="","",Capacity!P137) -> 7.6 | N8: =IF(OR(A8="",L8=0),"",M8/L8) -> 0.73310729 | P8: • Open Req rows let you plan work for people not hired yet.
A9: QA Engineer 1 | B9: QA / SDET | C9: Contractor | D9: InRhythm | E9: Playwright, API testing | F9: Remote | G9: 0.9 | H9: 10 | K9: 11000 | L9: =IF(A9="","",Capacity!P74) -> 10.366832 | M9: =IF(A9="","",Capacity!P138) -> 9 | N9: =IF(OR(A9="",L9=0),"",M9/L9) -> 0.86815337
A10: TBH Angular Dev | B10: Frontend Developer | C10: Open Req | D10: Fidelity | E10: Angular | F10: Raleigh | G10: 0.85 | H10: 15 | I10: 46478 | K10: 12000 | L10: =IF(A10="","",Capacity!P75) -> 7.1964827 | M10: =IF(A10="","",Capacity!P139) -> 7.2 | N10: =IF(OR(A10="",L10=0),"",M10/L10) -> 1.0004888
L11: =IF(A11="","",Capacity!P76) | M11: =IF(A11="","",Capacity!P140) | N11: =IF(OR(A11="",L11=0),"",M11/L11)
L12: =IF(A12="","",Capacity!P77) | M12: =IF(A12="","",Capacity!P141) | N12: =IF(OR(A12="",L12=0),"",M12/L12)
L13: =IF(A13="","",Capacity!P78) | M13: =IF(A13="","",Capacity!P142) | N13: =IF(OR(A13="",L13=0),"",M13/L13)
L14: =IF(A14="","",Capacity!P79) | M14: =IF(A14="","",Capacity!P143) | N14: =IF(OR(A14="",L14=0),"",M14/L14)
L15: =IF(A15="","",Capacity!P80) | M15: =IF(A15="","",Capacity!P144) | N15: =IF(OR(A15="",L15=0),"",M15/L15)
L16: =IF(A16="","",Capacity!P81) | M16: =IF(A16="","",Capacity!P145) | N16: =IF(OR(A16="",L16=0),"",M16/L16)
L17: =IF(A17="","",Capacity!P82) | M17: =IF(A17="","",Capacity!P146) | N17: =IF(OR(A17="",L17=0),"",M17/L17)
L18: =IF(A18="","",Capacity!P83) | M18: =IF(A18="","",Capacity!P147) | N18: =IF(OR(A18="",L18=0),"",M18/L18)
L19: =IF(A19="","",Capacity!P84) | M19: =IF(A19="","",Capacity!P148) | N19: =IF(OR(A19="",L19=0),"",M19/L19)
L20: =IF(A20="","",Capacity!P85) | M20: =IF(A20="","",Capacity!P149) | N20: =IF(OR(A20="",L20=0),"",M20/L20)
L21: =IF(A21="","",Capacity!P86) | M21: =IF(A21="","",Capacity!P150) | N21: =IF(OR(A21="",L21=0),"",M21/L21)
L22: =IF(A22="","",Capacity!P87) | M22: =IF(A22="","",Capacity!P151) | N22: =IF(OR(A22="",L22=0),"",M22/L22)
... L64: =IF(A64="","",Capacity!P129) | M64: =IF(A64="","",Capacity!P193) | N64: =IF(OR(A64="",L64=0),"",M64/L64)

Sheet Allocation
A1: Resource Allocation
A2: One row per person × project. Enter the share of that person's month (0.5 = 50%). Sample rows — overwrite.
A4: Resource | B4: Role | C4: Project ID | D4: Project | E4: Jan | F4: Feb | G4: Mar | H4: Apr | I4: May | J4: Jun | K4: Jul | L4: Aug | M4: Sep | N4: Oct | O4: Nov | P4: Dec | Q4: FTE-months | R4: Monthly rate | S4: Labor cost
A5: Tech Lead 1 | B5: =IF(A5="","",IFERROR(INDEX(Team!$B$5:$B$64,MATCH(A5,Team!$A$5:$A$64,0)),"Not in Team")) -> Tech Lead | C5: P001 | D5: =IF(C5="","",IFERROR(INDEX(Projects!$B$5:$B$54,MATCH(C5,Projects!$A$5:$A$54,0)),"Unknown ID")) -> RepApp Angular migration (strangler fig) | E5: 0.6 | F5: 0.6 | G5: 0.6 | H5: 0.6 | I5: 0.6 | J5: 0.6 | K5: 0.6 | L5: 0.6 | M5: 0.6 | N5: 0.6 | O5: 0.6 | P5: 0.6 | Q5: =IF(A5="","",SUM(E5:P5)) -> 7.2 | R5: =IF(A5="","",IFERROR(INDEX(Team!$K$5:$K$64,MATCH(A5,Team!$A$5:$A$64,0)),0)) -> 15000 | S5: =IF(A5="","",Q5*R5) -> 108000
A6: Tech Lead 1 | B6: =IF(A6="","",IFERROR(INDEX(Team!$B$5:$B$64,MATCH(A6,Team!$A$5:$A$64,0)),"Not in Team")) -> Tech Lead | C6: P002 | D6: =IF(C6="","",IFERROR(INDEX(Projects!$B$5:$B$54,MATCH(C6,Projects!$A$5:$A$54,0)),"Unknown ID")) -> Application portfolio dashboard | E6: 0.2 | F6: 0.2 | G6: 0.2 | H6: 0.2 | Q6: =IF(A6="","",SUM(E6:P6)) -> 0.8 | R6: =IF(A6="","",IFERROR(INDEX(Team!$K$5:$K$64,MATCH(A6,Team!$A$5:$A$64,0)),0)) -> 15000 | S6: =IF(A6="","",Q6*R6) -> 12000
A7: Tech Lead 1 | B7: =IF(A7="","",IFERROR(INDEX(Team!$B$5:$B$64,MATCH(A7,Team!$A$5:$A$64,0)),"Not in Team")) -> Tech Lead | C7: P003 | D7: =IF(C7="","",IFERROR(INDEX(Projects!$B$5:$B$54,MATCH(C7,Projects!$A$5:$A$54,0)),"Unknown ID")) -> Observability & alerting uplift | G7: 0.2 | H7: 0.2 | I7: 0.2 | J7: 0.2 | K7: 0.2 | L7: 0.2 | Q7: =IF(A7="","",SUM(E7:P7)) -> 1.2 | R7: =IF(A7="","",IFERROR(INDEX(Team!$K$5:$K$64,MATCH(A7,Team!$A$5:$A$64,0)),0)) -> 15000 | S7: =IF(A7="","",Q7*R7) -> 18000
A8: Java Dev 1 | B8: =IF(A8="","",IFERROR(INDEX(Team!$B$5:$B$64,MATCH(A8,Team!$A$5:$A$64,0)),"Not in Team")) -> Backend Developer | C8: P001 | D8: =IF(C8="","",IFERROR(INDEX(Projects!$B$5:$B$54,MATCH(C8,Projects!$A$5:$A$54,0)),"Unknown ID")) -> RepApp Angular migration (strangler fig) | E8: 0.5 | F8: 0.5 | G8: 0.5 | H8: 0.5 | I8: 0.5 | J8: 0.5 | K8: 0.5 | L8: 0.5 | M8: 0.5 | N8: 0.5 | O8: 0.5 | P8: 0.5 | Q8: =IF(A8="","",SUM(E8:P8)) -> 6 | R8: =IF(A8="","",IFERROR(INDEX(Team!$K$5:$K$64,MATCH(A8,Team!$A$5:$A$64,0)),0)) -> 12000 | S8: =IF(A8="","",Q8*R8) -> 72000
A9: Java Dev 1 | B9: =IF(A9="","",IFERROR(INDEX(Team!$B$5:$B$64,MATCH(A9,Team!$A$5:$A$64,0)),"Not in Team")) -> Backend Developer | C9: P003 | D9: =IF(C9="","",IFERROR(INDEX(Projects!$B$5:$B$54,MATCH(C9,Projects!$A$5:$A$54,0)),"Unknown ID")) -> Observability & alerting uplift | G9: 0.4 | H9: 0.4 | I9: 0.4 | J9: 0.4 | K9: 0.4 | L9: 0.4 | Q9: =IF(A9="","",SUM(E9:P9)) -> 2.4 | R9: =IF(A9="","",IFERROR(INDEX(Team!$K$5:$K$64,MATCH(A9,Team!$A$5:$A$64,0)),0)) -> 12000 | S9: =IF(A9="","",Q9*R9) -> 28800
A10: Angular Dev 1 | B10: =IF(A10="","",IFERROR(INDEX(Team!$B$5:$B$64,MATCH(A10,Team!$A$5:$A$64,0)),"Not in Team")) -> Frontend Developer | C10: P001 | D10: =IF(C10="","",IFERROR(INDEX(Projects!$B$5:$B$54,MATCH(C10,Projects!$A$5:$A$54,0)),"Unknown ID")) -> RepApp Angular migration (strangler fig) | E10: 0.9 | F10: 0.9 | G10: 0.9 | H10: 0.9 | I10: 0.9 | J10: 0.9 | K10: 0.9 | L10: 0.9 | M10: 0.9 | N10: 0.9 | O10: 0.9 | P10: 0.9 | Q10: =IF(A10="","",SUM(E10:P10)) -> 10.8 | R10: =IF(A10="","",IFERROR(INDEX(Team!$K$5:$K$64,MATCH(A10,Team!$A$5:$A$64,0)),0)) -> 14000 | S10: =IF(A10="","",Q10*R10) -> 151200
A11: Angular Dev 2 | B11: =IF(A11="","",IFERROR(INDEX(Team!$B$5:$B$64,MATCH(A11,Team!$A$5:$A$64,0)),"Not in Team")) -> Full-stack Developer | C11: P001 | D11: =IF(C11="","",IFERROR(INDEX(Projects!$B$5:$B$54,MATCH(C11,Projects!$A$5:$A$54,0)),"Unknown ID")) -> RepApp Angular migration (strangler fig) | E11: 0.5 | F11: 0.5 | G11: 0.5 | H11: 0.5 | I11: 0.5 | J11: 0.5 | K11: 0.5 | L11: 0.5 | M11: 0.5 | N11: 0.5 | O11: 0.5 | P11: 0.5 | Q11: =IF(A11="","",SUM(E11:P11)) -> 6 | R11: =IF(A11="","",IFERROR(INDEX(Team!$K$5:$K$64,MATCH(A11,Team!$A$5:$A$64,0)),0)) -> 14000 | S11: =IF(A11="","",Q11*R11) -> 84000
A12: Angular Dev 2 | B12: =IF(A12="","",IFERROR(INDEX(Team!$B$5:$B$64,MATCH(A12,Team!$A$5:$A$64,0)),"Not in Team")) -> Full-stack Developer | C12: P002 | D12: =IF(C12="","",IFERROR(INDEX(Projects!$B$5:$B$54,MATCH(C12,Projects!$A$5:$A$54,0)),"Unknown ID")) -> Application portfolio dashboard | E12: 0.4 | F12: 0.4 | G12: 0.4 | H12: 0.4 | Q12: =IF(A12="","",SUM(E12:P12)) -> 1.6 | R12: =IF(A12="","",IFERROR(INDEX(Team!$K$5:$K$64,MATCH(A12,Team!$A$5:$A$64,0)),0)) -> 14000 | S12: =IF(A12="","",Q12*R12) -> 22400
A13: QA Engineer 1 | B13: =IF(A13="","",IFERROR(INDEX(Team!$B$5:$B$64,MATCH(A13,Team!$A$5:$A$64,0)),"Not in Team")) -> QA / SDET | C13: P001 | D13: =IF(C13="","",IFERROR(INDEX(Projects!$B$5:$B$54,MATCH(C13,Projects!$A$5:$A$54,0)),"Unknown ID")) -> RepApp Angular migration (strangler fig) | E13: 0.6 | F13: 0.6 | G13: 0.6 | H13: 0.6 | I13: 0.6 | J13: 0.6 | K13: 0.6 | L13: 0.6 | M13: 0.6 | N13: 0.6 | O13: 0.6 | P13: 0.6 | Q13: =IF(A13="","",SUM(E13:P13)) -> 7.2 | R13: =IF(A13="","",IFERROR(INDEX(Team!$K$5:$K$64,MATCH(A13,Team!$A$5:$A$64,0)),0)) -> 11000 | S13: =IF(A13="","",Q13*R13) -> 79200
A14: QA Engineer 1 | B14: =IF(A14="","",IFERROR(INDEX(Team!$B$5:$B$64,MATCH(A14,Team!$A$5:$A$64,0)),"Not in Team")) -> QA / SDET | C14: P003 | D14: =IF(C14="","",IFERROR(INDEX(Projects!$B$5:$B$54,MATCH(C14,Projects!$A$5:$A$54,0)),"Unknown ID")) -> Observability & alerting uplift | G14: 0.3 | H14: 0.3 | I14: 0.3 | J14: 0.3 | K14: 0.3 | L14: 0.3 | Q14: =IF(A14="","",SUM(E14:P14)) -> 1.8 | R14: =IF(A14="","",IFERROR(INDEX(Team!$K$5:$K$64,MATCH(A14,Team!$A$5:$A$64,0)),0)) -> 11000 | S14: =IF(A14="","",Q14*R14) -> 19800
A15: TBH Angular Dev | B15: =IF(A15="","",IFERROR(INDEX(Team!$B$5:$B$64,MATCH(A15,Team!$A$5:$A$64,0)),"Not in Team")) -> Frontend Developer | C15: P001 | D15: =IF(C15="","",IFERROR(INDEX(Projects!$B$5:$B$54,MATCH(C15,Projects!$A$5:$A$54,0)),"Unknown ID")) -> RepApp Angular migration (strangler fig) | H15: 0.8 | I15: 0.8 | J15: 0.8 | K15: 0.8 | L15: 0.8 | M15: 0.8 | N15: 0.8 | O15: 0.8 | P15: 0.8 | Q15: =IF(A15="","",SUM(E15:P15)) -> 7.2 | R15: =IF(A15="","",IFERROR(INDEX(Team!$K$5:$K$64,MATCH(A15,Team!$A$5:$A$64,0)),0)) -> 12000 | S15: =IF(A15="","",Q15*R15) -> 86400
B16: =IF(A16="","",IFERROR(INDEX(Team!$B$5:$B$64,MATCH(A16,Team!$A$5:$A$64,0)),"Not in Team")) | D16: =IF(C16="","",IFERROR(INDEX(Projects!$B$5:$B$54,MATCH(C16,Projects!$A$5:$A$54,0)),"Unknown ID")) | Q16: =IF(A16="","",SUM(E16:P16)) | R16: =IF(A16="","",IFERROR(INDEX(Team!$K$5:$K$64,MATCH(A16,Team!$A$5:$A$64,0)),0)) | S16: =IF(A16="","",Q16*R16)
B17: =IF(A17="","",IFERROR(INDEX(Team!$B$5:$B$64,MATCH(A17,Team!$A$5:$A$64,0)),"Not in Team")) | D17: =IF(C17="","",IFERROR(INDEX(Projects!$B$5:$B$54,MATCH(C17,Projects!$A$5:$A$54,0)),"Unknown ID")) | Q17: =IF(A17="","",SUM(E17:P17)) | R17: =IF(A17="","",IFERROR(INDEX(Team!$K$5:$K$64,MATCH(A17,Team!$A$5:$A$64,0)),0)) | S17: =IF(A17="","",Q17*R17)
B18: =IF(A18="","",IFERROR(INDEX(Team!$B$5:$B$64,MATCH(A18,Team!$A$5:$A$64,0)),"Not in Team")) | D18: =IF(C18="","",IFERROR(INDEX(Projects!$B$5:$B$54,MATCH(C18,Projects!$A$5:$A$54,0)),"Unknown ID")) | Q18: =IF(A18="","",SUM(E18:P18)) | R18: =IF(A18="","",IFERROR(INDEX(Team!$K$5:$K$64,MATCH(A18,Team!$A$5:$A$64,0)),0)) | S18: =IF(A18="","",Q18*R18)
B19: =IF(A19="","",IFERROR(INDEX(Team!$B$5:$B$64,MATCH(A19,Team!$A$5:$A$64,0)),"Not in Team")) | D19: =IF(C19="","",IFERROR(INDEX(Projects!$B$5:$B$54,MATCH(C19,Projects!$A$5:$A$54,0)),"Unknown ID")) | Q19: =IF(A19="","",SUM(E19:P19)) | R19: =IF(A19="","",IFERROR(INDEX(Team!$K$5:$K$64,MATCH(A19,Team!$A$5:$A$64,0)),0)) | S19: =IF(A19="","",Q19*R19)
B20: =IF(A20="","",IFERROR(INDEX(Team!$B$5:$B$64,MATCH(A20,Team!$A$5:$A$64,0)),"Not in Team")) | D20: =IF(C20="","",IFERROR(INDEX(Projects!$B$5:$B$54,MATCH(C20,Projects!$A$5:$A$54,0)),"Unknown ID")) | Q20: =IF(A20="","",SUM(E20:P20)) | R20: =IF(A20="","",IFERROR(INDEX(Team!$K$5:$K$64,MATCH(A20,Team!$A$5:$A$64,0)),0)) | S20: =IF(A20="","",Q20*R20)
B21: =IF(A21="","",IFERROR(INDEX(Team!$B$5:$B$64,MATCH(A21,Team!$A$5:$A$64,0)),"Not in Team")) | D21: =IF(C21="","",IFERROR(INDEX(Projects!$B$5:$B$54,MATCH(C21,Projects!$A$5:$A$54,0)),"Unknown ID")) | Q21: =IF(A21="","",SUM(E21:P21)) | R21: =IF(A21="","",IFERROR(INDEX(Team!$K$5:$K$64,MATCH(A21,Team!$A$5:$A$64,0)),0)) | S21: =IF(A21="","",Q21*R21)
B22: =IF(A22="","",IFERROR(INDEX(Team!$B$5:$B$64,MATCH(A22,Team!$A$5:$A$64,0)),"Not in Team")) | D22: =IF(C22="","",IFERROR(INDEX(Projects!$B$5:$B$54,MATCH(C22,Projects!$A$5:$A$54,0)),"Unknown ID")) | Q22: =IF(A22="","",SUM(E22:P22)) | R22: =IF(A22="","",IFERROR(INDEX(Team!$K$5:$K$64,MATCH(A22,Team!$A$5:$A$64,0)),0)) | S22: =IF(A22="","",Q22*R22)
B23: =IF(A23="","",IFERROR(INDEX(Team!$B$5:$B$64,MATCH(A23,Team!$A$5:$A$64,0)),"Not in Team")) | D23: =IF(C23="","",IFERROR(INDEX(Projects!$B$5:$B$54,MATCH(C23,Projects!$A$5:$A$54,0)),"Unknown ID")) | Q23: =IF(A23="","",SUM(E23:P23)) | R23: =IF(A23="","",IFERROR(INDEX(Team!$K$5:$K$64,MATCH(A23,Team!$A$5:$A$64,0)),0)) | S23: =IF(A23="","",Q23*R23)
B24: =IF(A24="","",IFERROR(INDEX(Team!$B$5:$B$64,MATCH(A24,Team!$A$5:$A$64,0)),"Not in Team")) | D24: =IF(C24="","",IFERROR(INDEX(Projects!$B$5:$B$54,MATCH(C24,Projects!$A$5:$A$54,0)),"Unknown ID")) | Q24: =IF(A24="","",SUM(E24:P24)) | R24: =IF(A24="","",IFERROR(INDEX(Team!$K$5:$K$64,MATCH(A24,Team!$A$5:$A$64,0)),0)) | S24: =IF(A24="","",Q24*R24)
B25: =IF(A25="","",IFERROR(INDEX(Team!$B$5:$B$64,MATCH(A25,Team!$A$5:$A$64,0)),"Not in Team")) | D25: =IF(C25="","",IFERROR(INDEX(Projects!$B$5:$B$54,MATCH(C25,Projects!$A$5:$A$54,0)),"Unknown ID")) | Q25: =IF(A25="","",SUM(E25:P25)) | R25: =IF(A25="","",IFERROR(INDEX(Team!$K$5:$K$64,MATCH(A25,Team!$A$5:$A$64,0)),0)) | S25: =IF(A25="","",Q25*R25)
B26: =IF(A26="","",IFERROR(INDEX(Team!$B$5:$B$64,MATCH(A26,Team!$A$5:$A$64,0)),"Not in Team")) | D26: =IF(C26="","",IFERROR(INDEX(Projects!$B$5:$B$54,MATCH(C26,Projects!$A$5:$A$54,0)),"Unknown ID")) | Q26: =IF(A26="","",SUM(E26:P26)) | R26: =IF(A26="","",IFERROR(INDEX(Team!$K$5:$K$64,MATCH(A26,Team!$A$5:$A$64,0)),0)) | S26: =IF(A26="","",Q26*R26)
B27: =IF(A27="","",IFERROR(INDEX(Team!$B$5:$B$64,MATCH(A27,Team!$A$5:$A$64,0)),"Not in Team")) | D27: =IF(C27="","",IFERROR(INDEX(Projects!$B$5:$B$54,MATCH(C27,Projects!$A$5:$A$54,0)),"Unknown ID")) | Q27: =IF(A27="","",SUM(E27:P27)) | R27: =IF(A27="","",IFERROR(INDEX(Team!$K$5:$K$64,MATCH(A27,Team!$A$5:$A$64,0)),0)) | S27: =IF(A27="","",Q27*R27)
... B204: =IF(A204="","",IFERROR(INDEX(Team!$B$5:$B$64,MATCH(A204,Team!$A$5:$A$64,0)),"Not in Team")) | D204: =IF(C204="","",IFERROR(INDEX(Projects!$B$5:$B$54,MATCH(C204,Projects!$A$5:$A$54,0)),"Unknown ID")) | Q204: =IF(A204="","",SUM(E204:P204)) | R204: =IF(A204="","",IFERROR(INDEX(Team!$K$5:$K$64,MATCH(A204,Team!$A$5:$A$64,0)),0)) | S204: =IF(A204="","",Q204*R204)

Sheet Capacity
A1: Capacity & Utilization
A2: Fully calculated — no inputs. Red = over-allocated (>100%), amber = under 50%.
A4: Utilization (allocated ÷ capacity)
A5: Name | B5: Role | C5: Type | D5: =Settings!$A$8 -> 46388 | E5: =Settings!$A$9 -> 46419 | F5: =Settings!$A$10 -> 46447 | G5: =Settings!$A$11 -> 46478 | H5: =Settings!$A$12 -> 46508 | I5: =Settings!$A$13 -> 46539 | J5: =Settings!$A$14 -> 46569 | K5: =Settings!$A$15 -> 46600 | L5: =Settings!$A$16 -> 46631 | M5: =Settings!$A$17 -> 46661 | N5: =Settings!$A$18 -> 46692 | O5: =Settings!$A$19 -> 46722 | P5: Peak month | Q5: Annual | S5: 999% = work allocated in a month the person isn't available (before start / after end date).
A6: =IF(Team!$A5="","",Team!$A5) -> Tech Lead 1 | B6: =IF(Team!$A5="","",Team!$B5) -> Tech Lead | C6: =IF(Team!$A5="","",Team!$C5) -> FTE | D6: =IF($A6="","",IF(N(D70)=0,IF(N(D134)>0,9.99,""),D134/D70)) -> 1.0961538 | E6: =IF($A6="","",IF(N(E70)=0,IF(N(E134)>0,9.99,""),E134/E70)) -> 1.0961538 | F6: =IF($A6="","",IF(N(F70)=0,IF(N(F134)>0,9.99,""),F134/F70)) -> 1.352459 | G6: =IF($A6="","",IF(N(G70)=0,IF(N(G134)>0,9.99,""),G134/G70)) -> 1.352459 | H6: =IF($A6="","",IF(N(H70)=0,IF(N(H134)>0,9.99,""),H134/H70)) -> 1.0909091 | I6: =IF($A6="","",IF(N(I70)=0,IF(N(I134)>0,9.99,""),I134/I70)) -> 1.0862069 | J6: =IF($A6="","",IF(N(J70)=0,IF(N(J134)>0,9.99,""),J134/J70)) -> 1.0862069 | K6: =IF($A6="","",IF(N(K70)=0,IF(N(K134)>0,9.99,""),K134/K70)) -> 1.0819672 | ... O6: =IF($A6="","",IF(N(O70)=0,IF(N(O134)>0,9.99,""),O134/O70)) -> 0.81147541 | P6: =IF($A6="","",MAX(D6:O6)) -> 1.352459 | Q6: =IF(OR($A6="",N(P70)=0),"",P134/P70) -> 1.0419117
A7: =IF(Team!$A6="","",Team!$A6) -> Java Dev 1 | B7: =IF(Team!$A6="","",Team!$B6) -> Backend Developer | C7: =IF(Team!$A6="","",Team!$C6) -> FTE | D7: =IF($A7="","",IF(N(D71)=0,IF(N(D135)>0,9.99,""),D135/D71)) -> 0.64479638 | E7: =IF($A7="","",IF(N(E71)=0,IF(N(E135)>0,9.99,""),E135/E71)) -> 0.64479638 | F7: =IF($A7="","",IF(N(F71)=0,IF(N(F135)>0,9.99,""),F135/F71)) -> 1.1456123 | G7: =IF($A7="","",IF(N(G71)=0,IF(N(G135)>0,9.99,""),G135/G71)) -> 1.1456123 | H7: =IF($A7="","",IF(N(H71)=0,IF(N(H135)>0,9.99,""),H135/H71)) -> 1.1550802 | I7: =IF($A7="","",IF(N(I71)=0,IF(N(I135)>0,9.99,""),I135/I71)) -> 1.1501014 | J7: =IF($A7="","",IF(N(J71)=0,IF(N(J135)>0,9.99,""),J135/J71)) -> 1.1501014 | K7: =IF($A7="","",IF(N(K71)=0,IF(N(K135)>0,9.99,""),K135/K71)) -> 1.1456123 | ... O7: =IF($A7="","",IF(N(O71)=0,IF(N(O135)>0,9.99,""),O135/O71)) -> 0.6364513 | P7: =IF($A7="","",MAX(D7:O7)) -> 1.1550802 | Q7: =IF(OR($A7="",N(P71)=0),"",P135/P71) -> 0.89535119
A8: =IF(Team!$A7="","",Team!$A7) -> Angular Dev 1 | B8: =IF(Team!$A7="","",Team!$B7) -> Frontend Developer | C8: =IF(Team!$A7="","",Team!$C7) -> Contractor | D8: =IF($A8="","",IF(N(D72)=0,IF(N(D136)>0,9.99,""),D136/D72)) -> 1.0458716 | E8: =IF($A8="","",IF(N(E72)=0,IF(N(E136)>0,9.99,""),E136/E72)) -> 1.0458716 | F8: =IF($A8="","",IF(N(F72)=0,IF(N(F136)>0,9.99,""),F136/F72)) -> 1.0393701 | G8: =IF($A8="","",IF(N(G72)=0,IF(N(G136)>0,9.99,""),G136/G72)) -> 1.0393701 | H8: =IF($A8="","",IF(N(H72)=0,IF(N(H136)>0,9.99,""),H136/H72)) -> 1.0434783 | I8: =IF($A8="","",IF(N(I72)=0,IF(N(I136)>0,9.99,""),I136/I72)) -> 1.0413223 | J8: =IF($A8="","",IF(N(J72)=0,IF(N(J136)>0,9.99,""),J136/J72)) -> 1.0413223 | K8: =IF($A8="","",IF(N(K72)=0,IF(N(K136)>0,9.99,""),K136/K72)) -> 1.0393701 | ... O8: =IF($A8="","",IF(N(O72)=0,IF(N(O136)>0,9.99,""),O136/O72)) -> 1.0393701 | P8: =IF($A8="","",MAX(D8:O8)) -> 1.0458716 | Q8: =IF(OR($A8="",N(P72)=0),"",P136/P72) -> 1.041784
A9: =IF(Team!$A8="","",Team!$A8) -> Angular Dev 2 | B9: =IF(Team!$A8="","",Team!$B8) -> Full-stack Developer | C9: =IF(Team!$A8="","",Team!$C8) -> Contractor | D9: =IF($A9="","",IF(N(D73)=0,IF(N(D137)>0,9.99,""),D137/D73)) -> 1.0458716 | E9: =IF($A9="","",IF(N(E73)=0,IF(N(E137)>0,9.99,""),E137/E73)) -> 1.0458716 | F9: =IF($A9="","",IF(N(F73)=0,IF(N(F137)>0,9.99,""),F137/F73)) -> 1.0393701 | G9: =IF($A9="","",IF(N(G73)=0,IF(N(G137)>0,9.99,""),G137/G73)) -> 1.0393701 | H9: =IF($A9="","",IF(N(H73)=0,IF(N(H137)>0,9.99,""),H137/H73)) -> 0.57971014 | I9: =IF($A9="","",IF(N(I73)=0,IF(N(I137)>0,9.99,""),I137/I73)) -> 0.5785124 | J9: =IF($A9="","",IF(N(J73)=0,IF(N(J137)>0,9.99,""),J137/J73)) -> 0.5785124 | K9: =IF($A9="","",IF(N(K73)=0,IF(N(K137)>0,9.99,""),K137/K73)) -> 0.57742782 | ... O9: =IF($A9="","",IF(N(O73)=0,IF(N(O137)>0,9.99,""),O137/O73)) -> 0.57742782 | P9: =IF($A9="","",MAX(D9:O9)) -> 1.0458716 | Q9: =IF(OR($A9="",N(P73)=0),"",P137/P73) -> 0.73310729
A10: =IF(Team!$A9="","",Team!$A9) -> QA Engineer 1 | B10: =IF(Team!$A9="","",Team!$B9) -> QA / SDET | C10: =IF(Team!$A9="","",Team!$C9) -> Contractor | D10: =IF($A10="","",IF(N(D74)=0,IF(N(D138)>0,9.99,""),D138/D74)) -> 0.69724771 | E10: =IF($A10="","",IF(N(E74)=0,IF(N(E138)>0,9.99,""),E138/E74)) -> 0.69724771 | F10: =IF($A10="","",IF(N(F74)=0,IF(N(F138)>0,9.99,""),F138/F74)) -> 1.0393701 | G10: =IF($A10="","",IF(N(G74)=0,IF(N(G138)>0,9.99,""),G138/G74)) -> 1.0393701 | H10: =IF($A10="","",IF(N(H74)=0,IF(N(H138)>0,9.99,""),H138/H74)) -> 1.0434783 | I10: =IF($A10="","",IF(N(I74)=0,IF(N(I138)>0,9.99,""),I138/I74)) -> 1.0413223 | J10: =IF($A10="","",IF(N(J74)=0,IF(N(J138)>0,9.99,""),J138/J74)) -> 1.0413223 | K10: =IF($A10="","",IF(N(K74)=0,IF(N(K138)>0,9.99,""),K138/K74)) -> 1.0393701 | ... O10: =IF($A10="","",IF(N(O74)=0,IF(N(O138)>0,9.99,""),O138/O74)) -> 0.69291339 | P10: =IF($A10="","",MAX(D10:O10)) -> 1.0434783 | Q10: =IF(OR($A10="",N(P74)=0),"",P138/P74) -> 0.86815337
A11: =IF(Team!$A10="","",Team!$A10) -> TBH Angular Dev | B11: =IF(Team!$A10="","",Team!$B10) -> Frontend Developer | C11: =IF(Team!$A10="","",Team!$C10) -> Open Req | D11: =IF($A11="","",IF(N(D75)=0,IF(N(D139)>0,9.99,""),D139/D75)) | E11: =IF($A11="","",IF(N(E75)=0,IF(N(E139)>0,9.99,""),E139/E75)) | F11: =IF($A11="","",IF(N(F75)=0,IF(N(F139)>0,9.99,""),F139/F75)) | G11: =IF($A11="","",IF(N(G75)=0,IF(N(G139)>0,9.99,""),G139/G75)) -> 0.99787385 | H11: =IF($A11="","",IF(N(H75)=0,IF(N(H139)>0,9.99,""),H139/H75)) -> 1.0039216 | I11: =IF($A11="","",IF(N(I75)=0,IF(N(I139)>0,9.99,""),I139/I75)) -> 1.0007446 | J11: =IF($A11="","",IF(N(J75)=0,IF(N(J139)>0,9.99,""),J139/J75)) -> 1.0007446 | K11: =IF($A11="","",IF(N(K75)=0,IF(N(K139)>0,9.99,""),K139/K75)) -> 0.99787385 | ... O11: =IF($A11="","",IF(N(O75)=0,IF(N(O139)>0,9.99,""),O139/O75)) -> 0.99787385 | P11: =IF($A11="","",MAX(D11:O11)) -> 1.0039216 | Q11: =IF(OR($A11="",N(P75)=0),"",P139/P75) -> 1.0004888
A12: =IF(Team!$A11="","",Team!$A11) | B12: =IF(Team!$A11="","",Team!$B11) | C12: =IF(Team!$A11="","",Team!$C11) | D12: =IF($A12="","",IF(N(D76)=0,IF(N(D140)>0,9.99,""),D140/D76)) | E12: =IF($A12="","",IF(N(E76)=0,IF(N(E140)>0,9.99,""),E140/E76)) | F12: =IF($A12="","",IF(N(F76)=0,IF(N(F140)>0,9.99,""),F140/F76)) | G12: =IF($A12="","",IF(N(G76)=0,IF(N(G140)>0,9.99,""),G140/G76)) | H12: =IF($A12="","",IF(N(H76)=0,IF(N(H140)>0,9.99,""),H140/H76)) | I12: =IF($A12="","",IF(N(I76)=0,IF(N(I140)>0,9.99,""),I140/I76)) | J12: =IF($A12="","",IF(N(J76)=0,IF(N(J140)>0,9.99,""),J140/J76)) | K12: =IF($A12="","",IF(N(K76)=0,IF(N(K140)>0,9.99,""),K140/K76)) | ... O12: =IF($A12="","",IF(N(O76)=0,IF(N(O140)>0,9.99,""),O140/O76)) | P12: =IF($A12="","",MAX(D12:O12)) | Q12: =IF(OR($A12="",N(P76)=0),"",P140/P76)
A13: =IF(Team!$A12="","",Team!$A12) | B13: =IF(Team!$A12="","",Team!$B12) | C13: =IF(Team!$A12="","",Team!$C12) | D13: =IF($A13="","",IF(N(D77)=0,IF(N(D141)>0,9.99,""),D141/D77)) | E13: =IF($A13="","",IF(N(E77)=0,IF(N(E141)>0,9.99,""),E141/E77)) | F13: =IF($A13="","",IF(N(F77)=0,IF(N(F141)>0,9.99,""),F141/F77)) | G13: =IF($A13="","",IF(N(G77)=0,IF(N(G141)>0,9.99,""),G141/G77)) | H13: =IF($A13="","",IF(N(H77)=0,IF(N(H141)>0,9.99,""),H141/H77)) | I13: =IF($A13="","",IF(N(I77)=0,IF(N(I141)>0,9.99,""),I141/I77)) | J13: =IF($A13="","",IF(N(J77)=0,IF(N(J141)>0,9.99,""),J141/J77)) | K13: =IF($A13="","",IF(N(K77)=0,IF(N(K141)>0,9.99,""),K141/K77)) | ... O13: =IF($A13="","",IF(N(O77)=0,IF(N(O141)>0,9.99,""),O141/O77)) | P13: =IF($A13="","",MAX(D13:O13)) | Q13: =IF(OR($A13="",N(P77)=0),"",P141/P77)
A14: =IF(Team!$A13="","",Team!$A13) | B14: =IF(Team!$A13="","",Team!$B13) | C14: =IF(Team!$A13="","",Team!$C13) | D14: =IF($A14="","",IF(N(D78)=0,IF(N(D142)>0,9.99,""),D142/D78)) | E14: =IF($A14="","",IF(N(E78)=0,IF(N(E142)>0,9.99,""),E142/E78)) | F14: =IF($A14="","",IF(N(F78)=0,IF(N(F142)>0,9.99,""),F142/F78)) | G14: =IF($A14="","",IF(N(G78)=0,IF(N(G142)>0,9.99,""),G142/G78)) | H14: =IF($A14="","",IF(N(H78)=0,IF(N(H142)>0,9.99,""),H142/H78)) | I14: =IF($A14="","",IF(N(I78)=0,IF(N(I142)>0,9.99,""),I142/I78)) | J14: =IF($A14="","",IF(N(J78)=0,IF(N(J142)>0,9.99,""),J142/J78)) | K14: =IF($A14="","",IF(N(K78)=0,IF(N(K142)>0,9.99,""),K142/K78)) | ... O14: =IF($A14="","",IF(N(O78)=0,IF(N(O142)>0,9.99,""),O142/O78)) | P14: =IF($A14="","",MAX(D14:O14)) | Q14: =IF(OR($A14="",N(P78)=0),"",P142/P78)
A15: =IF(Team!$A14="","",Team!$A14) | B15: =IF(Team!$A14="","",Team!$B14) | C15: =IF(Team!$A14="","",Team!$C14) | D15: =IF($A15="","",IF(N(D79)=0,IF(N(D143)>0,9.99,""),D143/D79)) | E15: =IF($A15="","",IF(N(E79)=0,IF(N(E143)>0,9.99,""),E143/E79)) | F15: =IF($A15="","",IF(N(F79)=0,IF(N(F143)>0,9.99,""),F143/F79)) | G15: =IF($A15="","",IF(N(G79)=0,IF(N(G143)>0,9.99,""),G143/G79)) | H15: =IF($A15="","",IF(N(H79)=0,IF(N(H143)>0,9.99,""),H143/H79)) | I15: =IF($A15="","",IF(N(I79)=0,IF(N(I143)>0,9.99,""),I143/I79)) | J15: =IF($A15="","",IF(N(J79)=0,IF(N(J143)>0,9.99,""),J143/J79)) | K15: =IF($A15="","",IF(N(K79)=0,IF(N(K143)>0,9.99,""),K143/K79)) | ... O15: =IF($A15="","",IF(N(O79)=0,IF(N(O143)>0,9.99,""),O143/O79)) | P15: =IF($A15="","",MAX(D15:O15)) | Q15: =IF(OR($A15="",N(P79)=0),"",P143/P79)
A16: =IF(Team!$A15="","",Team!$A15) | B16: =IF(Team!$A15="","",Team!$B15) | C16: =IF(Team!$A15="","",Team!$C15) | D16: =IF($A16="","",IF(N(D80)=0,IF(N(D144)>0,9.99,""),D144/D80)) | E16: =IF($A16="","",IF(N(E80)=0,IF(N(E144)>0,9.99,""),E144/E80)) | F16: =IF($A16="","",IF(N(F80)=0,IF(N(F144)>0,9.99,""),F144/F80)) | G16: =IF($A16="","",IF(N(G80)=0,IF(N(G144)>0,9.99,""),G144/G80)) | H16: =IF($A16="","",IF(N(H80)=0,IF(N(H144)>0,9.99,""),H144/H80)) | I16: =IF($A16="","",IF(N(I80)=0,IF(N(I144)>0,9.99,""),I144/I80)) | J16: =IF($A16="","",IF(N(J80)=0,IF(N(J144)>0,9.99,""),J144/J80)) | K16: =IF($A16="","",IF(N(K80)=0,IF(N(K144)>0,9.99,""),K144/K80)) | ... O16: =IF($A16="","",IF(N(O80)=0,IF(N(O144)>0,9.99,""),O144/O80)) | P16: =IF($A16="","",MAX(D16:O16)) | Q16: =IF(OR($A16="",N(P80)=0),"",P144/P80)
A17: =IF(Team!$A16="","",Team!$A16) | B17: =IF(Team!$A16="","",Team!$B16) | C17: =IF(Team!$A16="","",Team!$C16) | D17: =IF($A17="","",IF(N(D81)=0,IF(N(D145)>0,9.99,""),D145/D81)) | E17: =IF($A17="","",IF(N(E81)=0,IF(N(E145)>0,9.99,""),E145/E81)) | F17: =IF($A17="","",IF(N(F81)=0,IF(N(F145)>0,9.99,""),F145/F81)) | G17: =IF($A17="","",IF(N(G81)=0,IF(N(G145)>0,9.99,""),G145/G81)) | H17: =IF($A17="","",IF(N(H81)=0,IF(N(H145)>0,9.99,""),H145/H81)) | I17: =IF($A17="","",IF(N(I81)=0,IF(N(I145)>0,9.99,""),I145/I81)) | J17: =IF($A17="","",IF(N(J81)=0,IF(N(J145)>0,9.99,""),J145/J81)) | K17: =IF($A17="","",IF(N(K81)=0,IF(N(K145)>0,9.99,""),K145/K81)) | ... O17: =IF($A17="","",IF(N(O81)=0,IF(N(O145)>0,9.99,""),O145/O81)) | P17: =IF($A17="","",MAX(D17:O17)) | Q17: =IF(OR($A17="",N(P81)=0),"",P145/P81)
... A65: =IF(Team!$A64="","",Team!$A64) | B65: =IF(Team!$A64="","",Team!$B64) | C65: =IF(Team!$A64="","",Team!$C64) | D65: =IF($A65="","",IF(N(D129)=0,IF(N(D193)>0,9.99,""),D193/D129)) | E65: =IF($A65="","",IF(N(E129)=0,IF(N(E193)>0,9.99,""),E193/E129)) | F65: =IF($A65="","",IF(N(F129)=0,IF(N(F193)>0,9.99,""),F193/F129)) | G65: =IF($A65="","",IF(N(G129)=0,IF(N(G193)>0,9.99,""),G193/G129)) | H65: =IF($A65="","",IF(N(H129)=0,IF(N(H193)>0,9.99,""),H193/H129)) | I65: =IF($A65="","",IF(N(I129)=0,IF(N(I193)>0,9.99,""),I193/I129)) | J65: =IF($A65="","",IF(N(J129)=0,IF(N(J193)>0,9.99,""),J193/J129)) | K65: =IF($A65="","",IF(N(K129)=0,IF(N(K193)>0,9.99,""),K193/K129)) | ... O65: =IF($A65="","",IF(N(O129)=0,IF(N(O193)>0,9.99,""),O193/O129)) | P65: =IF($A65="","",MAX(D65:O65)) | Q65: =IF(OR($A65="",N(P129)=0),"",P193/P129)
A68: Capacity (FTE available per month)
A69: Name | B69: Role | C69: Type | D69: =Settings!$A$8 -> 46388 | E69: =Settings!$A$9 -> 46419 | F69: =Settings!$A$10 -> 46447 | G69: =Settings!$A$11 -> 46478 | H69: =Settings!$A$12 -> 46508 | I69: =Settings!$A$13 -> 46539 | J69: =Settings!$A$14 -> 46569 | K69: =Settings!$A$15 -> 46600 | L69: =Settings!$A$16 -> 46631 | M69: =Settings!$A$17 -> 46661 | N69: =Settings!$A$18 -> 46692 | O69: =Settings!$A$19 -> 46722 | P69: Total FTE-mo
A70: =IF(Team!$A5="","",Team!$A5) -> Tech Lead 1 | B70: =IF(Team!$A5="","",Team!$B5) -> Tech Lead | C70: =IF(Team!$A5="","",Team!$C5) -> FTE | D70: =IF($A70="","",IF(AND(IF(Team!$I5="",DATE(Settings!$B$3,1,1),Team!$I5)<=EOMONTH(D$69,0),IF(Team!$J5="",DATE(Settings!$B$3,12,31),Team!$J5)>=D$69),IF(Team!$G5="",Settings!$B$4,Team!$G5)*(1-N(Team!$H5)/12/Settings!$B$8),0)) -> 0.72982456 | E70: =IF($A70="","",IF(AND(IF(Team!$I5="",DATE(Settings!$B$3,1,1),Team!$I5)<=EOMONTH(E$69,0),IF(Team!$J5="",DATE(Settings!$B$3,12,31),Team!$J5)>=E$69),IF(Team!$G5="",Settings!$B$4,Team!$G5)*(1-N(Team!$H5)/12/Settings!$B$9),0)) -> 0.72982456 | F70: =IF($A70="","",IF(AND(IF(Team!$I5="",DATE(Settings!$B$3,1,1),Team!$I5)<=EOMONTH(F$69,0),IF(Team!$J5="",DATE(Settings!$B$3,12,31),Team!$J5)>=F$69),IF(Team!$G5="",Settings!$B$4,Team!$G5)*(1-N(Team!$H5)/12/Settings!$B$10),0)) -> 0.73939394 | G70: =IF($A70="","",IF(AND(IF(Team!$I5="",DATE(Settings!$B$3,1,1),Team!$I5)<=EOMONTH(G$69,0),IF(Team!$J5="",DATE(Settings!$B$3,12,31),Team!$J5)>=G$69),IF(Team!$G5="",Settings!$B$4,Team!$G5)*(1-N(Team!$H5)/12/Settings!$B$11),0)) -> 0.73939394 | H70: =IF($A70="","",IF(AND(IF(Team!$I5="",DATE(Settings!$B$3,1,1),Team!$I5)<=EOMONTH(H$69,0),IF(Team!$J5="",DATE(Settings!$B$3,12,31),Team!$J5)>=H$69),IF(Team!$G5="",Settings!$B$4,Team!$G5)*(1-N(Team!$H5)/12/Settings!$B$12),0)) -> 0.73333333 | I70: =IF($A70="","",IF(AND(IF(Team!$I5="",DATE(Settings!$B$3,1,1),Team!$I5)<=EOMONTH(I$69,0),IF(Team!$J5="",DATE(Settings!$B$3,12,31),Team!$J5)>=I$69),IF(Team!$G5="",Settings!$B$4,Team!$G5)*(1-N(Team!$H5)/12/Settings!$B$13),0)) -> 0.73650794 | J70: =IF($A70="","",IF(AND(IF(Team!$I5="",DATE(Settings!$B$3,1,1),Team!$I5)<=EOMONTH(J$69,0),IF(Team!$J5="",DATE(Settings!$B$3,12,31),Team!$J5)>=J$69),IF(Team!$G5="",Settings!$B$4,Team!$G5)*(1-N(Team!$H5)/12/Settings!$B$14),0)) -> 0.73650794 | K70: =IF($A70="","",IF(AND(IF(Team!$I5="",DATE(Settings!$B$3,1,1),Team!$I5)<=EOMONTH(K$69,0),IF(Team!$J5="",DATE(Settings!$B$3,12,31),Team!$J5)>=K$69),IF(Team!$G5="",Settings!$B$4,Team!$G5)*(1-N(Team!$H5)/12/Settings!$B$15),0)) -> 0.73939394 | L70: =IF($A70="","",IF(AND(IF(Team!$I5="",DATE(Settings!$B$3,1,1),Team!$I5)<=EOMONTH(L$69,0),IF(Team!$J5="",DATE(Settings!$B$3,12,31),Team!$J5)>=L$69),IF(Team!$G5="",Settings!$B$4,Team!$G5)*(1-N(Team!$H5)/12/Settings!$B$16),0)) -> 0.73650794 | M70: =IF($A70="","",IF(AND(IF(Team!$I5="",DATE(Settings!$B$3,1,1),Team!$I5)<=EOMONTH(M$69,0),IF(Team!$J5="",DATE(Settings!$B$3,12,31),Team!$J5)>=M$69),IF(Team!$G5="",Settings!$B$4,Team!$G5)*(1-N(Team!$H5)/12/Settings!$B$17),0)) -> 0.73650794 | N70: =IF($A70="","",IF(AND(IF(Team!$I5="",DATE(Settings!$B$3,1,1),Team!$I5)<=EOMONTH(N$69,0),IF(Team!$J5="",DATE(Settings!$B$3,12,31),Team!$J5)>=N$69),IF(Team!$G5="",Settings!$B$4,Team!$G5)*(1-N(Team!$H5)/12/Settings!$B$18),0)) -> 0.73333333 | O70: =IF($A70="","",IF(AND(IF(Team!$I5="",DATE(Settings!$B$3,1,1),Team!$I5)<=EOMONTH(O$69,0),IF(Team!$J5="",DATE(Settings!$B$3,12,31),Team!$J5)>=O$69),IF(Team!$G5="",Settings!$B$4,Team!$G5)*(1-N(Team!$H5)/12/Settings!$B$19),0)) -> 0.73939394 | P70: =IF($A70="","",SUM(D70:O70)) -> 8.8299233
A71: =IF(Team!$A6="","",Team!$A6) -> Java Dev 1 | B71: =IF(Team!$A6="","",Team!$B6) -> Backend Developer | C71: =IF(Team!$A6="","",Team!$C6) -> FTE | D71: =IF($A71="","",IF(AND(IF(Team!$I6="",DATE(Settings!$B$3,1,1),Team!$I6)<=EOMONTH(D$69,0),IF(Team!$J6="",DATE(Settings!$B$3,12,31),Team!$J6)>=D$69),IF(Team!$G6="",Settings!$B$4,Team!$G6)*(1-N(Team!$H6)/12/Settings!$B$8),0)) -> 0.7754386 | E71: =IF($A71="","",IF(AND(IF(Team!$I6="",DATE(Settings!$B$3,1,1),Team!$I6)<=EOMONTH(E$69,0),IF(Team!$J6="",DATE(Settings!$B$3,12,31),Team!$J6)>=E$69),IF(Team!$G6="",Settings!$B$4,Team!$G6)*(1-N(Team!$H6)/12/Settings!$B$9),0)) -> 0.7754386 | F71: =IF($A71="","",IF(AND(IF(Team!$I6="",DATE(Settings!$B$3,1,1),Team!$I6)<=EOMONTH(F$69,0),IF(Team!$J6="",DATE(Settings!$B$3,12,31),Team!$J6)>=F$69),IF(Team!$G6="",Settings!$B$4,Team!$G6)*(1-N(Team!$H6)/12/Settings!$B$10),0)) -> 0.78560606 | G71: =IF($A71="","",IF(AND(IF(Team!$I6="",DATE(Settings!$B$3,1,1),Team!$I6)<=EOMONTH(G$69,0),IF(Team!$J6="",DATE(Settings!$B$3,12,31),Team!$J6)>=G$69),IF(Team!$G6="",Settings!$B$4,Team!$G6)*(1-N(Team!$H6)/12/Settings!$B$11),0)) -> 0.78560606 | H71: =IF($A71="","",IF(AND(IF(Team!$I6="",DATE(Settings!$B$3,1,1),Team!$I6)<=EOMONTH(H$69,0),IF(Team!$J6="",DATE(Settings!$B$3,12,31),Team!$J6)>=H$69),IF(Team!$G6="",Settings!$B$4,Team!$G6)*(1-N(Team!$H6)/12/Settings!$B$12),0)) -> 0.77916667 | I71: =IF($A71="","",IF(AND(IF(Team!$I6="",DATE(Settings!$B$3,1,1),Team!$I6)<=EOMONTH(I$69,0),IF(Team!$J6="",DATE(Settings!$B$3,12,31),Team!$J6)>=I$69),IF(Team!$G6="",Settings!$B$4,Team!$G6)*(1-N(Team!$H6)/12/Settings!$B$13),0)) -> 0.78253968 | J71: =IF($A71="","",IF(AND(IF(Team!$I6="",DATE(Settings!$B$3,1,1),Team!$I6)<=EOMONTH(J$69,0),IF(Team!$J6="",DATE(Settings!$B$3,12,31),Team!$J6)>=J$69),IF(Team!$G6="",Settings!$B$4,Team!$G6)*(1-N(Team!$H6)/12/Settings!$B$14),0)) -> 0.78253968 | K71: =IF($A71="","",IF(AND(IF(Team!$I6="",DATE(Settings!$B$3,1,1),Team!$I6)<=EOMONTH(K$69,0),IF(Team!$J6="",DATE(Settings!$B$3,12,31),Team!$J6)>=K$69),IF(Team!$G6="",Settings!$B$4,Team!$G6)*(1-N(Team!$H6)/12/Settings!$B$15),0)) -> 0.78560606 | L71: =IF($A71="","",IF(AND(IF(Team!$I6="",DATE(Settings!$B$3,1,1),Team!$I6)<=EOMONTH(L$69,0),IF(Team!$J6="",DATE(Settings!$B$3,12,31),Team!$J6)>=L$69),IF(Team!$G6="",Settings!$B$4,Team!$G6)*(1-N(Team!$H6)/12/Settings!$B$16),0)) -> 0.78253968 | M71: =IF($A71="","",IF(AND(IF(Team!$I6="",DATE(Settings!$B$3,1,1),Team!$I6)<=EOMONTH(M$69,0),IF(Team!$J6="",DATE(Settings!$B$3,12,31),Team!$J6)>=M$69),IF(Team!$G6="",Settings!$B$4,Team!$G6)*(1-N(Team!$H6)/12/Settings!$B$17),0)) -> 0.78253968 | N71: =IF($A71="","",IF(AND(IF(Team!$I6="",DATE(Settings!$B$3,1,1),Team!$I6)<=EOMONTH(N$69,0),IF(Team!$J6="",DATE(Settings!$B$3,12,31),Team!$J6)>=N$69),IF(Team!$G6="",Settings!$B$4,Team!$G6)*(1-N(Team!$H6)/12/Settings!$B$18),0)) -> 0.77916667 | O71: =IF($A71="","",IF(AND(IF(Team!$I6="",DATE(Settings!$B$3,1,1),Team!$I6)<=EOMONTH(O$69,0),IF(Team!$J6="",DATE(Settings!$B$3,12,31),Team!$J6)>=O$69),IF(Team!$G6="",Settings!$B$4,Team!$G6)*(1-N(Team!$H6)/12/Settings!$B$19),0)) -> 0.78560606 | P71: =IF($A71="","",SUM(D71:O71)) -> 9.3817935
A72: =IF(Team!$A7="","",Team!$A7) -> Angular Dev 1 | B72: =IF(Team!$A7="","",Team!$B7) -> Frontend Developer | C72: =IF(Team!$A7="","",Team!$C7) -> Contractor | D72: =IF($A72="","",IF(AND(IF(Team!$I7="",DATE(Settings!$B$3,1,1),Team!$I7)<=EOMONTH(D$69,0),IF(Team!$J7="",DATE(Settings!$B$3,12,31),Team!$J7)>=D$69),IF(Team!$G7="",Settings!$B$4,Team!$G7)*(1-N(Team!$H7)/12/Settings!$B$8),0)) -> 0.86052632 | E72: =IF($A72="","",IF(AND(IF(Team!$I7="",DATE(Settings!$B$3,1,1),Team!$I7)<=EOMONTH(E$69,0),IF(Team!$J7="",DATE(Settings!$B$3,12,31),Team!$J7)>=E$69),IF(Team!$G7="",Settings!$B$4,Team!$G7)*(1-N(Team!$H7)/12/Settings!$B$9),0)) -> 0.86052632 | F72: =IF($A72="","",IF(AND(IF(Team!$I7="",DATE(Settings!$B$3,1,1),Team!$I7)<=EOMONTH(F$69,0),IF(Team!$J7="",DATE(Settings!$B$3,12,31),Team!$J7)>=F$69),IF(Team!$G7="",Settings!$B$4,Team!$G7)*(1-N(Team!$H7)/12/Settings!$B$10),0)) -> 0.86590909 | G72: =IF($A72="","",IF(AND(IF(Team!$I7="",DATE(Settings!$B$3,1,1),Team!$I7)<=EOMONTH(G$69,0),IF(Team!$J7="",DATE(Settings!$B$3,12,31),Team!$J7)>=G$69),IF(Team!$G7="",Settings!$B$4,Team!$G7)*(1-N(Team!$H7)/12/Settings!$B$11),0)) -> 0.86590909 | H72: =IF($A72="","",IF(AND(IF(Team!$I7="",DATE(Settings!$B$3,1,1),Team!$I7)<=EOMONTH(H$69,0),IF(Team!$J7="",DATE(Settings!$B$3,12,31),Team!$J7)>=H$69),IF(Team!$G7="",Settings!$B$4,Team!$G7)*(1-N(Team!$H7)/12/Settings!$B$12),0)) -> 0.8625 | I72: =IF($A72="","",IF(AND(IF(Team!$I7="",DATE(Settings!$B$3,1,1),Team!$I7)<=EOMONTH(I$69,0),IF(Team!$J7="",DATE(Settings!$B$3,12,31),Team!$J7)>=I$69),IF(Team!$G7="",Settings!$B$4,Team!$G7)*(1-N(Team!$H7)/12/Settings!$B$13),0)) -> 0.86428571 | J72: =IF($A72="","",IF(AND(IF(Team!$I7="",DATE(Settings!$B$3,1,1),Team!$I7)<=EOMONTH(J$69,0),IF(Team!$J7="",DATE(Settings!$B$3,12,31),Team!$J7)>=J$69),IF(Team!$G7="",Settings!$B$4,Team!$G7)*(1-N(Team!$H7)/12/Settings!$B$14),0)) -> 0.86428571 | K72: =IF($A72="","",IF(AND(IF(Team!$I7="",DATE(Settings!$B$3,1,1),Team!$I7)<=EOMONTH(K$69,0),IF(Team!$J7="",DATE(Settings!$B$3,12,31),Team!$J7)>=K$69),IF(Team!$G7="",Settings!$B$4,Team!$G7)*(1-N(Team!$H7)/12/Settings!$B$15),0)) -> 0.86590909 | L72: =IF($A72="","",IF(AND(IF(Team!$I7="",DATE(Settings!$B$3,1,1),Team!$I7)<=EOMONTH(L$69,0),IF(Team!$J7="",DATE(Settings!$B$3,12,31),Team!$J7)>=L$69),IF(Team!$G7="",Settings!$B$4,Team!$G7)*(1-N(Team!$H7)/12/Settings!$B$16),0)) -> 0.86428571 | M72: =IF($A72="","",IF(AND(IF(Team!$I7="",DATE(Settings!$B$3,1,1),Team!$I7)<=EOMONTH(M$69,0),IF(Team!$J7="",DATE(Settings!$B$3,12,31),Team!$J7)>=M$69),IF(Team!$G7="",Settings!$B$4,Team!$G7)*(1-N(Team!$H7)/12/Settings!$B$17),0)) -> 0.86428571 | N72: =IF($A72="","",IF(AND(IF(Team!$I7="",DATE(Settings!$B$3,1,1),Team!$I7)<=EOMONTH(N$69,0),IF(Team!$J7="",DATE(Settings!$B$3,12,31),Team!$J7)>=N$69),IF(Team!$G7="",Settings!$B$4,Team!$G7)*(1-N(Team!$H7)/12/Settings!$B$18),0)) -> 0.8625 | O72: =IF($A72="","",IF(AND(IF(Team!$I7="",DATE(Settings!$B$3,1,1),Team!$I7)<=EOMONTH(O$69,0),IF(Team!$J7="",DATE(Settings!$B$3,12,31),Team!$J7)>=O$69),IF(Team!$G7="",Settings!$B$4,Team!$G7)*(1-N(Team!$H7)/12/Settings!$B$19),0)) -> 0.86590909 | P72: =IF($A72="","",SUM(D72:O72)) -> 10.366832
A73: =IF(Team!$A8="","",Team!$A8) -> Angular Dev 2 | B73: =IF(Team!$A8="","",Team!$B8) -> Full-stack Developer | C73: =IF(Team!$A8="","",Team!$C8) -> Contractor | D73: =IF($A73="","",IF(AND(IF(Team!$I8="",DATE(Settings!$B$3,1,1),Team!$I8)<=EOMONTH(D$69,0),IF(Team!$J8="",DATE(Settings!$B$3,12,31),Team!$J8)>=D$69),IF(Team!$G8="",Settings!$B$4,Team!$G8)*(1-N(Team!$H8)/12/Settings!$B$8),0)) -> 0.86052632 | E73: =IF($A73="","",IF(AND(IF(Team!$I8="",DATE(Settings!$B$3,1,1),Team!$I8)<=EOMONTH(E$69,0),IF(Team!$J8="",DATE(Settings!$B$3,12,31),Team!$J8)>=E$69),IF(Team!$G8="",Settings!$B$4,Team!$G8)*(1-N(Team!$H8)/12/Settings!$B$9),0)) -> 0.86052632 | F73: =IF($A73="","",IF(AND(IF(Team!$I8="",DATE(Settings!$B$3,1,1),Team!$I8)<=EOMONTH(F$69,0),IF(Team!$J8="",DATE(Settings!$B$3,12,31),Team!$J8)>=F$69),IF(Team!$G8="",Settings!$B$4,Team!$G8)*(1-N(Team!$H8)/12/Settings!$B$10),0)) -> 0.86590909 | G73: =IF($A73="","",IF(AND(IF(Team!$I8="",DATE(Settings!$B$3,1,1),Team!$I8)<=EOMONTH(G$69,0),IF(Team!$J8="",DATE(Settings!$B$3,12,31),Team!$J8)>=G$69),IF(Team!$G8="",Settings!$B$4,Team!$G8)*(1-N(Team!$H8)/12/Settings!$B$11),0)) -> 0.86590909 | H73: =IF($A73="","",IF(AND(IF(Team!$I8="",DATE(Settings!$B$3,1,1),Team!$I8)<=EOMONTH(H$69,0),IF(Team!$J8="",DATE(Settings!$B$3,12,31),Team!$J8)>=H$69),IF(Team!$G8="",Settings!$B$4,Team!$G8)*(1-N(Team!$H8)/12/Settings!$B$12),0)) -> 0.8625 | I73: =IF($A73="","",IF(AND(IF(Team!$I8="",DATE(Settings!$B$3,1,1),Team!$I8)<=EOMONTH(I$69,0),IF(Team!$J8="",DATE(Settings!$B$3,12,31),Team!$J8)>=I$69),IF(Team!$G8="",Settings!$B$4,Team!$G8)*(1-N(Team!$H8)/12/Settings!$B$13),0)) -> 0.86428571 | J73: =IF($A73="","",IF(AND(IF(Team!$I8="",DATE(Settings!$B$3,1,1),Team!$I8)<=EOMONTH(J$69,0),IF(Team!$J8="",DATE(Settings!$B$3,12,31),Team!$J8)>=J$69),IF(Team!$G8="",Settings!$B$4,Team!$G8)*(1-N(Team!$H8)/12/Settings!$B$14),0)) -> 0.86428571 | K73: =IF($A73="","",IF(AND(IF(Team!$I8="",DATE(Settings!$B$3,1,1),Team!$I8)<=EOMONTH(K$69,0),IF(Team!$J8="",DATE(Settings!$B$3,12,31),Team!$J8)>=K$69),IF(Team!$G8="",Settings!$B$4,Team!$G8)*(1-N(Team!$H8)/12/Settings!$B$15),0)) -> 0.86590909 | L73: =IF($A73="","",IF(AND(IF(Team!$I8="",DATE(Settings!$B$3,1,1),Team!$I8)<=EOMONTH(L$69,0),IF(Team!$J8="",DATE(Settings!$B$3,12,31),Team!$J8)>=L$69),IF(Team!$G8="",Settings!$B$4,Team!$G8)*(1-N(Team!$H8)/12/Settings!$B$16),0)) -> 0.86428571 | M73: =IF($A73="","",IF(AND(IF(Team!$I8="",DATE(Settings!$B$3,1,1),Team!$I8)<=EOMONTH(M$69,0),IF(Team!$J8="",DATE(Settings!$B$3,12,31),Team!$J8)>=M$69),IF(Team!$G8="",Settings!$B$4,Team!$G8)*(1-N(Team!$H8)/12/Settings!$B$17),0)) -> 0.86428571 | N73: =IF($A73="","",IF(AND(IF(Team!$I8="",DATE(Settings!$B$3,1,1),Team!$I8)<=EOMONTH(N$69,0),IF(Team!$J8="",DATE(Settings!$B$3,12,31),Team!$J8)>=N$69),IF(Team!$G8="",Settings!$B$4,Team!$G8)*(1-N(Team!$H8)/12/Settings!$B$18),0)) -> 0.8625 | O73: =IF($A73="","",IF(AND(IF(Team!$I8="",DATE(Settings!$B$3,1,1),Team!$I8)<=EOMONTH(O$69,0),IF(Team!$J8="",DATE(Settings!$B$3,12,31),Team!$J8)>=O$69),IF(Team!$G8="",Settings!$B$4,Team!$G8)*(1-N(Team!$H8)/12/Settings!$B$19),0)) -> 0.86590909 | P73: =IF($A73="","",SUM(D73:O73)) -> 10.366832
A74: =IF(Team!$A9="","",Team!$A9) -> QA Engineer 1 | B74: =IF(Team!$A9="","",Team!$B9) -> QA / SDET | C74: =IF(Team!$A9="","",Team!$C9) -> Contractor | D74: =IF($A74="","",IF(AND(IF(Team!$I9="",DATE(Settings!$B$3,1,1),Team!$I9)<=EOMONTH(D$69,0),IF(Team!$J9="",DATE(Settings!$B$3,12,31),Team!$J9)>=D$69),IF(Team!$G9="",Settings!$B$4,Team!$G9)*(1-N(Team!$H9)/12/Settings!$B$8),0)) -> 0.86052632 | E74: =IF($A74="","",IF(AND(IF(Team!$I9="",DATE(Settings!$B$3,1,1),Team!$I9)<=EOMONTH(E$69,0),IF(Team!$J9="",DATE(Settings!$B$3,12,31),Team!$J9)>=E$69),IF(Team!$G9="",Settings!$B$4,Team!$G9)*(1-N(Team!$H9)/12/Settings!$B$9),0)) -> 0.86052632 | F74: =IF($A74="","",IF(AND(IF(Team!$I9="",DATE(Settings!$B$3,1,1),Team!$I9)<=EOMONTH(F$69,0),IF(Team!$J9="",DATE(Settings!$B$3,12,31),Team!$J9)>=F$69),IF(Team!$G9="",Settings!$B$4,Team!$G9)*(1-N(Team!$H9)/12/Settings!$B$10),0)) -> 0.86590909 | G74: =IF($A74="","",IF(AND(IF(Team!$I9="",DATE(Settings!$B$3,1,1),Team!$I9)<=EOMONTH(G$69,0),IF(Team!$J9="",DATE(Settings!$B$3,12,31),Team!$J9)>=G$69),IF(Team!$G9="",Settings!$B$4,Team!$G9)*(1-N(Team!$H9)/12/Settings!$B$11),0)) -> 0.86590909 | H74: =IF($A74="","",IF(AND(IF(Team!$I9="",DATE(Settings!$B$3,1,1),Team!$I9)<=EOMONTH(H$69,0),IF(Team!$J9="",DATE(Settings!$B$3,12,31),Team!$J9)>=H$69),IF(Team!$G9="",Settings!$B$4,Team!$G9)*(1-N(Team!$H9)/12/Settings!$B$12),0)) -> 0.8625 | I74: =IF($A74="","",IF(AND(IF(Team!$I9="",DATE(Settings!$B$3,1,1),Team!$I9)<=EOMONTH(I$69,0),IF(Team!$J9="",DATE(Settings!$B$3,12,31),Team!$J9)>=I$69),IF(Team!$G9="",Settings!$B$4,Team!$G9)*(1-N(Team!$H9)/12/Settings!$B$13),0)) -> 0.86428571 | J74: =IF($A74="","",IF(AND(IF(Team!$I9="",DATE(Settings!$B$3,1,1),Team!$I9)<=EOMONTH(J$69,0),IF(Team!$J9="",DATE(Settings!$B$3,12,31),Team!$J9)>=J$69),IF(Team!$G9="",Settings!$B$4,Team!$G9)*(1-N(Team!$H9)/12/Settings!$B$14),0)) -> 0.86428571 | K74: =IF($A74="","",IF(AND(IF(Team!$I9="",DATE(Settings!$B$3,1,1),Team!$I9)<=EOMONTH(K$69,0),IF(Team!$J9="",DATE(Settings!$B$3,12,31),Team!$J9)>=K$69),IF(Team!$G9="",Settings!$B$4,Team!$G9)*(1-N(Team!$H9)/12/Settings!$B$15),0)) -> 0.86590909 | L74: =IF($A74="","",IF(AND(IF(Team!$I9="",DATE(Settings!$B$3,1,1),Team!$I9)<=EOMONTH(L$69,0),IF(Team!$J9="",DATE(Settings!$B$3,12,31),Team!$J9)>=L$69),IF(Team!$G9="",Settings!$B$4,Team!$G9)*(1-N(Team!$H9)/12/Settings!$B$16),0)) -> 0.86428571 | M74: =IF($A74="","",IF(AND(IF(Team!$I9="",DATE(Settings!$B$3,1,1),Team!$I9)<=EOMONTH(M$69,0),IF(Team!$J9="",DATE(Settings!$B$3,12,31),Team!$J9)>=M$69),IF(Team!$G9="",Settings!$B$4,Team!$G9)*(1-N(Team!$H9)/12/Settings!$B$17),0)) -> 0.86428571 | N74: =IF($A74="","",IF(AND(IF(Team!$I9="",DATE(Settings!$B$3,1,1),Team!$I9)<=EOMONTH(N$69,0),IF(Team!$J9="",DATE(Settings!$B$3,12,31),Team!$J9)>=N$69),IF(Team!$G9="",Settings!$B$4,Team!$G9)*(1-N(Team!$H9)/12/Settings!$B$18),0)) -> 0.8625 | O74: =IF($A74="","",IF(AND(IF(Team!$I9="",DATE(Settings!$B$3,1,1),Team!$I9)<=EOMONTH(O$69,0),IF(Team!$J9="",DATE(Settings!$B$3,12,31),Team!$J9)>=O$69),IF(Team!$G9="",Settings!$B$4,Team!$G9)*(1-N(Team!$H9)/12/Settings!$B$19),0)) -> 0.86590909 | P74: =IF($A74="","",SUM(D74:O74)) -> 10.366832
A75: =IF(Team!$A10="","",Team!$A10) -> TBH Angular Dev | B75: =IF(Team!$A10="","",Team!$B10) -> Frontend Developer | C75: =IF(Team!$A10="","",Team!$C10) -> Open Req | D75: =IF($A75="","",IF(AND(IF(Team!$I10="",DATE(Settings!$B$3,1,1),Team!$I10)<=EOMONTH(D$69,0),IF(Team!$J10="",DATE(Settings!$B$3,12,31),Team!$J10)>=D$69),IF(Team!$G10="",Settings!$B$4,Team!$G10)*(1-N(Team!$H10)/12/Settings!$B$8),0)) -> 0 | E75: =IF($A75="","",IF(AND(IF(Team!$I10="",DATE(Settings!$B$3,1,1),Team!$I10)<=EOMONTH(E$69,0),IF(Team!$J10="",DATE(Settings!$B$3,12,31),Team!$J10)>=E$69),IF(Team!$G10="",Settings!$B$4,Team!$G10)*(1-N(Team!$H10)/12/Settings!$B$9),0)) -> 0 | F75: =IF($A75="","",IF(AND(IF(Team!$I10="",DATE(Settings!$B$3,1,1),Team!$I10)<=EOMONTH(F$69,0),IF(Team!$J10="",DATE(Settings!$B$3,12,31),Team!$J10)>=F$69),IF(Team!$G10="",Settings!$B$4,Team!$G10)*(1-N(Team!$H10)/12/Settings!$B$10),0)) -> 0 | G75: =IF($A75="","",IF(AND(IF(Team!$I10="",DATE(Settings!$B$3,1,1),Team!$I10)<=EOMONTH(G$69,0),IF(Team!$J10="",DATE(Settings!$B$3,12,31),Team!$J10)>=G$69),IF(Team!$G10="",Settings!$B$4,Team!$G10)*(1-N(Team!$H10)/12/Settings!$B$11),0)) -> 0.80170455 | H75: =IF($A75="","",IF(AND(IF(Team!$I10="",DATE(Settings!$B$3,1,1),Team!$I10)<=EOMONTH(H$69,0),IF(Team!$J10="",DATE(Settings!$B$3,12,31),Team!$J10)>=H$69),IF(Team!$G10="",Settings!$B$4,Team!$G10)*(1-N(Team!$H10)/12/Settings!$B$12),0)) -> 0.796875 | I75: =IF($A75="","",IF(AND(IF(Team!$I10="",DATE(Settings!$B$3,1,1),Team!$I10)<=EOMONTH(I$69,0),IF(Team!$J10="",DATE(Settings!$B$3,12,31),Team!$J10)>=I$69),IF(Team!$G10="",Settings!$B$4,Team!$G10)*(1-N(Team!$H10)/12/Settings!$B$13),0)) -> 0.79940476 | J75: =IF($A75="","",IF(AND(IF(Team!$I10="",DATE(Settings!$B$3,1,1),Team!$I10)<=EOMONTH(J$69,0),IF(Team!$J10="",DATE(Settings!$B$3,12,31),Team!$J10)>=J$69),IF(Team!$G10="",Settings!$B$4,Team!$G10)*(1-N(Team!$H10)/12/Settings!$B$14),0)) -> 0.79940476 | K75: =IF($A75="","",IF(AND(IF(Team!$I10="",DATE(Settings!$B$3,1,1),Team!$I10)<=EOMONTH(K$69,0),IF(Team!$J10="",DATE(Settings!$B$3,12,31),Team!$J10)>=K$69),IF(Team!$G10="",Settings!$B$4,Team!$G10)*(1-N(Team!$H10)/12/Settings!$B$15),0)) -> 0.80170455 | L75: =IF($A75="","",IF(AND(IF(Team!$I10="",DATE(Settings!$B$3,1,1),Team!$I10)<=EOMONTH(L$69,0),IF(Team!$J10="",DATE(Settings!$B$3,12,31),Team!$J10)>=L$69),IF(Team!$G10="",Settings!$B$4,Team!$G10)*(1-N(Team!$H10)/12/Settings!$B$16),0)) -> 0.79940476 | M75: =IF($A75="","",IF(AND(IF(Team!$I10="",DATE(Settings!$B$3,1,1),Team!$I10)<=EOMONTH(M$69,0),IF(Team!$J10="",DATE(Settings!$B$3,12,31),Team!$J10)>=M$69),IF(Team!$G10="",Settings!$B$4,Team!$G10)*(1-N(Team!$H10)/12/Settings!$B$17),0)) -> 0.79940476 | N75: =IF($A75="","",IF(AND(IF(Team!$I10="",DATE(Settings!$B$3,1,1),Team!$I10)<=EOMONTH(N$69,0),IF(Team!$J10="",DATE(Settings!$B$3,12,31),Team!$J10)>=N$69),IF(Team!$G10="",Settings!$B$4,Team!$G10)*(1-N(Team!$H10)/12/Settings!$B$18),0)) -> 0.796875 | O75: =IF($A75="","",IF(AND(IF(Team!$I10="",DATE(Settings!$B$3,1,1),Team!$I10)<=EOMONTH(O$69,0),IF(Team!$J10="",DATE(Settings!$B$3,12,31),Team!$J10)>=O$69),IF(Team!$G10="",Settings!$B$4,Team!$G10)*(1-N(Team!$H10)/12/Settings!$B$19),0)) -> 0.80170455 | P75: =IF($A75="","",SUM(D75:O75)) -> 7.1964827
A76: =IF(Team!$A11="","",Team!$A11) | B76: =IF(Team!$A11="","",Team!$B11) | C76: =IF(Team!$A11="","",Team!$C11) | D76: =IF($A76="","",IF(AND(IF(Team!$I11="",DATE(Settings!$B$3,1,1),Team!$I11)<=EOMONTH(D$69,0),IF(Team!$J11="",DATE(Settings!$B$3,12,31),Team!$J11)>=D$69),IF(Team!$G11="",Settings!$B$4,Team!$G11)*(1-N(Team!$H11)/12/Settings!$B$8),0)) | E76: =IF($A76="","",IF(AND(IF(Team!$I11="",DATE(Settings!$B$3,1,1),Team!$I11)<=EOMONTH(E$69,0),IF(Team!$J11="",DATE(Settings!$B$3,12,31),Team!$J11)>=E$69),IF(Team!$G11="",Settings!$B$4,Team!$G11)*(1-N(Team!$H11)/12/Settings!$B$9),0)) | F76: =IF($A76="","",IF(AND(IF(Team!$I11="",DATE(Settings!$B$3,1,1),Team!$I11)<=EOMONTH(F$69,0),IF(Team!$J11="",DATE(Settings!$B$3,12,31),Team!$J11)>=F$69),IF(Team!$G11="",Settings!$B$4,Team!$G11)*(1-N(Team!$H11)/12/Settings!$B$10),0)) | G76: =IF($A76="","",IF(AND(IF(Team!$I11="",DATE(Settings!$B$3,1,1),Team!$I11)<=EOMONTH(G$69,0),IF(Team!$J11="",DATE(Settings!$B$3,12,31),Team!$J11)>=G$69),IF(Team!$G11="",Settings!$B$4,Team!$G11)*(1-N(Team!$H11)/12/Settings!$B$11),0)) | H76: =IF($A76="","",IF(AND(IF(Team!$I11="",DATE(Settings!$B$3,1,1),Team!$I11)<=EOMONTH(H$69,0),IF(Team!$J11="",DATE(Settings!$B$3,12,31),Team!$J11)>=H$69),IF(Team!$G11="",Settings!$B$4,Team!$G11)*(1-N(Team!$H11)/12/Settings!$B$12),0)) | I76: =IF($A76="","",IF(AND(IF(Team!$I11="",DATE(Settings!$B$3,1,1),Team!$I11)<=EOMONTH(I$69,0),IF(Team!$J11="",DATE(Settings!$B$3,12,31),Team!$J11)>=I$69),IF(Team!$G11="",Settings!$B$4,Team!$G11)*(1-N(Team!$H11)/12/Settings!$B$13),0)) | J76: =IF($A76="","",IF(AND(IF(Team!$I11="",DATE(Settings!$B$3,1,1),Team!$I11)<=EOMONTH(J$69,0),IF(Team!$J11="",DATE(Settings!$B$3,12,31),Team!$J11)>=J$69),IF(Team!$G11="",Settings!$B$4,Team!$G11)*(1-N(Team!$H11)/12/Settings!$B$14),0)) | K76: =IF($A76="","",IF(AND(IF(Team!$I11="",DATE(Settings!$B$3,1,1),Team!$I11)<=EOMONTH(K$69,0),IF(Team!$J11="",DATE(Settings!$B$3,12,31),Team!$J11)>=K$69),IF(Team!$G11="",Settings!$B$4,Team!$G11)*(1-N(Team!$H11)/12/Settings!$B$15),0)) | L76: =IF($A76="","",IF(AND(IF(Team!$I11="",DATE(Settings!$B$3,1,1),Team!$I11)<=EOMONTH(L$69,0),IF(Team!$J11="",DATE(Settings!$B$3,12,31),Team!$J11)>=L$69),IF(Team!$G11="",Settings!$B$4,Team!$G11)*(1-N(Team!$H11)/12/Settings!$B$16),0)) | M76: =IF($A76="","",IF(AND(IF(Team!$I11="",DATE(Settings!$B$3,1,1),Team!$I11)<=EOMONTH(M$69,0),IF(Team!$J11="",DATE(Settings!$B$3,12,31),Team!$J11)>=M$69),IF(Team!$G11="",Settings!$B$4,Team!$G11)*(1-N(Team!$H11)/12/Settings!$B$17),0)) | N76: =IF($A76="","",IF(AND(IF(Team!$I11="",DATE(Settings!$B$3,1,1),Team!$I11)<=EOMONTH(N$69,0),IF(Team!$J11="",DATE(Settings!$B$3,12,31),Team!$J11)>=N$69),IF(Team!$G11="",Settings!$B$4,Team!$G11)*(1-N(Team!$H11)/12/Settings!$B$18),0)) | O76: =IF($A76="","",IF(AND(IF(Team!$I11="",DATE(Settings!$B$3,1,1),Team!$I11)<=EOMONTH(O$69,0),IF(Team!$J11="",DATE(Settings!$B$3,12,31),Team!$J11)>=O$69),IF(Team!$G11="",Settings!$B$4,Team!$G11)*(1-N(Team!$H11)/12/Settings!$B$19),0)) | P76: =IF($A76="","",SUM(D76:O76))
A77: =IF(Team!$A12="","",Team!$A12) | B77: =IF(Team!$A12="","",Team!$B12) | C77: =IF(Team!$A12="","",Team!$C12) | D77: =IF($A77="","",IF(AND(IF(Team!$I12="",DATE(Settings!$B$3,1,1),Team!$I12)<=EOMONTH(D$69,0),IF(Team!$J12="",DATE(Settings!$B$3,12,31),Team!$J12)>=D$69),IF(Team!$G12="",Settings!$B$4,Team!$G12)*(1-N(Team!$H12)/12/Settings!$B$8),0)) | E77: =IF($A77="","",IF(AND(IF(Team!$I12="",DATE(Settings!$B$3,1,1),Team!$I12)<=EOMONTH(E$69,0),IF(Team!$J12="",DATE(Settings!$B$3,12,31),Team!$J12)>=E$69),IF(Team!$G12="",Settings!$B$4,Team!$G12)*(1-N(Team!$H12)/12/Settings!$B$9),0)) | F77: =IF($A77="","",IF(AND(IF(Team!$I12="",DATE(Settings!$B$3,1,1),Team!$I12)<=EOMONTH(F$69,0),IF(Team!$J12="",DATE(Settings!$B$3,12,31),Team!$J12)>=F$69),IF(Team!$G12="",Settings!$B$4,Team!$G12)*(1-N(Team!$H12)/12/Settings!$B$10),0)) | G77: =IF($A77="","",IF(AND(IF(Team!$I12="",DATE(Settings!$B$3,1,1),Team!$I12)<=EOMONTH(G$69,0),IF(Team!$J12="",DATE(Settings!$B$3,12,31),Team!$J12)>=G$69),IF(Team!$G12="",Settings!$B$4,Team!$G12)*(1-N(Team!$H12)/12/Settings!$B$11),0)) | H77: =IF($A77="","",IF(AND(IF(Team!$I12="",DATE(Settings!$B$3,1,1),Team!$I12)<=EOMONTH(H$69,0),IF(Team!$J12="",DATE(Settings!$B$3,12,31),Team!$J12)>=H$69),IF(Team!$G12="",Settings!$B$4,Team!$G12)*(1-N(Team!$H12)/12/Settings!$B$12),0)) | I77: =IF($A77="","",IF(AND(IF(Team!$I12="",DATE(Settings!$B$3,1,1),Team!$I12)<=EOMONTH(I$69,0),IF(Team!$J12="",DATE(Settings!$B$3,12,31),Team!$J12)>=I$69),IF(Team!$G12="",Settings!$B$4,Team!$G12)*(1-N(Team!$H12)/12/Settings!$B$13),0)) | J77: =IF($A77="","",IF(AND(IF(Team!$I12="",DATE(Settings!$B$3,1,1),Team!$I12)<=EOMONTH(J$69,0),IF(Team!$J12="",DATE(Settings!$B$3,12,31),Team!$J12)>=J$69),IF(Team!$G12="",Settings!$B$4,Team!$G12)*(1-N(Team!$H12)/12/Settings!$B$14),0)) | K77: =IF($A77="","",IF(AND(IF(Team!$I12="",DATE(Settings!$B$3,1,1),Team!$I12)<=EOMONTH(K$69,0),IF(Team!$J12="",DATE(Settings!$B$3,12,31),Team!$J12)>=K$69),IF(Team!$G12="",Settings!$B$4,Team!$G12)*(1-N(Team!$H12)/12/Settings!$B$15),0)) | L77: =IF($A77="","",IF(AND(IF(Team!$I12="",DATE(Settings!$B$3,1,1),Team!$I12)<=EOMONTH(L$69,0),IF(Team!$J12="",DATE(Settings!$B$3,12,31),Team!$J12)>=L$69),IF(Team!$G12="",Settings!$B$4,Team!$G12)*(1-N(Team!$H12)/12/Settings!$B$16),0)) | M77: =IF($A77="","",IF(AND(IF(Team!$I12="",DATE(Settings!$B$3,1,1),Team!$I12)<=EOMONTH(M$69,0),IF(Team!$J12="",DATE(Settings!$B$3,12,31),Team!$J12)>=M$69),IF(Team!$G12="",Settings!$B$4,Team!$G12)*(1-N(Team!$H12)/12/Settings!$B$17),0)) | N77: =IF($A77="","",IF(AND(IF(Team!$I12="",DATE(Settings!$B$3,1,1),Team!$I12)<=EOMONTH(N$69,0),IF(Team!$J12="",DATE(Settings!$B$3,12,31),Team!$J12)>=N$69),IF(Team!$G12="",Settings!$B$4,Team!$G12)*(1-N(Team!$H12)/12/Settings!$B$18),0)) | O77: =IF($A77="","",IF(AND(IF(Team!$I12="",DATE(Settings!$B$3,1,1),Team!$I12)<=EOMONTH(O$69,0),IF(Team!$J12="",DATE(Settings!$B$3,12,31),Team!$J12)>=O$69),IF(Team!$G12="",Settings!$B$4,Team!$G12)*(1-N(Team!$H12)/12/Settings!$B$19),0)) | P77: =IF($A77="","",SUM(D77:O77))
A78: =IF(Team!$A13="","",Team!$A13) | B78: =IF(Team!$A13="","",Team!$B13) | C78: =IF(Team!$A13="","",Team!$C13) | D78: =IF($A78="","",IF(AND(IF(Team!$I13="",DATE(Settings!$B$3,1,1),Team!$I13)<=EOMONTH(D$69,0),IF(Team!$J13="",DATE(Settings!$B$3,12,31),Team!$J13)>=D$69),IF(Team!$G13="",Settings!$B$4,Team!$G13)*(1-N(Team!$H13)/12/Settings!$B$8),0)) | E78: =IF($A78="","",IF(AND(IF(Team!$I13="",DATE(Settings!$B$3,1,1),Team!$I13)<=EOMONTH(E$69,0),IF(Team!$J13="",DATE(Settings!$B$3,12,31),Team!$J13)>=E$69),IF(Team!$G13="",Settings!$B$4,Team!$G13)*(1-N(Team!$H13)/12/Settings!$B$9),0)) | F78: =IF($A78="","",IF(AND(IF(Team!$I13="",DATE(Settings!$B$3,1,1),Team!$I13)<=EOMONTH(F$69,0),IF(Team!$J13="",DATE(Settings!$B$3,12,31),Team!$J13)>=F$69),IF(Team!$G13="",Settings!$B$4,Team!$G13)*(1-N(Team!$H13)/12/Settings!$B$10),0)) | G78: =IF($A78="","",IF(AND(IF(Team!$I13="",DATE(Settings!$B$3,1,1),Team!$I13)<=EOMONTH(G$69,0),IF(Team!$J13="",DATE(Settings!$B$3,12,31),Team!$J13)>=G$69),IF(Team!$G13="",Settings!$B$4,Team!$G13)*(1-N(Team!$H13)/12/Settings!$B$11),0)) | H78: =IF($A78="","",IF(AND(IF(Team!$I13="",DATE(Settings!$B$3,1,1),Team!$I13)<=EOMONTH(H$69,0),IF(Team!$J13="",DATE(Settings!$B$3,12,31),Team!$J13)>=H$69),IF(Team!$G13="",Settings!$B$4,Team!$G13)*(1-N(Team!$H13)/12/Settings!$B$12),0)) | I78: =IF($A78="","",IF(AND(IF(Team!$I13="",DATE(Settings!$B$3,1,1),Team!$I13)<=EOMONTH(I$69,0),IF(Team!$J13="",DATE(Settings!$B$3,12,31),Team!$J13)>=I$69),IF(Team!$G13="",Settings!$B$4,Team!$G13)*(1-N(Team!$H13)/12/Settings!$B$13),0)) | J78: =IF($A78="","",IF(AND(IF(Team!$I13="",DATE(Settings!$B$3,1,1),Team!$I13)<=EOMONTH(J$69,0),IF(Team!$J13="",DATE(Settings!$B$3,12,31),Team!$J13)>=J$69),IF(Team!$G13="",Settings!$B$4,Team!$G13)*(1-N(Team!$H13)/12/Settings!$B$14),0)) | K78: =IF($A78="","",IF(AND(IF(Team!$I13="",DATE(Settings!$B$3,1,1),Team!$I13)<=EOMONTH(K$69,0),IF(Team!$J13="",DATE(Settings!$B$3,12,31),Team!$J13)>=K$69),IF(Team!$G13="",Settings!$B$4,Team!$G13)*(1-N(Team!$H13)/12/Settings!$B$15),0)) | L78: =IF($A78="","",IF(AND(IF(Team!$I13="",DATE(Settings!$B$3,1,1),Team!$I13)<=EOMONTH(L$69,0),IF(Team!$J13="",DATE(Settings!$B$3,12,31),Team!$J13)>=L$69),IF(Team!$G13="",Settings!$B$4,Team!$G13)*(1-N(Team!$H13)/12/Settings!$B$16),0)) | M78: =IF($A78="","",IF(AND(IF(Team!$I13="",DATE(Settings!$B$3,1,1),Team!$I13)<=EOMONTH(M$69,0),IF(Team!$J13="",DATE(Settings!$B$3,12,31),Team!$J13)>=M$69),IF(Team!$G13="",Settings!$B$4,Team!$G13)*(1-N(Team!$H13)/12/Settings!$B$17),0)) | N78: =IF($A78="","",IF(AND(IF(Team!$I13="",DATE(Settings!$B$3,1,1),Team!$I13)<=EOMONTH(N$69,0),IF(Team!$J13="",DATE(Settings!$B$3,12,31),Team!$J13)>=N$69),IF(Team!$G13="",Settings!$B$4,Team!$G13)*(1-N(Team!$H13)/12/Settings!$B$18),0)) | O78: =IF($A78="","",IF(AND(IF(Team!$I13="",DATE(Settings!$B$3,1,1),Team!$I13)<=EOMONTH(O$69,0),IF(Team!$J13="",DATE(Settings!$B$3,12,31),Team!$J13)>=O$69),IF(Team!$G13="",Settings!$B$4,Team!$G13)*(1-N(Team!$H13)/12/Settings!$B$19),0)) | P78: =IF($A78="","",SUM(D78:O78))
A79: =IF(Team!$A14="","",Team!$A14) | B79: =IF(Team!$A14="","",Team!$B14) | C79: =IF(Team!$A14="","",Team!$C14) | D79: =IF($A79="","",IF(AND(IF(Team!$I14="",DATE(Settings!$B$3,1,1),Team!$I14)<=EOMONTH(D$69,0),IF(Team!$J14="",DATE(Settings!$B$3,12,31),Team!$J14)>=D$69),IF(Team!$G14="",Settings!$B$4,Team!$G14)*(1-N(Team!$H14)/12/Settings!$B$8),0)) | E79: =IF($A79="","",IF(AND(IF(Team!$I14="",DATE(Settings!$B$3,1,1),Team!$I14)<=EOMONTH(E$69,0),IF(Team!$J14="",DATE(Settings!$B$3,12,31),Team!$J14)>=E$69),IF(Team!$G14="",Settings!$B$4,Team!$G14)*(1-N(Team!$H14)/12/Settings!$B$9),0)) | F79: =IF($A79="","",IF(AND(IF(Team!$I14="",DATE(Settings!$B$3,1,1),Team!$I14)<=EOMONTH(F$69,0),IF(Team!$J14="",DATE(Settings!$B$3,12,31),Team!$J14)>=F$69),IF(Team!$G14="",Settings!$B$4,Team!$G14)*(1-N(Team!$H14)/12/Settings!$B$10),0)) | G79: =IF($A79="","",IF(AND(IF(Team!$I14="",DATE(Settings!$B$3,1,1),Team!$I14)<=EOMONTH(G$69,0),IF(Team!$J14="",DATE(Settings!$B$3,12,31),Team!$J14)>=G$69),IF(Team!$G14="",Settings!$B$4,Team!$G14)*(1-N(Team!$H14)/12/Settings!$B$11),0)) | H79: =IF($A79="","",IF(AND(IF(Team!$I14="",DATE(Settings!$B$3,1,1),Team!$I14)<=EOMONTH(H$69,0),IF(Team!$J14="",DATE(Settings!$B$3,12,31),Team!$J14)>=H$69),IF(Team!$G14="",Settings!$B$4,Team!$G14)*(1-N(Team!$H14)/12/Settings!$B$12),0)) | I79: =IF($A79="","",IF(AND(IF(Team!$I14="",DATE(Settings!$B$3,1,1),Team!$I14)<=EOMONTH(I$69,0),IF(Team!$J14="",DATE(Settings!$B$3,12,31),Team!$J14)>=I$69),IF(Team!$G14="",Settings!$B$4,Team!$G14)*(1-N(Team!$H14)/12/Settings!$B$13),0)) | J79: =IF($A79="","",IF(AND(IF(Team!$I14="",DATE(Settings!$B$3,1,1),Team!$I14)<=EOMONTH(J$69,0),IF(Team!$J14="",DATE(Settings!$B$3,12,31),Team!$J14)>=J$69),IF(Team!$G14="",Settings!$B$4,Team!$G14)*(1-N(Team!$H14)/12/Settings!$B$14),0)) | K79: =IF($A79="","",IF(AND(IF(Team!$I14="",DATE(Settings!$B$3,1,1),Team!$I14)<=EOMONTH(K$69,0),IF(Team!$J14="",DATE(Settings!$B$3,12,31),Team!$J14)>=K$69),IF(Team!$G14="",Settings!$B$4,Team!$G14)*(1-N(Team!$H14)/12/Settings!$B$15),0)) | L79: =IF($A79="","",IF(AND(IF(Team!$I14="",DATE(Settings!$B$3,1,1),Team!$I14)<=EOMONTH(L$69,0),IF(Team!$J14="",DATE(Settings!$B$3,12,31),Team!$J14)>=L$69),IF(Team!$G14="",Settings!$B$4,Team!$G14)*(1-N(Team!$H14)/12/Settings!$B$16),0)) | M79: =IF($A79="","",IF(AND(IF(Team!$I14="",DATE(Settings!$B$3,1,1),Team!$I14)<=EOMONTH(M$69,0),IF(Team!$J14="",DATE(Settings!$B$3,12,31),Team!$J14)>=M$69),IF(Team!$G14="",Settings!$B$4,Team!$G14)*(1-N(Team!$H14)/12/Settings!$B$17),0)) | N79: =IF($A79="","",IF(AND(IF(Team!$I14="",DATE(Settings!$B$3,1,1),Team!$I14)<=EOMONTH(N$69,0),IF(Team!$J14="",DATE(Settings!$B$3,12,31),Team!$J14)>=N$69),IF(Team!$G14="",Settings!$B$4,Team!$G14)*(1-N(Team!$H14)/12/Settings!$B$18),0)) | O79: =IF($A79="","",IF(AND(IF(Team!$I14="",DATE(Settings!$B$3,1,1),Team!$I14)<=EOMONTH(O$69,0),IF(Team!$J14="",DATE(Settings!$B$3,12,31),Team!$J14)>=O$69),IF(Team!$G14="",Settings!$B$4,Team!$G14)*(1-N(Team!$H14)/12/Settings!$B$19),0)) | P79: =IF($A79="","",SUM(D79:O79))
A80: =IF(Team!$A15="","",Team!$A15) | B80: =IF(Team!$A15="","",Team!$B15) | C80: =IF(Team!$A15="","",Team!$C15) | D80: =IF($A80="","",IF(AND(IF(Team!$I15="",DATE(Settings!$B$3,1,1),Team!$I15)<=EOMONTH(D$69,0),IF(Team!$J15="",DATE(Settings!$B$3,12,31),Team!$J15)>=D$69),IF(Team!$G15="",Settings!$B$4,Team!$G15)*(1-N(Team!$H15)/12/Settings!$B$8),0)) | E80: =IF($A80="","",IF(AND(IF(Team!$I15="",DATE(Settings!$B$3,1,1),Team!$I15)<=EOMONTH(E$69,0),IF(Team!$J15="",DATE(Settings!$B$3,12,31),Team!$J15)>=E$69),IF(Team!$G15="",Settings!$B$4,Team!$G15)*(1-N(Team!$H15)/12/Settings!$B$9),0)) | F80: =IF($A80="","",IF(AND(IF(Team!$I15="",DATE(Settings!$B$3,1,1),Team!$I15)<=EOMONTH(F$69,0),IF(Team!$J15="",DATE(Settings!$B$3,12,31),Team!$J15)>=F$69),IF(Team!$G15="",Settings!$B$4,Team!$G15)*(1-N(Team!$H15)/12/Settings!$B$10),0)) | G80: =IF($A80="","",IF(AND(IF(Team!$I15="",DATE(Settings!$B$3,1,1),Team!$I15)<=EOMONTH(G$69,0),IF(Team!$J15="",DATE(Settings!$B$3,12,31),Team!$J15)>=G$69),IF(Team!$G15="",Settings!$B$4,Team!$G15)*(1-N(Team!$H15)/12/Settings!$B$11),0)) | H80: =IF($A80="","",IF(AND(IF(Team!$I15="",DATE(Settings!$B$3,1,1),Team!$I15)<=EOMONTH(H$69,0),IF(Team!$J15="",DATE(Settings!$B$3,12,31),Team!$J15)>=H$69),IF(Team!$G15="",Settings!$B$4,Team!$G15)*(1-N(Team!$H15)/12/Settings!$B$12),0)) | I80: =IF($A80="","",IF(AND(IF(Team!$I15="",DATE(Settings!$B$3,1,1),Team!$I15)<=EOMONTH(I$69,0),IF(Team!$J15="",DATE(Settings!$B$3,12,31),Team!$J15)>=I$69),IF(Team!$G15="",Settings!$B$4,Team!$G15)*(1-N(Team!$H15)/12/Settings!$B$13),0)) | J80: =IF($A80="","",IF(AND(IF(Team!$I15="",DATE(Settings!$B$3,1,1),Team!$I15)<=EOMONTH(J$69,0),IF(Team!$J15="",DATE(Settings!$B$3,12,31),Team!$J15)>=J$69),IF(Team!$G15="",Settings!$B$4,Team!$G15)*(1-N(Team!$H15)/12/Settings!$B$14),0)) | K80: =IF($A80="","",IF(AND(IF(Team!$I15="",DATE(Settings!$B$3,1,1),Team!$I15)<=EOMONTH(K$69,0),IF(Team!$J15="",DATE(Settings!$B$3,12,31),Team!$J15)>=K$69),IF(Team!$G15="",Settings!$B$4,Team!$G15)*(1-N(Team!$H15)/12/Settings!$B$15),0)) | L80: =IF($A80="","",IF(AND(IF(Team!$I15="",DATE(Settings!$B$3,1,1),Team!$I15)<=EOMONTH(L$69,0),IF(Team!$J15="",DATE(Settings!$B$3,12,31),Team!$J15)>=L$69),IF(Team!$G15="",Settings!$B$4,Team!$G15)*(1-N(Team!$H15)/12/Settings!$B$16),0)) | M80: =IF($A80="","",IF(AND(IF(Team!$I15="",DATE(Settings!$B$3,1,1),Team!$I15)<=EOMONTH(M$69,0),IF(Team!$J15="",DATE(Settings!$B$3,12,31),Team!$J15)>=M$69),IF(Team!$G15="",Settings!$B$4,Team!$G15)*(1-N(Team!$H15)/12/Settings!$B$17),0)) | N80: =IF($A80="","",IF(AND(IF(Team!$I15="",DATE(Settings!$B$3,1,1),Team!$I15)<=EOMONTH(N$69,0),IF(Team!$J15="",DATE(Settings!$B$3,12,31),Team!$J15)>=N$69),IF(Team!$G15="",Settings!$B$4,Team!$G15)*(1-N(Team!$H15)/12/Settings!$B$18),0)) | O80: =IF($A80="","",IF(AND(IF(Team!$I15="",DATE(Settings!$B$3,1,1),Team!$I15)<=EOMONTH(O$69,0),IF(Team!$J15="",DATE(Settings!$B$3,12,31),Team!$J15)>=O$69),IF(Team!$G15="",Settings!$B$4,Team!$G15)*(1-N(Team!$H15)/12/Settings!$B$19),0)) | P80: =IF($A80="","",SUM(D80:O80))
A81: =IF(Team!$A16="","",Team!$A16) | B81: =IF(Team!$A16="","",Team!$B16) | C81: =IF(Team!$A16="","",Team!$C16) | D81: =IF($A81="","",IF(AND(IF(Team!$I16="",DATE(Settings!$B$3,1,1),Team!$I16)<=EOMONTH(D$69,0),IF(Team!$J16="",DATE(Settings!$B$3,12,31),Team!$J16)>=D$69),IF(Team!$G16="",Settings!$B$4,Team!$G16)*(1-N(Team!$H16)/12/Settings!$B$8),0)) | E81: =IF($A81="","",IF(AND(IF(Team!$I16="",DATE(Settings!$B$3,1,1),Team!$I16)<=EOMONTH(E$69,0),IF(Team!$J16="",DATE(Settings!$B$3,12,31),Team!$J16)>=E$69),IF(Team!$G16="",Settings!$B$4,Team!$G16)*(1-N(Team!$H16)/12/Settings!$B$9),0)) | F81: =IF($A81="","",IF(AND(IF(Team!$I16="",DATE(Settings!$B$3,1,1),Team!$I16)<=EOMONTH(F$69,0),IF(Team!$J16="",DATE(Settings!$B$3,12,31),Team!$J16)>=F$69),IF(Team!$G16="",Settings!$B$4,Team!$G16)*(1-N(Team!$H16)/12/Settings!$B$10),0)) | G81: =IF($A81="","",IF(AND(IF(Team!$I16="",DATE(Settings!$B$3,1,1),Team!$I16)<=EOMONTH(G$69,0),IF(Team!$J16="",DATE(Settings!$B$3,12,31),Team!$J16)>=G$69),IF(Team!$G16="",Settings!$B$4,Team!$G16)*(1-N(Team!$H16)/12/Settings!$B$11),0)) | H81: =IF($A81="","",IF(AND(IF(Team!$I16="",DATE(Settings!$B$3,1,1),Team!$I16)<=EOMONTH(H$69,0),IF(Team!$J16="",DATE(Settings!$B$3,12,31),Team!$J16)>=H$69),IF(Team!$G16="",Settings!$B$4,Team!$G16)*(1-N(Team!$H16)/12/Settings!$B$12),0)) | I81: =IF($A81="","",IF(AND(IF(Team!$I16="",DATE(Settings!$B$3,1,1),Team!$I16)<=EOMONTH(I$69,0),IF(Team!$J16="",DATE(Settings!$B$3,12,31),Team!$J16)>=I$69),IF(Team!$G16="",Settings!$B$4,Team!$G16)*(1-N(Team!$H16)/12/Settings!$B$13),0)) | J81: =IF($A81="","",IF(AND(IF(Team!$I16="",DATE(Settings!$B$3,1,1),Team!$I16)<=EOMONTH(J$69,0),IF(Team!$J16="",DATE(Settings!$B$3,12,31),Team!$J16)>=J$69),IF(Team!$G16="",Settings!$B$4,Team!$G16)*(1-N(Team!$H16)/12/Settings!$B$14),0)) | K81: =IF($A81="","",IF(AND(IF(Team!$I16="",DATE(Settings!$B$3,1,1),Team!$I16)<=EOMONTH(K$69,0),IF(Team!$J16="",DATE(Settings!$B$3,12,31),Team!$J16)>=K$69),IF(Team!$G16="",Settings!$B$4,Team!$G16)*(1-N(Team!$H16)/12/Settings!$B$15),0)) | L81: =IF($A81="","",IF(AND(IF(Team!$I16="",DATE(Settings!$B$3,1,1),Team!$I16)<=EOMONTH(L$69,0),IF(Team!$J16="",DATE(Settings!$B$3,12,31),Team!$J16)>=L$69),IF(Team!$G16="",Settings!$B$4,Team!$G16)*(1-N(Team!$H16)/12/Settings!$B$16),0)) | M81: =IF($A81="","",IF(AND(IF(Team!$I16="",DATE(Settings!$B$3,1,1),Team!$I16)<=EOMONTH(M$69,0),IF(Team!$J16="",DATE(Settings!$B$3,12,31),Team!$J16)>=M$69),IF(Team!$G16="",Settings!$B$4,Team!$G16)*(1-N(Team!$H16)/12/Settings!$B$17),0)) | N81: =IF($A81="","",IF(AND(IF(Team!$I16="",DATE(Settings!$B$3,1,1),Team!$I16)<=EOMONTH(N$69,0),IF(Team!$J16="",DATE(Settings!$B$3,12,31),Team!$J16)>=N$69),IF(Team!$G16="",Settings!$B$4,Team!$G16)*(1-N(Team!$H16)/12/Settings!$B$18),0)) | O81: =IF($A81="","",IF(AND(IF(Team!$I16="",DATE(Settings!$B$3,1,1),Team!$I16)<=EOMONTH(O$69,0),IF(Team!$J16="",DATE(Settings!$B$3,12,31),Team!$J16)>=O$69),IF(Team!$G16="",Settings!$B$4,Team!$G16)*(1-N(Team!$H16)/12/Settings!$B$19),0)) | P81: =IF($A81="","",SUM(D81:O81))
... A129: =IF(Team!$A64="","",Team!$A64) | B129: =IF(Team!$A64="","",Team!$B64) | C129: =IF(Team!$A64="","",Team!$C64) | D129: =IF($A129="","",IF(AND(IF(Team!$I64="",DATE(Settings!$B$3,1,1),Team!$I64)<=EOMONTH(D$69,0),IF(Team!$J64="",DATE(Settings!$B$3,12,31),Team!$J64)>=D$69),IF(Team!$G64="",Settings!$B$4,Team!$G64)*(1-N(Team!$H64)/12/Settings!$B$8),0)) | E129: =IF($A129="","",IF(AND(IF(Team!$I64="",DATE(Settings!$B$3,1,1),Team!$I64)<=EOMONTH(E$69,0),IF(Team!$J64="",DATE(Settings!$B$3,12,31),Team!$J64)>=E$69),IF(Team!$G64="",Settings!$B$4,Team!$G64)*(1-N(Team!$H64)/12/Settings!$B$9),0)) | F129: =IF($A129="","",IF(AND(IF(Team!$I64="",DATE(Settings!$B$3,1,1),Team!$I64)<=EOMONTH(F$69,0),IF(Team!$J64="",DATE(Settings!$B$3,12,31),Team!$J64)>=F$69),IF(Team!$G64="",Settings!$B$4,Team!$G64)*(1-N(Team!$H64)/12/Settings!$B$10),0)) | G129: =IF($A129="","",IF(AND(IF(Team!$I64="",DATE(Settings!$B$3,1,1),Team!$I64)<=EOMONTH(G$69,0),IF(Team!$J64="",DATE(Settings!$B$3,12,31),Team!$J64)>=G$69),IF(Team!$G64="",Settings!$B$4,Team!$G64)*(1-N(Team!$H64)/12/Settings!$B$11),0)) | H129: =IF($A129="","",IF(AND(IF(Team!$I64="",DATE(Settings!$B$3,1,1),Team!$I64)<=EOMONTH(H$69,0),IF(Team!$J64="",DATE(Settings!$B$3,12,31),Team!$J64)>=H$69),IF(Team!$G64="",Settings!$B$4,Team!$G64)*(1-N(Team!$H64)/12/Settings!$B$12),0)) | I129: =IF($A129="","",IF(AND(IF(Team!$I64="",DATE(Settings!$B$3,1,1),Team!$I64)<=EOMONTH(I$69,0),IF(Team!$J64="",DATE(Settings!$B$3,12,31),Team!$J64)>=I$69),IF(Team!$G64="",Settings!$B$4,Team!$G64)*(1-N(Team!$H64)/12/Settings!$B$13),0)) | J129: =IF($A129="","",IF(AND(IF(Team!$I64="",DATE(Settings!$B$3,1,1),Team!$I64)<=EOMONTH(J$69,0),IF(Team!$J64="",DATE(Settings!$B$3,12,31),Team!$J64)>=J$69),IF(Team!$G64="",Settings!$B$4,Team!$G64)*(1-N(Team!$H64)/12/Settings!$B$14),0)) | K129: =IF($A129="","",IF(AND(IF(Team!$I64="",DATE(Settings!$B$3,1,1),Team!$I64)<=EOMONTH(K$69,0),IF(Team!$J64="",DATE(Settings!$B$3,12,31),Team!$J64)>=K$69),IF(Team!$G64="",Settings!$B$4,Team!$G64)*(1-N(Team!$H64)/12/Settings!$B$15),0)) | L129: =IF($A129="","",IF(AND(IF(Team!$I64="",DATE(Settings!$B$3,1,1),Team!$I64)<=EOMONTH(L$69,0),IF(Team!$J64="",DATE(Settings!$B$3,12,31),Team!$J64)>=L$69),IF(Team!$G64="",Settings!$B$4,Team!$G64)*(1-N(Team!$H64)/12/Settings!$B$16),0)) | M129: =IF($A129="","",IF(AND(IF(Team!$I64="",DATE(Settings!$B$3,1,1),Team!$I64)<=EOMONTH(M$69,0),IF(Team!$J64="",DATE(Settings!$B$3,12,31),Team!$J64)>=M$69),IF(Team!$G64="",Settings!$B$4,Team!$G64)*(1-N(Team!$H64)/12/Settings!$B$17),0)) | N129: =IF($A129="","",IF(AND(IF(Team!$I64="",DATE(Settings!$B$3,1,1),Team!$I64)<=EOMONTH(N$69,0),IF(Team!$J64="",DATE(Settings!$B$3,12,31),Team!$J64)>=N$69),IF(Team!$G64="",Settings!$B$4,Team!$G64)*(1-N(Team!$H64)/12/Settings!$B$18),0)) | O129: =IF($A129="","",IF(AND(IF(Team!$I64="",DATE(Settings!$B$3,1,1),Team!$I64)<=EOMONTH(O$69,0),IF(Team!$J64="",DATE(Settings!$B$3,12,31),Team!$J64)>=O$69),IF(Team!$G64="",Settings!$B$4,Team!$G64)*(1-N(Team!$H64)/12/Settings!$B$19),0)) | P129: =IF($A129="","",SUM(D129:O129))
A132: Allocated (FTE per month, from Allocation)
A133: Name | B133: Role | C133: Type | D133: =Settings!$A$8 -> 46388 | E133: =Settings!$A$9 -> 46419 | F133: =Settings!$A$10 -> 46447 | G133: =Settings!$A$11 -> 46478 | H133: =Settings!$A$12 -> 46508 | I133: =Settings!$A$13 -> 46539 | J133: =Settings!$A$14 -> 46569 | K133: =Settings!$A$15 -> 46600 | L133: =Settings!$A$16 -> 46631 | M133: =Settings!$A$17 -> 46661 | N133: =Settings!$A$18 -> 46692 | O133: =Settings!$A$19 -> 46722 | P133: Total FTE-mo
A134: =IF(Team!$A5="","",Team!$A5) -> Tech Lead 1 | B134: =IF(Team!$A5="","",Team!$B5) -> Tech Lead | C134: =IF(Team!$A5="","",Team!$C5) -> FTE | D134: =IF($A134="","",SUMIFS(Allocation!E$5:E$204,Allocation!$A$5:$A$204,$A134)) -> 0.8 | E134: =IF($A134="","",SUMIFS(Allocation!F$5:F$204,Allocation!$A$5:$A$204,$A134)) -> 0.8 | F134: =IF($A134="","",SUMIFS(Allocation!G$5:G$204,Allocation!$A$5:$A$204,$A134)) -> 1 | G134: =IF($A134="","",SUMIFS(Allocation!H$5:H$204,Allocation!$A$5:$A$204,$A134)) -> 1 | H134: =IF($A134="","",SUMIFS(Allocation!I$5:I$204,Allocation!$A$5:$A$204,$A134)) -> 0.8 | I134: =IF($A134="","",SUMIFS(Allocation!J$5:J$204,Allocation!$A$5:$A$204,$A134)) -> 0.8 | J134: =IF($A134="","",SUMIFS(Allocation!K$5:K$204,Allocation!$A$5:$A$204,$A134)) -> 0.8 | K134: =IF($A134="","",SUMIFS(Allocation!L$5:L$204,Allocation!$A$5:$A$204,$A134)) -> 0.8 | ... O134: =IF($A134="","",SUMIFS(Allocation!P$5:P$204,Allocation!$A$5:$A$204,$A134)) -> 0.6 | P134: =IF($A134="","",SUM(D134:O134)) -> 9.2
A135: =IF(Team!$A6="","",Team!$A6) -> Java Dev 1 | B135: =IF(Team!$A6="","",Team!$B6) -> Backend Developer | C135: =IF(Team!$A6="","",Team!$C6) -> FTE | D135: =IF($A135="","",SUMIFS(Allocation!E$5:E$204,Allocation!$A$5:$A$204,$A135)) -> 0.5 | E135: =IF($A135="","",SUMIFS(Allocation!F$5:F$204,Allocation!$A$5:$A$204,$A135)) -> 0.5 | F135: =IF($A135="","",SUMIFS(Allocation!G$5:G$204,Allocation!$A$5:$A$204,$A135)) -> 0.9 | G135: =IF($A135="","",SUMIFS(Allocation!H$5:H$204,Allocation!$A$5:$A$204,$A135)) -> 0.9 | H135: =IF($A135="","",SUMIFS(Allocation!I$5:I$204,Allocation!$A$5:$A$204,$A135)) -> 0.9 | I135: =IF($A135="","",SUMIFS(Allocation!J$5:J$204,Allocation!$A$5:$A$204,$A135)) -> 0.9 | J135: =IF($A135="","",SUMIFS(Allocation!K$5:K$204,Allocation!$A$5:$A$204,$A135)) -> 0.9 | K135: =IF($A135="","",SUMIFS(Allocation!L$5:L$204,Allocation!$A$5:$A$204,$A135)) -> 0.9 | ... O135: =IF($A135="","",SUMIFS(Allocation!P$5:P$204,Allocation!$A$5:$A$204,$A135)) -> 0.5 | P135: =IF($A135="","",SUM(D135:O135)) -> 8.4
A136: =IF(Team!$A7="","",Team!$A7) -> Angular Dev 1 | B136: =IF(Team!$A7="","",Team!$B7) -> Frontend Developer | C136: =IF(Team!$A7="","",Team!$C7) -> Contractor | D136: =IF($A136="","",SUMIFS(Allocation!E$5:E$204,Allocation!$A$5:$A$204,$A136)) -> 0.9 | E136: =IF($A136="","",SUMIFS(Allocation!F$5:F$204,Allocation!$A$5:$A$204,$A136)) -> 0.9 | F136: =IF($A136="","",SUMIFS(Allocation!G$5:G$204,Allocation!$A$5:$A$204,$A136)) -> 0.9 | G136: =IF($A136="","",SUMIFS(Allocation!H$5:H$204,Allocation!$A$5:$A$204,$A136)) -> 0.9 | H136: =IF($A136="","",SUMIFS(Allocation!I$5:I$204,Allocation!$A$5:$A$204,$A136)) -> 0.9 | I136: =IF($A136="","",SUMIFS(Allocation!J$5:J$204,Allocation!$A$5:$A$204,$A136)) -> 0.9 | J136: =IF($A136="","",SUMIFS(Allocation!K$5:K$204,Allocation!$A$5:$A$204,$A136)) -> 0.9 | K136: =IF($A136="","",SUMIFS(Allocation!L$5:L$204,Allocation!$A$5:$A$204,$A136)) -> 0.9 | ... O136: =IF($A136="","",SUMIFS(Allocation!P$5:P$204,Allocation!$A$5:$A$204,$A136)) -> 0.9 | P136: =IF($A136="","",SUM(D136:O136)) -> 10.8
A137: =IF(Team!$A8="","",Team!$A8) -> Angular Dev 2 | B137: =IF(Team!$A8="","",Team!$B8) -> Full-stack Developer | C137: =IF(Team!$A8="","",Team!$C8) -> Contractor | D137: =IF($A137="","",SUMIFS(Allocation!E$5:E$204,Allocation!$A$5:$A$204,$A137)) -> 0.9 | E137: =IF($A137="","",SUMIFS(Allocation!F$5:F$204,Allocation!$A$5:$A$204,$A137)) -> 0.9 | F137: =IF($A137="","",SUMIFS(Allocation!G$5:G$204,Allocation!$A$5:$A$204,$A137)) -> 0.9 | G137: =IF($A137="","",SUMIFS(Allocation!H$5:H$204,Allocation!$A$5:$A$204,$A137)) -> 0.9 | H137: =IF($A137="","",SUMIFS(Allocation!I$5:I$204,Allocation!$A$5:$A$204,$A137)) -> 0.5 | I137: =IF($A137="","",SUMIFS(Allocation!J$5:J$204,Allocation!$A$5:$A$204,$A137)) -> 0.5 | J137: =IF($A137="","",SUMIFS(Allocation!K$5:K$204,Allocation!$A$5:$A$204,$A137)) -> 0.5 | K137: =IF($A137="","",SUMIFS(Allocation!L$5:L$204,Allocation!$A$5:$A$204,$A137)) -> 0.5 | ... O137: =IF($A137="","",SUMIFS(Allocation!P$5:P$204,Allocation!$A$5:$A$204,$A137)) -> 0.5 | P137: =IF($A137="","",SUM(D137:O137)) -> 7.6
A138: =IF(Team!$A9="","",Team!$A9) -> QA Engineer 1 | B138: =IF(Team!$A9="","",Team!$B9) -> QA / SDET | C138: =IF(Team!$A9="","",Team!$C9) -> Contractor | D138: =IF($A138="","",SUMIFS(Allocation!E$5:E$204,Allocation!$A$5:$A$204,$A138)) -> 0.6 | E138: =IF($A138="","",SUMIFS(Allocation!F$5:F$204,Allocation!$A$5:$A$204,$A138)) -> 0.6 | F138: =IF($A138="","",SUMIFS(Allocation!G$5:G$204,Allocation!$A$5:$A$204,$A138)) -> 0.9 | G138: =IF($A138="","",SUMIFS(Allocation!H$5:H$204,Allocation!$A$5:$A$204,$A138)) -> 0.9 | H138: =IF($A138="","",SUMIFS(Allocation!I$5:I$204,Allocation!$A$5:$A$204,$A138)) -> 0.9 | I138: =IF($A138="","",SUMIFS(Allocation!J$5:J$204,Allocation!$A$5:$A$204,$A138)) -> 0.9 | J138: =IF($A138="","",SUMIFS(Allocation!K$5:K$204,Allocation!$A$5:$A$204,$A138)) -> 0.9 | K138: =IF($A138="","",SUMIFS(Allocation!L$5:L$204,Allocation!$A$5:$A$204,$A138)) -> 0.9 | ... O138: =IF($A138="","",SUMIFS(Allocation!P$5:P$204,Allocation!$A$5:$A$204,$A138)) -> 0.6 | P138: =IF($A138="","",SUM(D138:O138)) -> 9
A139: =IF(Team!$A10="","",Team!$A10) -> TBH Angular Dev | B139: =IF(Team!$A10="","",Team!$B10) -> Frontend Developer | C139: =IF(Team!$A10="","",Team!$C10) -> Open Req | D139: =IF($A139="","",SUMIFS(Allocation!E$5:E$204,Allocation!$A$5:$A$204,$A139)) -> 0 | E139: =IF($A139="","",SUMIFS(Allocation!F$5:F$204,Allocation!$A$5:$A$204,$A139)) -> 0 | F139: =IF($A139="","",SUMIFS(Allocation!G$5:G$204,Allocation!$A$5:$A$204,$A139)) -> 0 | G139: =IF($A139="","",SUMIFS(Allocation!H$5:H$204,Allocation!$A$5:$A$204,$A139)) -> 0.8 | H139: =IF($A139="","",SUMIFS(Allocation!I$5:I$204,Allocation!$A$5:$A$204,$A139)) -> 0.8 | I139: =IF($A139="","",SUMIFS(Allocation!J$5:J$204,Allocation!$A$5:$A$204,$A139)) -> 0.8 | J139: =IF($A139="","",SUMIFS(Allocation!K$5:K$204,Allocation!$A$5:$A$204,$A139)) -> 0.8 | K139: =IF($A139="","",SUMIFS(Allocation!L$5:L$204,Allocation!$A$5:$A$204,$A139)) -> 0.8 | ... O139: =IF($A139="","",SUMIFS(Allocation!P$5:P$204,Allocation!$A$5:$A$204,$A139)) -> 0.8 | P139: =IF($A139="","",SUM(D139:O139)) -> 7.2
A140: =IF(Team!$A11="","",Team!$A11) | B140: =IF(Team!$A11="","",Team!$B11) | C140: =IF(Team!$A11="","",Team!$C11) | D140: =IF($A140="","",SUMIFS(Allocation!E$5:E$204,Allocation!$A$5:$A$204,$A140)) | E140: =IF($A140="","",SUMIFS(Allocation!F$5:F$204,Allocation!$A$5:$A$204,$A140)) | F140: =IF($A140="","",SUMIFS(Allocation!G$5:G$204,Allocation!$A$5:$A$204,$A140)) | G140: =IF($A140="","",SUMIFS(Allocation!H$5:H$204,Allocation!$A$5:$A$204,$A140)) | H140: =IF($A140="","",SUMIFS(Allocation!I$5:I$204,Allocation!$A$5:$A$204,$A140)) | I140: =IF($A140="","",SUMIFS(Allocation!J$5:J$204,Allocation!$A$5:$A$204,$A140)) | J140: =IF($A140="","",SUMIFS(Allocation!K$5:K$204,Allocation!$A$5:$A$204,$A140)) | K140: =IF($A140="","",SUMIFS(Allocation!L$5:L$204,Allocation!$A$5:$A$204,$A140)) | ... O140: =IF($A140="","",SUMIFS(Allocation!P$5:P$204,Allocation!$A$5:$A$204,$A140)) | P140: =IF($A140="","",SUM(D140:O140))
A141: =IF(Team!$A12="","",Team!$A12) | B141: =IF(Team!$A12="","",Team!$B12) | C141: =IF(Team!$A12="","",Team!$C12) | D141: =IF($A141="","",SUMIFS(Allocation!E$5:E$204,Allocation!$A$5:$A$204,$A141)) | E141: =IF($A141="","",SUMIFS(Allocation!F$5:F$204,Allocation!$A$5:$A$204,$A141)) | F141: =IF($A141="","",SUMIFS(Allocation!G$5:G$204,Allocation!$A$5:$A$204,$A141)) | G141: =IF($A141="","",SUMIFS(Allocation!H$5:H$204,Allocation!$A$5:$A$204,$A141)) | H141: =IF($A141="","",SUMIFS(Allocation!I$5:I$204,Allocation!$A$5:$A$204,$A141)) | I141: =IF($A141="","",SUMIFS(Allocation!J$5:J$204,Allocation!$A$5:$A$204,$A141)) | J141: =IF($A141="","",SUMIFS(Allocation!K$5:K$204,Allocation!$A$5:$A$204,$A141)) | K141: =IF($A141="","",SUMIFS(Allocation!L$5:L$204,Allocation!$A$5:$A$204,$A141)) | ... O141: =IF($A141="","",SUMIFS(Allocation!P$5:P$204,Allocation!$A$5:$A$204,$A141)) | P141: =IF($A141="","",SUM(D141:O141))
A142: =IF(Team!$A13="","",Team!$A13) | B142: =IF(Team!$A13="","",Team!$B13) | C142: =IF(Team!$A13="","",Team!$C13) | D142: =IF($A142="","",SUMIFS(Allocation!E$5:E$204,Allocation!$A$5:$A$204,$A142)) | E142: =IF($A142="","",SUMIFS(Allocation!F$5:F$204,Allocation!$A$5:$A$204,$A142)) | F142: =IF($A142="","",SUMIFS(Allocation!G$5:G$204,Allocation!$A$5:$A$204,$A142)) | G142: =IF($A142="","",SUMIFS(Allocation!H$5:H$204,Allocation!$A$5:$A$204,$A142)) | H142: =IF($A142="","",SUMIFS(Allocation!I$5:I$204,Allocation!$A$5:$A$204,$A142)) | I142: =IF($A142="","",SUMIFS(Allocation!J$5:J$204,Allocation!$A$5:$A$204,$A142)) | J142: =IF($A142="","",SUMIFS(Allocation!K$5:K$204,Allocation!$A$5:$A$204,$A142)) | K142: =IF($A142="","",SUMIFS(Allocation!L$5:L$204,Allocation!$A$5:$A$204,$A142)) | ... O142: =IF($A142="","",SUMIFS(Allocation!P$5:P$204,Allocation!$A$5:$A$204,$A142)) | P142: =IF($A142="","",SUM(D142:O142))
A143: =IF(Team!$A14="","",Team!$A14) | B143: =IF(Team!$A14="","",Team!$B14) | C143: =IF(Team!$A14="","",Team!$C14) | D143: =IF($A143="","",SUMIFS(Allocation!E$5:E$204,Allocation!$A$5:$A$204,$A143)) | E143: =IF($A143="","",SUMIFS(Allocation!F$5:F$204,Allocation!$A$5:$A$204,$A143)) | F143: =IF($A143="","",SUMIFS(Allocation!G$5:G$204,Allocation!$A$5:$A$204,$A143)) | G143: =IF($A143="","",SUMIFS(Allocation!H$5:H$204,Allocation!$A$5:$A$204,$A143)) | H143: =IF($A143="","",SUMIFS(Allocation!I$5:I$204,Allocation!$A$5:$A$204,$A143)) | I143: =IF($A143="","",SUMIFS(Allocation!J$5:J$204,Allocation!$A$5:$A$204,$A143)) | J143: =IF($A143="","",SUMIFS(Allocation!K$5:K$204,Allocation!$A$5:$A$204,$A143)) | K143: =IF($A143="","",SUMIFS(Allocation!L$5:L$204,Allocation!$A$5:$A$204,$A143)) | ... O143: =IF($A143="","",SUMIFS(Allocation!P$5:P$204,Allocation!$A$5:$A$204,$A143)) | P143: =IF($A143="","",SUM(D143:O143))
A144: =IF(Team!$A15="","",Team!$A15) | B144: =IF(Team!$A15="","",Team!$B15) | C144: =IF(Team!$A15="","",Team!$C15) | D144: =IF($A144="","",SUMIFS(Allocation!E$5:E$204,Allocation!$A$5:$A$204,$A144)) | E144: =IF($A144="","",SUMIFS(Allocation!F$5:F$204,Allocation!$A$5:$A$204,$A144)) | F144: =IF($A144="","",SUMIFS(Allocation!G$5:G$204,Allocation!$A$5:$A$204,$A144)) | G144: =IF($A144="","",SUMIFS(Allocation!H$5:H$204,Allocation!$A$5:$A$204,$A144)) | H144: =IF($A144="","",SUMIFS(Allocation!I$5:I$204,Allocation!$A$5:$A$204,$A144)) | I144: =IF($A144="","",SUMIFS(Allocation!J$5:J$204,Allocation!$A$5:$A$204,$A144)) | J144: =IF($A144="","",SUMIFS(Allocation!K$5:K$204,Allocation!$A$5:$A$204,$A144)) | K144: =IF($A144="","",SUMIFS(Allocation!L$5:L$204,Allocation!$A$5:$A$204,$A144)) | ... O144: =IF($A144="","",SUMIFS(Allocation!P$5:P$204,Allocation!$A$5:$A$204,$A144)) | P144: =IF($A144="","",SUM(D144:O144))
A145: =IF(Team!$A16="","",Team!$A16) | B145: =IF(Team!$A16="","",Team!$B16) | C145: =IF(Team!$A16="","",Team!$C16) | D145: =IF($A145="","",SUMIFS(Allocation!E$5:E$204,Allocation!$A$5:$A$204,$A145)) | E145: =IF($A145="","",SUMIFS(Allocation!F$5:F$204,Allocation!$A$5:$A$204,$A145)) | F145: =IF($A145="","",SUMIFS(Allocation!G$5:G$204,Allocation!$A$5:$A$204,$A145)) | G145: =IF($A145="","",SUMIFS(Allocation!H$5:H$204,Allocation!$A$5:$A$204,$A145)) | H145: =IF($A145="","",SUMIFS(Allocation!I$5:I$204,Allocation!$A$5:$A$204,$A145)) | I145: =IF($A145="","",SUMIFS(Allocation!J$5:J$204,Allocation!$A$5:$A$204,$A145)) | J145: =IF($A145="","",SUMIFS(Allocation!K$5:K$204,Allocation!$A$5:$A$204,$A145)) | K145: =IF($A145="","",SUMIFS(Allocation!L$5:L$204,Allocation!$A$5:$A$204,$A145)) | ... O145: =IF($A145="","",SUMIFS(Allocation!P$5:P$204,Allocation!$A$5:$A$204,$A145)) | P145: =IF($A145="","",SUM(D145:O145))
... A193: =IF(Team!$A64="","",Team!$A64) | B193: =IF(Team!$A64="","",Team!$B64) | C193: =IF(Team!$A64="","",Team!$C64) | D193: =IF($A193="","",SUMIFS(Allocation!E$5:E$204,Allocation!$A$5:$A$204,$A193)) | E193: =IF($A193="","",SUMIFS(Allocation!F$5:F$204,Allocation!$A$5:$A$204,$A193)) | F193: =IF($A193="","",SUMIFS(Allocation!G$5:G$204,Allocation!$A$5:$A$204,$A193)) | G193: =IF($A193="","",SUMIFS(Allocation!H$5:H$204,Allocation!$A$5:$A$204,$A193)) | H193: =IF($A193="","",SUMIFS(Allocation!I$5:I$204,Allocation!$A$5:$A$204,$A193)) | I193: =IF($A193="","",SUMIFS(Allocation!J$5:J$204,Allocation!$A$5:$A$204,$A193)) | J193: =IF($A193="","",SUMIFS(Allocation!K$5:K$204,Allocation!$A$5:$A$204,$A193)) | K193: =IF($A193="","",SUMIFS(Allocation!L$5:L$204,Allocation!$A$5:$A$204,$A193)) | ... O193: =IF($A193="","",SUMIFS(Allocation!P$5:P$204,Allocation!$A$5:$A$204,$A193)) | P193: =IF($A193="","",SUM(D193:O193))

Sheet Milestones
A1: Milestones & Key Dates
A2: Releases, decision gates and dates you've committed to. They show as ◆ on the Roadmap.
A4: Project ID | B4: Project | C4: Milestone | D4: Target date | E4: Quarter | F4: Type | G4: Owner | H4: Status | I4: Notes
A5: P002 | B5: =IF(A5="","",IFERROR(INDEX(Projects!$B$5:$B$54,MATCH(A5,Projects!$A$5:$A$54,0)),"Unknown ID")) -> Application portfolio dashboard | C5: MVP dashboard to manager peers | D5: 46461 | E5: =IF(D5="","","Q"&ROUNDUP(MONTH(D5)/3,0)) -> Q1 | F5: Release | G5: Tech Lead 1 | H5: Not Started
A6: P001 | B6: =IF(A6="","",IFERROR(INDEX(Projects!$B$5:$B$54,MATCH(A6,Projects!$A$5:$A$54,0)),"Unknown ID")) -> RepApp Angular migration (strangler fig) | C6: Phase 1 screens live behind strangler proxy | D6: 46477 | E6: =IF(D6="","","Q"&ROUNDUP(MONTH(D6)/3,0)) -> Q1 | F6: Release | G6: Tech Lead 1 | H6: On Track
A7: P003 | B7: =IF(A7="","",IFERROR(INDEX(Projects!$B$5:$B$54,MATCH(A7,Projects!$A$5:$A$54,0)),"Unknown ID")) -> Observability & alerting uplift | C7: Alerting baseline in production | D7: 46568 | E7: =IF(D7="","","Q"&ROUNDUP(MONTH(D7)/3,0)) -> Q2 | F7: Milestone | G7: Java Dev 1 | H7: Not Started
A8: P001 | B8: =IF(A8="","",IFERROR(INDEX(Projects!$B$5:$B$54,MATCH(A8,Projects!$A$5:$A$54,0)),"Unknown ID")) -> RepApp Angular migration (strangler fig) | C8: Phase 2 screens live | D8: 46598 | E8: =IF(D8="","","Q"&ROUNDUP(MONTH(D8)/3,0)) -> Q3 | F8: Release | G8: Tech Lead 1 | H8: Not Started
A9: P001 | B9: =IF(A9="","",IFERROR(INDEX(Projects!$B$5:$B$54,MATCH(A9,Projects!$A$5:$A$54,0)),"Unknown ID")) -> RepApp Angular migration (strangler fig) | C9: Legacy JSP decommission decision | D9: 46706 | E9: =IF(D9="","","Q"&ROUNDUP(MONTH(D9)/3,0)) -> Q4 | F9: Decision Gate | G9: Siva | H9: Not Started
B10: =IF(A10="","",IFERROR(INDEX(Projects!$B$5:$B$54,MATCH(A10,Projects!$A$5:$A$54,0)),"Unknown ID")) | E10: =IF(D10="","","Q"&ROUNDUP(MONTH(D10)/3,0))
B11: =IF(A11="","",IFERROR(INDEX(Projects!$B$5:$B$54,MATCH(A11,Projects!$A$5:$A$54,0)),"Unknown ID")) | E11: =IF(D11="","","Q"&ROUNDUP(MONTH(D11)/3,0))
B12: =IF(A12="","",IFERROR(INDEX(Projects!$B$5:$B$54,MATCH(A12,Projects!$A$5:$A$54,0)),"Unknown ID")) | E12: =IF(D12="","","Q"&ROUNDUP(MONTH(D12)/3,0))
B13: =IF(A13="","",IFERROR(INDEX(Projects!$B$5:$B$54,MATCH(A13,Projects!$A$5:$A$54,0)),"Unknown ID")) | E13: =IF(D13="","","Q"&ROUNDUP(MONTH(D13)/3,0))
B14: =IF(A14="","",IFERROR(INDEX(Projects!$B$5:$B$54,MATCH(A14,Projects!$A$5:$A$54,0)),"Unknown ID")) | E14: =IF(D14="","","Q"&ROUNDUP(MONTH(D14)/3,0))
B15: =IF(A15="","",IFERROR(INDEX(Projects!$B$5:$B$54,MATCH(A15,Projects!$A$5:$A$54,0)),"Unknown ID")) | E15: =IF(D15="","","Q"&ROUNDUP(MONTH(D15)/3,0))
B16: =IF(A16="","",IFERROR(INDEX(Projects!$B$5:$B$54,MATCH(A16,Projects!$A$5:$A$54,0)),"Unknown ID")) | E16: =IF(D16="","","Q"&ROUNDUP(MONTH(D16)/3,0))
B17: =IF(A17="","",IFERROR(INDEX(Projects!$B$5:$B$54,MATCH(A17,Projects!$A$5:$A$54,0)),"Unknown ID")) | E17: =IF(D17="","","Q"&ROUNDUP(MONTH(D17)/3,0))
B18: =IF(A18="","",IFERROR(INDEX(Projects!$B$5:$B$54,MATCH(A18,Projects!$A$5:$A$54,0)),"Unknown ID")) | E18: =IF(D18="","","Q"&ROUNDUP(MONTH(D18)/3,0))
B19: =IF(A19="","",IFERROR(INDEX(Projects!$B$5:$B$54,MATCH(A19,Projects!$A$5:$A$54,0)),"Unknown ID")) | E19: =IF(D19="","","Q"&ROUNDUP(MONTH(D19)/3,0))
B20: =IF(A20="","",IFERROR(INDEX(Projects!$B$5:$B$54,MATCH(A20,Projects!$A$5:$A$54,0)),"Unknown ID")) | E20: =IF(D20="","","Q"&ROUNDUP(MONTH(D20)/3,0))
B21: =IF(A21="","",IFERROR(INDEX(Projects!$B$5:$B$54,MATCH(A21,Projects!$A$5:$A$54,0)),"Unknown ID")) | E21: =IF(D21="","","Q"&ROUNDUP(MONTH(D21)/3,0))
... B104: =IF(A104="","",IFERROR(INDEX(Projects!$B$5:$B$54,MATCH(A104,Projects!$A$5:$A$54,0)),"Unknown ID")) | E104: =IF(D104="","","Q"&ROUNDUP(MONTH(D104)/3,0))

Sheet RAID
A1: Risks, Assumptions, Issues & Dependencies
A2: Score = probability × impact (1–5 each). High ≥ 15, Medium ≥ 8.
A4: ID | B4: Type | C4: Project ID | D4: Description | E4: Probability (1-5) | F4: Impact (1-5) | G4: Score | H4: Severity | I4: Owner | J4: Mitigation / next step | K4: Due | L4: Status
A5: R001 | B5: Risk | C5: P001 | D5: Contractor roll-off or attrition slows Angular migration | E5: 3 | F5: 4 | G5: =IF(OR(E5="",F5=""),"",E5*F5) -> 12 | H5: =IF(G5="","",IF(G5>=15,"High",IF(G5>=8,"Medium","Low"))) -> Medium | I5: Siva | J5: Pair FTE with each contractor; document modules | K5: 46446 | L5: Open
A6: A001 | B6: Assumption | C6: P001 | D6: TBH Angular developer onboarded by April | E6: 3 | F6: 4 | G6: =IF(OR(E6="",F6=""),"",E6*F6) -> 12 | H6: =IF(G6="","",IF(G6>=15,"High",IF(G6>=8,"Medium","Low"))) -> Medium | I6: Siva | J6: Open req approved in Q4; backup: extend InRhythm SOW | K6: 46418 | L6: Open
A7: D001 | B7: Dependency | C7: P002 | D7: SNOW + Jira API access approved | E7: 3 | F7: 3 | G7: =IF(OR(E7="",F7=""),"",E7*F7) -> 9 | H7: =IF(G7="","",IF(G7>=15,"High",IF(G7>=8,"Medium","Low"))) -> Medium | I7: Tech Lead 1 | J7: Raise access request in January | K7: 46416 | L7: Open
G8: =IF(OR(E8="",F8=""),"",E8*F8) | H8: =IF(G8="","",IF(G8>=15,"High",IF(G8>=8,"Medium","Low")))
G9: =IF(OR(E9="",F9=""),"",E9*F9) | H9: =IF(G9="","",IF(G9>=15,"High",IF(G9>=8,"Medium","Low")))
G10: =IF(OR(E10="",F10=""),"",E10*F10) | H10: =IF(G10="","",IF(G10>=15,"High",IF(G10>=8,"Medium","Low")))
G11: =IF(OR(E11="",F11=""),"",E11*F11) | H11: =IF(G11="","",IF(G11>=15,"High",IF(G11>=8,"Medium","Low")))
G12: =IF(OR(E12="",F12=""),"",E12*F12) | H12: =IF(G12="","",IF(G12>=15,"High",IF(G12>=8,"Medium","Low")))
G13: =IF(OR(E13="",F13=""),"",E13*F13) | H13: =IF(G13="","",IF(G13>=15,"High",IF(G13>=8,"Medium","Low")))
G14: =IF(OR(E14="",F14=""),"",E14*F14) | H14: =IF(G14="","",IF(G14>=15,"High",IF(G14>=8,"Medium","Low")))
G15: =IF(OR(E15="",F15=""),"",E15*F15) | H15: =IF(G15="","",IF(G15>=15,"High",IF(G15>=8,"Medium","Low")))
G16: =IF(OR(E16="",F16=""),"",E16*F16) | H16: =IF(G16="","",IF(G16>=15,"High",IF(G16>=8,"Medium","Low")))
G17: =IF(OR(E17="",F17=""),"",E17*F17) | H17: =IF(G17="","",IF(G17>=15,"High",IF(G17>=8,"Medium","Low")))
G18: =IF(OR(E18="",F18=""),"",E18*F18) | H18: =IF(G18="","",IF(G18>=15,"High",IF(G18>=8,"Medium","Low")))
G19: =IF(OR(E19="",F19=""),"",E19*F19) | H19: =IF(G19="","",IF(G19>=15,"High",IF(G19>=8,"Medium","Low")))
... G104: =IF(OR(E104="",F104=""),"",E104*F104) | H104: =IF(G104="","",IF(G104>=15,"High",IF(G104>=8,"Medium","Low")))

Sheet Settings
A1: Settings & Lists
A2: Edit yellow cells. Lists feed every dropdown in the workbook — add/rename values here.
A3: Plan year | B3: 2027
A4: Default availability (focus factor) | B4: 0.85 | C4: Share of a person's time available for project work after meetings, support, admin. Used when Team availability is blank.
A7: Month start | B7: Working days | C7: Quarter | E7: Holiday date | F7: Holiday | H7: Project Status | I7: Priority | J7: Category | K7: Size | L7: RAG | M7: Resource Type | N7: Role | O7: RAID Type | P7: RAID Status | Q7: Milestone Status | R7: Milestone Type
A8: =DATE($B$3,1,1) -> 46388 | B8: =NETWORKDAYS(A8,EOMONTH(A8,0),$E$8:$E$30) -> 19 | C8: ="Q"&ROUNDUP(MONTH(A8)/3,0) -> Q1 | E8: 46388 | F8: New Year's Day | H8: Proposed | I8: P1 | J8: Run / KTLO | K8: S | L8: Green | M8: FTE | N8: Engineering Manager | O8: Risk | P8: Open | Q8: Not Started | R8: Milestone
A9: =DATE($B$3,2,1) -> 46419 | B9: =NETWORKDAYS(A9,EOMONTH(A9,0),$E$8:$E$30) -> 19 | C9: ="Q"&ROUNDUP(MONTH(A9)/3,0) -> Q1 | E9: 46405 | F9: MLK Day | H9: Approved | I9: P2 | J9: Grow | K9: M | L9: Amber | M9: Contractor | N9: Tech Lead | O9: Assumption | P9: Mitigating | Q9: On Track | R9: Release
A10: =DATE($B$3,3,1) -> 46447 | B10: =NETWORKDAYS(A10,EOMONTH(A10,0),$E$8:$E$30) -> 22 | C10: ="Q"&ROUNDUP(MONTH(A10)/3,0) -> Q1 | E10: 46433 | F10: Presidents' Day | H10: In Progress | I10: P3 | J10: Transform | K10: L | L10: Red | M10: Open Req | N10: Architect | O10: Issue | P10: Closed | Q10: At Risk | R10: Decision Gate
A11: =DATE($B$3,4,1) -> 46478 | B11: =NETWORKDAYS(A11,EOMONTH(A11,0),$E$8:$E$30) -> 22 | C11: ="Q"&ROUNDUP(MONTH(A11)/3,0) -> Q2 | E11: 46472 | F11: Good Friday | H11: On Hold | I11: P4 | J11: Compliance / Risk | K11: XL | N11: Backend Developer | O11: Dependency | Q11: Late | R11: Dependency Due
A12: =DATE($B$3,5,1) -> 46508 | B12: =NETWORKDAYS(A12,EOMONTH(A12,0),$E$8:$E$30) -> 20 | C12: ="Q"&ROUNDUP(MONTH(A12)/3,0) -> Q2 | E12: 46538 | F12: Memorial Day | H12: Done | J12: Tech Debt | N12: Frontend Developer | Q12: Done
A13: =DATE($B$3,6,1) -> 46539 | B13: =NETWORKDAYS(A13,EOMONTH(A13,0),$E$8:$E$30) -> 21 | C13: ="Q"&ROUNDUP(MONTH(A13)/3,0) -> Q2 | E13: 46556 | F13: Juneteenth (observed) | H13: Cancelled | N13: Full-stack Developer
A14: =DATE($B$3,7,1) -> 46569 | B14: =NETWORKDAYS(A14,EOMONTH(A14,0),$E$8:$E$30) -> 21 | C14: ="Q"&ROUNDUP(MONTH(A14)/3,0) -> Q3 | E14: 46573 | F14: Independence Day (observed) | N14: QA / SDET
A15: =DATE($B$3,8,1) -> 46600 | B15: =NETWORKDAYS(A15,EOMONTH(A15,0),$E$8:$E$30) -> 22 | C15: ="Q"&ROUNDUP(MONTH(A15)/3,0) -> Q3 | E15: 46636 | F15: Labor Day | N15: DevOps / SRE
A16: =DATE($B$3,9,1) -> 46631 | B16: =NETWORKDAYS(A16,EOMONTH(A16,0),$E$8:$E$30) -> 21 | C16: ="Q"&ROUNDUP(MONTH(A16)/3,0) -> Q3 | E16: 46716 | F16: Thanksgiving | N16: Business Analyst
A17: =DATE($B$3,10,1) -> 46661 | B17: =NETWORKDAYS(A17,EOMONTH(A17,0),$E$8:$E$30) -> 21 | C17: ="Q"&ROUNDUP(MONTH(A17)/3,0) -> Q4 | E17: 46717 | F17: Day after Thanksgiving | N17: Product Owner
A18: =DATE($B$3,11,1) -> 46692 | B18: =NETWORKDAYS(A18,EOMONTH(A18,0),$E$8:$E$30) -> 20 | C18: ="Q"&ROUNDUP(MONTH(A18)/3,0) -> Q4 | E18: 46745 | F18: Christmas (observed) | N18: Scrum Master
A19: =DATE($B$3,12,1) -> 46722 | B19: =NETWORKDAYS(A19,EOMONTH(A19,0),$E$8:$E$30) -> 22 | C19: ="Q"&ROUNDUP(MONTH(A19)/3,0) -> Q4 | N19: UX Designer
E31: Sample US 2027 dates — replace with your company holiday calendar.
